Workbook

Sheet Carpetas
A1: Cliente | B1: Carpeta
A2: Almacen Amc Sas | B2: AMC
A3: Central De Maderas G&S S.A.S. | B3: Central de maderas
A4: Centro Comercial Y Empresarial Obelisco - P.H.- | B4: Obelisco
A5: Centro Comercial Y Empresarial Savanna Plaza Propiedad Horizontal | B5: Savanna Plaza
A6: Condominio Acanto P. H | B6: Acanto
A7: Congregación De Religiosas Hijas De Cristo Rey | B7: Cristo Rey
A8: Conjunto Residencial San Esteban Del Poblado P.H. | B8: San Esteban
A9: Cooperativa Antioqueña De Salud | B9: coopsana ips
A10: Ecoimagen Salud S.A.S | B10: Ecoimagen ips
A11: Edificio Torre Almagran Propiedad Horizontal | B11: Almagran
A12: Instituto Bolivariano (Ibes) | B12: instituto bolivariano (ibes)
... A27: Minigranja Solar El Son | B27: 0015 El Son

Sheet Diciembre
A1: Proyecto | B1: CLIENTE | C1: Inversionista | D1: Documento contable | E1: Ciudad | F1: Concepto | G1: Total | H1: Factura | I1: Link Carpeta General | J1: Codigo | L1: Generar | M1: Proyecto | N1: Carpeta proyecto | O1: Factura | Q1: Fecha de Firma | R1: 46029 | S1: Fecha periodo | T1: 01 al 31 de diciembre del 2025 | U1: consecutivo final | V1: 287
A2: Almacen Amc Sas | B2: ALMACEN AMC SAS | C2: Total | D2: Mandato | E2: Sincelejo | F2: Ingreso Bruto | G2: =SUMIFS('Diciembre Data'!C:C,'Diciembre Data'!A:A,B2,'Diciembre Data'!B:B,F2) -> 3807241.5 | H2: =VLOOKUP(B2,'Diciembre Data'!A:D,4,FALSE) -> UESP1325 | I2: AMC | J2: =V1 -> 287 | L2: FALSE | M2: Almacen Amc Sas | N2: AMC
A3: Almacen Amc Sas | B3: ALMACEN AMC SAS | C3: total | D3: Mandato | E3: Sincelejo | F3: Interes | G3: =SUMIFS('Diciembre Data'!C:C,'Diciembre Data'!A:A,B3,'Diciembre Data'!B:B,F3) -> 108024.99 | H3: =VLOOKUP(B3,'Diciembre Data'!A:D,4,FALSE) -> UESP1325 | I3: AMC | L3: FALSE | M3: Arcillas San Simon S.A.S. | N3: Arcillas San Simón
A4: Almacen Amc Sas | B4: ALMACEN AMC SAS | C4: total | D4: Mandato | E4: Sincelejo | F4: Valor a Pagar | G4: =G2+G3 -> 3915266.5 | H4: =VLOOKUP(B4,'Diciembre Data'!A:D,4,FALSE) -> UESP1325 | L4: FALSE | M4: Central De Maderas G&S S.A.S. | N4: Central de maderas
A5: Almacen Amc Sas | B5: ALMACEN AMC SAS | C5: Factura | D5: Factura | E5: Sincelejo | F5: Administración | G5: =G4*5% -> 195763.32 | H5: =VLOOKUP(B5,'Diciembre Data'!A:D,4,FALSE) -> UESP1325 | I5: AMC | L5: FALSE | M5: Centro Comercial Y Empresarial Obelisco - P.H.- | N5: Obelisco
A6: Almacen Amc Sas | B6: ALMACEN AMC SAS | C6: Factura | D6: Factura | E6: Sincelejo | F6: Total | G6: =G5 -> 195763.32 | H6: =VLOOKUP(B6,'Diciembre Data'!A:D,4,FALSE) -> UESP1325 | I6: AMC
A7: Arcillas San Simon S.A.S. | B7: ARCILLAS SAN SIMON S.A.S. | C7: Total | D7: Mandato | E7: El Zulia | F7: Ingreso Bruto | G7: =SUMIFS('Diciembre Data'!C:C,'Diciembre Data'!A:A,B7,'Diciembre Data'!B:B,F7) -> 0 | H7: =VLOOKUP(B7,'Diciembre Data'!A:D,4,FALSE) -> #N/A | I7: Arcillas San Simón | J7: =J2+1 -> 288 | L7: FALSE | M7: Condominio Acanto P. H | N7: Acanto
A8: Arcillas San Simon S.A.S. | B8: ARCILLAS SAN SIMON S.A.S. | C8: total | D8: Mandato | E8: El Zulia | F8: Interes | G8: =SUMIFS('Diciembre Data'!C:C,'Diciembre Data'!A:A,B8,'Diciembre Data'!B:B,F8) -> 0 | H8: =VLOOKUP(B8,'Diciembre Data'!A:D,4,FALSE) -> #N/A | I8: Arcillas San Simón | L8: FALSE | M8: Congregación De Religiosas Hijas De Cristo Rey | N8: Cristo Rey
A9: Arcillas San Simon S.A.S. | B9: ARCILLAS SAN SIMON S.A.S. | C9: total | D9: Mandato | E9: El Zulia | F9: Valor a Pagar | G9: =G8+G7 -> 0 | H9: =VLOOKUP(B9,'Diciembre Data'!A:D,4,FALSE) -> #N/A | L9: FALSE | M9: Conjunto Laureles Campestre Etapas I Ii Y Iii Ph | N9: Laureles Campestre
A10: Arcillas San Simon S.A.S. | B10: ARCILLAS SAN SIMON S.A.S. | C10: Factura | D10: Factura | E10: El Zulia | F10: Administración | G10: =G9*5% -> 0 | H10: =VLOOKUP(B10,'Diciembre Data'!A:D,4,FALSE) -> #N/A | L10: FALSE | M10: Conjunto Residencial San Esteban Del Poblado P.H. | N10: San Esteban
A11: Arcillas San Simon S.A.S. | B11: ARCILLAS SAN SIMON S.A.S. | C11: Factura | D11: Factura | E11: El Zulia | F11: Total | G11: =G10 -> 0 | H11: =VLOOKUP(B11,'Diciembre Data'!A:D,4,FALSE) -> #N/A | L11: FALSE | M11: Cooperativa Antioqueña De Salud | N11: coopsana ips
A12: Central De Maderas G&S S.A.S. | B12: CENTRAL DE MADERAS G&S S.A.S. | C12: Total | D12: Mandato | E12: Turbaná | F12: Ingreso Bruto | G12: =SUMIFS('Diciembre Data'!C:C,'Diciembre Data'!A:A,B12,'Diciembre Data'!B:B,F12) -> 3356632.7 | H12: =VLOOKUP(B12,'Diciembre Data'!A:D,4,FALSE) -> UESP1334 | I12: Central de maderas | J12: =J2+1 -> 288 | L12: FALSE | M12: Dual Cross S.A.S | N12: Cross Bisnes center
A13: Central De Maderas G&S S.A.S. | B13: CENTRAL DE MADERAS G&S S.A.S. | C13: total | D13: Mandato | E13: Turbaná | F13: Interes | G13: =SUMIFS('Diciembre Data'!C:C,'Diciembre Data'!A:A,B13,'Diciembre Data'!B:B,F13) -> 56978.08 | H13: =VLOOKUP(B13,'Diciembre Data'!A:D,4,FALSE) -> UESP1334 | I13: Central de maderas | L13: FALSE | M13: Ecoimagen Salud S.A.S | N13: Ecoimagen ips
A14: Central De Maderas G&S S.A.S. | B14: CENTRAL DE MADERAS G&S S.A.S. | C14: total | D14: Mandato | F14: Retención en la fuente | G14: =(G12+G13)*4% -> 136544.43 | H14: =VLOOKUP(B14,'Diciembre Data'!A:D,4,FALSE) -> UESP1334 | L14: FALSE | M14: Edificio Torre Almagran Propiedad Horizontal | N14: Almagran
A15: Central De Maderas G&S S.A.S. | B15: CENTRAL DE MADERAS G&S S.A.S. | C15: total | D15: Mandato | E15: Turbaná | F15: Valor a Pagar | G15: =G12+G13-G14 -> 3277066.3 | H15: =VLOOKUP(B15,'Diciembre Data'!A:D,4,FALSE) -> UESP1334 | L15: FALSE | M15: Instituto Bolivariano (Ibes) | N15: instituto bolivariano (ibes)
A16: Central De Maderas G&S S.A.S. | B16: CENTRAL DE MADERAS G&S S.A.S. | C16: Factura | D16: Factura | E16: Turbaná | F16: Administración | G16: =G15*5% -> 163853.32 | H16: =VLOOKUP(B16,'Diciembre Data'!A:D,4,FALSE) -> UESP1334 | L16: FALSE | M16: Los Coches | N16: Hotel los coches
A17: Central De Maderas G&S S.A.S. | B17: CENTRAL DE MADERAS G&S S.A.S. | C17: Factura | D17: Factura | E17: Turbaná | F17: Total | G17: =G16 -> 163853.32 | H17: =VLOOKUP(B17,'Diciembre Data'!A:D,4,FALSE) -> UESP1334 | L17: FALSE | M17: M.D.M. Cientifica S.A.S | N17: MDM Cientifica
A18: Centro Comercial Y Empresarial Obelisco - P.H.- | B18: CENTRO COMERCIAL Y EMPRESARIAL OBELISCO - P.H.- | C18: Total | D18: Mandato | E18: Medellín | F18: Ingreso Bruto | G18: =SUMIFS('Diciembre Data'!C:C,'Diciembre Data'!A:A,B18,'Diciembre Data'!B:B,F18) -> 5394120.8 | H18: =VLOOKUP(B18,'Diciembre Data'!A:D,4,FALSE) -> UESP1327 | I18: Obelisco | J18: =J12+1 -> 289 | L18: FALSE | M18: Polikem S.A.S | N18: Polikem
A19: Centro Comercial Y Empresarial Obelisco - P.H.- | B19: CENTRO COMERCIAL Y EMPRESARIAL OBELISCO - P.H.- | C19: total | D19: Mandato | E19: Medellín | F19: Interes | G19: =SUMIFS('Diciembre Data'!C:C,'Diciembre Data'!A:A,B19,'Diciembre Data'!B:B,F19) -> 0 | H19: =VLOOKUP(B19,'Diciembre Data'!A:D,4,FALSE) -> UESP1327 | I19: Obelisco | L19: FALSE | M19: Servicios Industriales Y Metalmecanicos Sas | N19: Seridme
A20: Centro Comercial Y Empresarial Obelisco - P.H.- | B20: CENTRO COMERCIAL Y EMPRESARIAL OBELISCO - P.H.- | C20: total | D20: Mandato | E20: Medellín | F20: Valor a Pagar | G20: =G19+G18 -> 5394120.8 | H20: =VLOOKUP(B20,'Diciembre Data'!A:D,4,FALSE) -> UESP1327 | L20: FALSE | M20: Sociedad Educativa Ngs Sas | N20: NGS
A21: Centro Comercial Y Empresarial Obelisco - P.H.- | B21: CENTRO COMERCIAL Y EMPRESARIAL OBELISCO - P.H.- | C21: Factura | D21: Factura | F21: Administración | G21: =G20*5% -> 269706.04 | H21: =VLOOKUP(B21,'Diciembre Data'!A:D,4,FALSE) -> UESP1327 | L21: FALSE | M21: Sociedad Medica Rionegro S.A. Somer S.A. | N21: Clinica Somer
A22: Centro Comercial Y Empresarial Obelisco - P.H.- | B22: CENTRO COMERCIAL Y EMPRESARIAL OBELISCO - P.H.- | C22: Factura | D22: Factura | F22: Total | G22: =G21 -> 269706.04 | H22: =VLOOKUP(B22,'Diciembre Data'!A:D,4,FALSE) -> UESP1327 | L22: FALSE | M22: The Pub S. A. S. | N22: Pola Del Pub
L23: FALSE | M23: Urbanizacion Arboleda De Castilla Propiedad Horizontal | N23: arboleda de castilla
A29: Condominio Acanto P. H | B29: CONDOMINIO ACANTO Ρ. Η | C29: Total | D29: Mandato | E29: Envigado | F29: Ingreso Bruto | G29: =SUMIFS('Diciembre Data'!C:C,'Diciembre Data'!A:A,B29,'Diciembre Data'!B:B,F29) -> 4790049.8 | H29: =VLOOKUP(B29,'Diciembre Data'!A:D,4,FALSE) -> UESP1323 | I29: Acanto | J29: =J18+1 -> 290
A30: Condominio Acanto P. H | B30: CONDOMINIO ACANTO Ρ. Η | C30: total | D30: Mandato | E30: Envigado | F30: Interes | G30: =SUMIFS('Diciembre Data'!C:C,'Diciembre Data'!A:A,B30,'Diciembre Data'!B:B,F30) -> 0 | H30: =VLOOKUP(B30,'Diciembre Data'!A:D,4,FALSE) -> UESP1323 | I30: Acanto
A31: Condominio Acanto P. H | B31: CONDOMINIO ACANTO Ρ. Η | C31: total | D31: Mandato | E31: Envigado | F31: Valor a Pagar | G31: =G30+G29 -> 4790049.8 | H31: =VLOOKUP(B31,'Diciembre Data'!A:D,4,FALSE) -> UESP1323
A32: Condominio Acanto P. H | B32: CONDOMINIO ACANTO Ρ. Η | C32: Factura | D32: Factura | F32: Administración | G32: =G31*5% -> 239502.49 | H32: =VLOOKUP(B32,'Diciembre Data'!A:D,4,FALSE) -> UESP1323
A33: Condominio Acanto P. H | B33: CONDOMINIO ACANTO Ρ. Η | C33: Factura | D33: Factura | F33: Total | G33: =G32 -> 239502.49 | H33: =VLOOKUP(B33,'Diciembre Data'!A:D,4,FALSE) -> UESP1323
A34: Congregación De Religiosas Hijas De Cristo Rey | B34: CONGREGACIÓN DE RELIGIOSAS HIJAS DE CRISTO REY | C34: Total | D34: Mandato | E34: Bogotá, D.C. | F34: Ingreso Bruto | G34: =SUMIFS('Diciembre Data'!C:C,'Diciembre Data'!A:A,B34,'Diciembre Data'!B:B,F34) -> 2680876.5 | H34: =VLOOKUP(B34,'Diciembre Data'!A:D,4,FALSE) -> UESP1336 | I34: Cristo Rey | J34: =J29+1 -> 291
A35: Congregación De Religiosas Hijas De Cristo Rey | B35: CONGREGACIÓN DE RELIGIOSAS HIJAS DE CRISTO REY | C35: total | D35: Mandato | E35: Bogotá, D.C. | F35: Interes | G35: =SUMIFS('Diciembre Data'!C:C,'Diciembre Data'!A:A,B35,'Diciembre Data'!B:B,F35) -> 16521.27 | H35: =VLOOKUP(B35,'Diciembre Data'!A:D,4,FALSE) -> UESP1336 | I35: Cristo Rey
A36: Congregación De Religiosas Hijas De Cristo Rey | B36: CONGREGACIÓN DE RELIGIOSAS HIJAS DE CRISTO REY | C36: total | D36: Mandato | E36: Bogotá, D.C. | F36: Valor a Pagar | G36: =G35+G34 -> 2697397.8 | H36: =VLOOKUP(B36,'Diciembre Data'!A:D,4,FALSE) -> UESP1336
A37: Congregación De Religiosas Hijas De Cristo Rey | B37: CONGREGACIÓN DE RELIGIOSAS HIJAS DE CRISTO REY | C37: Factura | D37: Factura | F37: Administración | G37: =G36*5% -> 134869.89 | H37: =VLOOKUP(B37,'Diciembre Data'!A:D,4,FALSE) -> UESP1336
A38: Congregación De Religiosas Hijas De Cristo Rey | B38: CONGREGACIÓN DE RELIGIOSAS HIJAS DE CRISTO REY | C38: Factura | D38: Factura | F38: Total | G38: =G37 -> 134869.89 | H38: =VLOOKUP(B38,'Diciembre Data'!A:D,4,FALSE) -> UESP1336
A39: Conjunto Laureles Campestre Etapas I Ii Y Iii Ph | B39: CONJUNTO LAURELES CAMPESTRE ETAPAS I II Y III | C39: Total | D39: Mandato | E39: Medellín | F39: Ingreso Bruto | G39: =SUMIFS('Diciembre Data'!C:C,'Diciembre Data'!A:A,B39,'Diciembre Data'!B:B,F39) -> 12077510 | H39: =VLOOKUP(B39,'Diciembre Data'!A:D,4,FALSE) -> UESP1339 | I39: Laureles Campestre | J39: =J34+1 -> 292
A40: Conjunto Laureles Campestre Etapas I Ii Y Iii Ph | B40: CONJUNTO LAURELES CAMPESTRE ETAPAS I II Y III | C40: total | D40: Mandato | E40: Medellín | F40: Interes | G40: =SUMIFS('Diciembre Data'!C:C,'Diciembre Data'!A:A,B40,'Diciembre Data'!B:B,F40) -> 75767.13 | H40: =VLOOKUP(B40,'Diciembre Data'!A:D,4,FALSE) -> UESP1339 | I40: Laureles Campestre
A41: Conjunto Laureles Campestre Etapas I Ii Y Iii Ph | B41: CONJUNTO LAURELES CAMPESTRE ETAPAS I II Y III | C41: total | D41: Mandato | E41: Medellín | F41: Valor a Pagar | G41: =G40+G39 -> 12153277 | H41: =VLOOKUP(B41,'Diciembre Data'!A:D,4,FALSE) -> UESP1339
A42: Conjunto Laureles Campestre Etapas I Ii Y Iii Ph | B42: CONJUNTO LAURELES CAMPESTRE ETAPAS I II Y III | C42: Factura | D42: Factura | F42: Administración | G42: =G41*5% -> 607663.87 | H42: =VLOOKUP(B42,'Diciembre Data'!A:D,4,FALSE) -> UESP1339
A43: Conjunto Laureles Campestre Etapas I Ii Y Iii Ph | B43: CONJUNTO LAURELES CAMPESTRE ETAPAS I II Y III | C43: Factura | D43: Factura | F43: Total | G43: =G42 -> 607663.87 | H43: =VLOOKUP(B43,'Diciembre Data'!A:D,4,FALSE) -> UESP1339
A44: Conjunto Residencial San Esteban Del Poblado P.H. | B44: CONJUNTO RESIDENCIAL SAN ESTEBAN DEL POBLADO P.H. | C44: Total | D44: Mandato | E44: Medellín | F44: Ingreso Bruto | G44: =SUMIFS('Diciembre Data'!C:C,'Diciembre Data'!A:A,B44,'Diciembre Data'!B:B,F44) -> 1943033.4 | H44: =VLOOKUP(B44,'Diciembre Data'!A:D,4,FALSE) -> UESP1329 | I44: San Esteban | J44: =J39+1 -> 293
A45: Conjunto Residencial San Esteban Del Poblado P.H. | B45: CONJUNTO RESIDENCIAL SAN ESTEBAN DEL POBLADO P.H. | C45: total | D45: Mandato | E45: Medellín | F45: Interes | G45: =SUMIFS('Diciembre Data'!C:C,'Diciembre Data'!A:A,B45,'Diciembre Data'!B:B,F45) -> 0 | H45: =VLOOKUP(B45,'Diciembre Data'!A:D,4,FALSE) -> UESP1329 | I45: San Esteban
A46: Conjunto Residencial San Esteban Del Poblado P.H. | B46: CONJUNTO RESIDENCIAL SAN ESTEBAN DEL POBLADO P.H. | C46: total | D46: Mandato | E46: Medellín | F46: Valor a Pagar | G46: =G45+G44 -> 1943033.4 | H46: =VLOOKUP(B46,'Diciembre Data'!A:D,4,FALSE) -> UESP1329
A47: Conjunto Residencial San Esteban Del Poblado P.H. | B47: CONJUNTO RESIDENCIAL SAN ESTEBAN DEL POBLADO P.H. | C47: Factura | D47: Factura | F47: Administración | G47: =G46*5% -> 97151.671 | H47: =VLOOKUP(B47,'Diciembre Data'!A:D,4,FALSE) -> UESP1329
A48: Conjunto Residencial San Esteban Del Poblado P.H. | B48: CONJUNTO RESIDENCIAL SAN ESTEBAN DEL POBLADO P.H. | C48: Factura | D48: Factura | F48: Total | G48: =G47 -> 97151.671 | H48: =VLOOKUP(B48,'Diciembre Data'!A:D,4,FALSE) -> UESP1329
A49: Cooperativa Antioqueña De Salud | B49: COOPERATIVA ANTIOQUEÑA DE SALUD | C49: Total | D49: Mandato | E49: Medellín | F49: Ingreso Bruto | G49: =SUMIFS('Diciembre Data'!C:C,'Diciembre Data'!A:A,B49,'Diciembre Data'!B:B,F49) -> 2359601.9 | H49: =VLOOKUP(B49,'Diciembre Data'!A:D,4,FALSE) -> UESP1335 | I49: coopsana ips | J49: =J44+1 -> 294
A50: Cooperativa Antioqueña De Salud | B50: COOPERATIVA ANTIOQUEÑA DE SALUD | C50: Total | D50: Mandato | E50: Medellín | F50: Interes | G50: =SUMIFS('Diciembre Data'!C:C,'Diciembre Data'!A:A,B50,'Diciembre Data'!B:B,F50) -> 317112.94 | H50: =VLOOKUP(B50,'Diciembre Data'!A:D,4,FALSE) -> UESP1335 | I50: coopsana ips
A51: Cooperativa Antioqueña De Salud | B51: COOPERATIVA ANTIOQUEÑA DE SALUD | C51: Total | D51: Mandato | E51: Medellín | F51: Valor a Pagar | G51: =G50+G49 -> 2676714.8 | H51: =VLOOKUP(B51,'Diciembre Data'!A:D,4,FALSE) -> UESP1335
A52: Cooperativa Antioqueña De Salud | B52: COOPERATIVA ANTIOQUEÑA DE SALUD | C52: Factura | D52: Factura | F52: Administración | G52: =G51*5% -> 133835.74 | H52: =VLOOKUP(B52,'Diciembre Data'!A:D,4,FALSE) -> UESP1335
A53: Cooperativa Antioqueña De Salud | B53: COOPERATIVA ANTIOQUEÑA DE SALUD | C53: Factura | D53: Factura | F53: Total | G53: =G52 -> 133835.74 | H53: =VLOOKUP(B53,'Diciembre Data'!A:D,4,FALSE) -> UESP1335
A54: Dual Cross S.A.S | B54: DUAL CROSS S.A.S | C54: Total | D54: Mandato | E54: Medellín | F54: Ingreso Bruto | G54: =SUMIFS('Diciembre Data'!C:C,'Diciembre Data'!A:A,B54,'Diciembre Data'!B:B,F54) -> 2544083.6 | H54: =VLOOKUP(B54,'Diciembre Data'!A:D,4,FALSE) -> UESP1333 | I54: Cross Bisnes center | J54: =J49+1 -> 295
A55: Dual Cross S.A.S | B55: DUAL CROSS S.A.S | C55: total | D55: Mandato | E55: Medellín | F55: Interes | G55: =SUMIFS('Diciembre Data'!C:C,'Diciembre Data'!A:A,B55,'Diciembre Data'!B:B,F55) -> 44557.61 | H55: =VLOOKUP(B55,'Diciembre Data'!A:D,4,FALSE) -> UESP1333 | I55: Cross Bisnes center
A56: Dual Cross S.A.S | B56: DUAL CROSS S.A.S | C56: total | D56: Mandato | F56: Retención en la fuente | G56: =(G54+G55)*4% -> 103545.65 | H56: =VLOOKUP(B56,'Diciembre Data'!A:D,4,FALSE) -> UESP1333
A57: Dual Cross S.A.S | B57: DUAL CROSS S.A.S | C57: total | D57: Mandato | E57: Medellín | F57: Valor a Pagar | G57: =G54+G55-G56 -> 2485095.6 | H57: =VLOOKUP(B57,'Diciembre Data'!A:D,4,FALSE) -> UESP1333
A58: Dual Cross S.A.S | B58: DUAL CROSS S.A.S | C58: Factura | D58: Factura | F58: Administración | G58: =G57*5% -> 124254.78 | H58: =VLOOKUP(B58,'Diciembre Data'!A:D,4,FALSE) -> UESP1333
A59: Dual Cross S.A.S | B59: DUAL CROSS S.A.S | C59: Factura | D59: Factura | F59: Total | G59: =G58 -> 124254.78 | H59: =VLOOKUP(B59,'Diciembre Data'!A:D,4,FALSE) -> UESP1333
A60: Ecoimagen Salud S.A.S | B60: ECOIMAGEN SALUD S.A.S | C60: Total | D60: Mandato | E60: Cúcuta | F60: Ingreso Bruto | G60: =SUMIFS('Diciembre Data'!C:C,'Diciembre Data'!A:A,B60,'Diciembre Data'!B:B,F60) -> 1569583.4 | H60: =VLOOKUP(B60,'Diciembre Data'!A:D,4,FALSE) -> UESP1322 | I60: Ecoimagen ips | J60: =J54+1 -> 296
A61: Ecoimagen Salud S.A.S | B61: ECOIMAGEN SALUD S.A.S | C61: total | D61: Mandato | E61: Cúcuta | F61: Interes | G61: =SUMIFS('Diciembre Data'!C:C,'Diciembre Data'!A:A,B61,'Diciembre Data'!B:B,F61) -> 12999.13 | H61: =VLOOKUP(B61,'Diciembre Data'!A:D,4,FALSE) -> UESP1322 | I61: Ecoimagen ips
A62: Ecoimagen Salud S.A.S | B62: ECOIMAGEN SALUD S.A.S | C62: total | D62: Mandato | E62: Cúcuta | F62: Retención en la fuente | G62: =(G60+G61)*2.5% -> 39564.565 | H62: =VLOOKUP(B62,'Diciembre Data'!A:D,4,FALSE) -> UESP1322
A63: Ecoimagen Salud S.A.S | B63: ECOIMAGEN SALUD S.A.S | C63: total | D63: Mandato | E63: Cúcuta | F63: Valor a Pagar | G63: =G60+G61-G62 -> 1543018
A64: Ecoimagen Salud S.A.S | B64: ECOIMAGEN SALUD S.A.S | C64: Factura | D64: Factura | F64: Administración | G64: =G63*5% -> 77150.901 | H64: =VLOOKUP(B64,'Diciembre Data'!A:D,4,FALSE) -> UESP1322
A65: Ecoimagen Salud S.A.S | B65: ECOIMAGEN SALUD S.A.S | C65: Factura | D65: Factura | F65: Total | G65: =G64 -> 77150.901 | H65: =VLOOKUP(B65,'Diciembre Data'!A:D,4,FALSE) -> UESP1322
A66: Edificio Torre Almagran Propiedad Horizontal | B66: EDIFICIO TORRE ALMAGRAN PROPIEDAD HORIZONTAL | C66: Total | D66: Mandato | E66: Medellín | F66: Ingreso Bruto | G66: =SUMIFS('Diciembre Data'!C:C,'Diciembre Data'!A:A,B66,'Diciembre Data'!B:B,F66) -> 1626816.4 | H66: =VLOOKUP(B66,'Diciembre Data'!A:D,4,FALSE) -> UESP1324 | I66: Almagran | J66: =J60+1 -> 297
A67: Edificio Torre Almagran Propiedad Horizontal | B67: EDIFICIO TORRE ALMAGRAN PROPIEDAD HORIZONTAL | C67: total | D67: Mandato | E67: Medellín | F67: Interes | G67: =SUMIFS('Diciembre Data'!C:C,'Diciembre Data'!A:A,B67,'Diciembre Data'!B:B,F67) -> 0 | H67: =VLOOKUP(B67,'Diciembre Data'!A:D,4,FALSE) -> UESP1324 | I67: Almagran
A68: Edificio Torre Almagran Propiedad Horizontal | B68: EDIFICIO TORRE ALMAGRAN PROPIEDAD HORIZONTAL | C68: total | D68: Mandato | F68: Retención en la fuente | G68: =(G66+G67)*2.5% -> 40670.41 | H68: =VLOOKUP(B68,'Diciembre Data'!A:D,4,FALSE) -> UESP1324
A69: Edificio Torre Almagran Propiedad Horizontal | B69: EDIFICIO TORRE ALMAGRAN PROPIEDAD HORIZONTAL | C69: total | D69: Mandato | E69: Medellín | F69: Valor a Pagar | G69: =G66+G67-G68 -> 1586146 | H69: =VLOOKUP(B69,'Diciembre Data'!A:D,4,FALSE) -> UESP1324
A70: Edificio Torre Almagran Propiedad Horizontal | B70: EDIFICIO TORRE ALMAGRAN PROPIEDAD HORIZONTAL | C70: Factura | D70: Factura | F70: Administración | G70: =G69*5% -> 79307.299 | H70: =VLOOKUP(B70,'Diciembre Data'!A:D,4,FALSE) -> UESP1324
A71: Edificio Torre Almagran Propiedad Horizontal | B71: EDIFICIO TORRE ALMAGRAN PROPIEDAD HORIZONTAL | C71: Factura | D71: Factura | F71: Total | G71: =G70 -> 79307.299 | H71: =VLOOKUP(B71,'Diciembre Data'!A:D,4,FALSE) -> UESP1324
A72: Instituto Bolivariano (Ibes) | B72: CORREDOR NIÑO FRANK EDWIN | C72: Total | D72: Mandato | E72: Cúcuta | F72: Ingreso Bruto | G72: =SUMIFS('Diciembre Data'!C:C,'Diciembre Data'!A:A,B72,'Diciembre Data'!B:B,F72) -> 3011589.4 | H72: =VLOOKUP(B72,'Diciembre Data'!A:D,4,FALSE) -> UESP1326 | I72: instituto bolivariano (ibes) | J72: =J66+1 -> 298
A73: Instituto Bolivariano (Ibes) | B73: CORREDOR NIÑO FRANK EDWIN | C73: total | D73: Mandato | E73: Cúcuta | F73: Interes | G73: =SUMIFS('Diciembre Data'!C:C,'Diciembre Data'!A:A,B73,'Diciembre Data'!B:B,F73) -> 92079.71 | H73: =VLOOKUP(B73,'Diciembre Data'!A:D,4,FALSE) -> UESP1326 | I73: instituto bolivariano (ibes)
A74: Instituto Bolivariano (Ibes) | B74: CORREDOR NIÑO FRANK EDWIN | C74: total | D74: Mandato | E74: Cúcuta | F74: Valor a Pagar | G74: =G73+G72 -> 3103669.1 | H74: =VLOOKUP(B74,'Diciembre Data'!A:D,4,FALSE) -> UESP1326
A75: Instituto Bolivariano (Ibes) | B75: CORREDOR NIÑO FRANK EDWIN | C75: Factura | D75: Factura | F75: Administración | G75: =G74*5% -> 155183.46 | H75: =VLOOKUP(B75,'Diciembre Data'!A:D,4,FALSE) -> UESP1326
A76: Instituto Bolivariano (Ibes) | B76: CORREDOR NIÑO FRANK EDWIN | C76: Factura | D76: Factura | F76: Total | G76: =G75 -> 155183.46 | H76: =VLOOKUP(B76,'Diciembre Data'!A:D,4,FALSE) -> UESP1326
A77: Los Coches | B77: CORREA TOBON ALBERTO DE JESUS | C77: Total | D77: Mandato | E77: Montelíbano | F77: Ingreso Bruto | G77: =SUMIFS('Diciembre Data'!C:C,'Diciembre Data'!A:A,B77,'Diciembre Data'!B:B,F77) -> 2349990.6 | H77: =VLOOKUP(B77,'Diciembre Data'!A:D,4,FALSE) -> UESP1331 | I77: Hotel los coches | J77: =J72+1 -> 299
A78: Los Coches | B78: CORREA TOBON ALBERTO DE JESUS | C78: total | D78: Mandato | E78: Montelíbano | F78: Interes | G78: =SUMIFS('Diciembre Data'!C:C,'Diciembre Data'!A:A,B78,'Diciembre Data'!B:B,F78) -> 0 | H78: =VLOOKUP(B78,'Diciembre Data'!A:D,4,FALSE) -> UESP1331 | I78: Hotel los coches
A79: Los Coches | B79: CORREA TOBON ALBERTO DE JESUS | C79: total | D79: Mandato | E79: Montelíbano | F79: Valor a Pagar | G79: =G78+G77 -> 2349990.6 | H79: =VLOOKUP(B79,'Diciembre Data'!A:D,4,FALSE) -> UESP1331
A80: Los Coches | B80: CORREA TOBON ALBERTO DE JESUS | C80: Factura | D80: Factura | F80: Administración | G80: =G79*5% -> 117499.53 | H80: =VLOOKUP(B80,'Diciembre Data'!A:D,4,FALSE) -> UESP1331
A81: Los Coches | B81: CORREA TOBON ALBERTO DE JESUS | C81: Factura | D81: Factura | F81: Total | G81: =G80 -> 117499.53 | H81: =VLOOKUP(B81,'Diciembre Data'!A:D,4,FALSE) -> UESP1331
A82: M.D.M. Cientifica S.A.S | B82: M.D.M. CIENTIFICA S.A.S | C82: Total | D82: Mandato | E82: Medellín | F82: Ingreso Bruto | G82: =SUMIFS('Diciembre Data'!C:C,'Diciembre Data'!A:A,B82,'Diciembre Data'!B:B,F82) -> 0 | H82: =VLOOKUP(B82,'Diciembre Data'!A:D,4,FALSE) -> #N/A | I82: MDM Cientifica | J82: =J77+1 -> 300
A83: M.D.M. Cientifica S.A.S | B83: M.D.M. CIENTIFICA S.A.S | C83: total | D83: Mandato | E83: Medellín | F83: Interes | G83: =SUMIFS('Diciembre Data'!C:C,'Diciembre Data'!A:A,B83,'Diciembre Data'!B:B,F83) -> 0 | H83: =VLOOKUP(B83,'Diciembre Data'!A:D,4,FALSE) -> #N/A | I83: MDM Cientifica
A84: M.D.M. Cientifica S.A.S | B84: M.D.M. CIENTIFICA S.A.S | C84: total | D84: Mandato | F84: Retención en la fuente | G84: =(G82+G83)*2.5% -> 0 | H84: =VLOOKUP(B84,'Diciembre Data'!A:D,4,FALSE) -> #N/A
A85: M.D.M. Cientifica S.A.S | B85: M.D.M. CIENTIFICA S.A.S | C85: total | D85: Mandato | E85: Medellín | F85: Valor a Pagar | G85: =G82+G83-G84 -> 0 | H85: =VLOOKUP(B85,'Diciembre Data'!A:D,4,FALSE) -> #N/A
A86: M.D.M. Cientifica S.A.S | B86: M.D.M. CIENTIFICA S.A.S | C86: Factura | D86: Factura | F86: Administración | G86: =G85*5% -> 0 | H86: =VLOOKUP(B86,'Diciembre Data'!A:D,4,FALSE) -> #N/A
A87: M.D.M. Cientifica S.A.S | B87: M.D.M. CIENTIFICA S.A.S | C87: Factura | D87: Factura | F87: Total | G87: =G86 -> 0 | H87: =VLOOKUP(B87,'Diciembre Data'!A:D,4,FALSE) -> #N/A
A88: Polikem S.A.S | B88: POLIKEM S.A.S | C88: Total | D88: Mandato | E88: Rionegro | F88: Ingreso Bruto | G88: =SUMIFS('Diciembre Data'!C:C,'Diciembre Data'!A:A,B88,'Diciembre Data'!B:B,F88) -> 1023570.9 | H88: =VLOOKUP(B88,'Diciembre Data'!A:D,4,FALSE) -> UESP1328 | I88: Polikem | J88: =J77+1 -> 300
A89: Polikem S.A.S | B89: POLIKEM S.A.S | C89: total | D89: Mandato | E89: Rionegro | F89: Interes | G89: =SUMIFS('Diciembre Data'!C:C,'Diciembre Data'!A:A,B89,'Diciembre Data'!B:B,F89) -> 0 | H89: =VLOOKUP(B89,'Diciembre Data'!A:D,4,FALSE) -> UESP1328 | I89: Polikem
A90: Polikem S.A.S | B90: POLIKEM S.A.S | C90: total | D90: Mandato | F90: Retención en la fuente | G90: =(G88+G89)*4% -> 40942.834 | H90: =VLOOKUP(B90,'Diciembre Data'!A:D,4,FALSE) -> UESP1328
A91: Polikem S.A.S | B91: POLIKEM S.A.S | C91: total | D91: Mandato | F91: ICA | G91: =(G88+G89)*0.4% -> 4094.2834 | H91: =VLOOKUP(B91,'Diciembre Data'!A:D,4,FALSE) -> UESP1328
A92: Polikem S.A.S | B92: POLIKEM S.A.S | C92: total | D92: Mandato | E92: Rionegro | F92: Valor a Pagar | G92: =G88+G89-G90-G91 -> 978533.74 | H92: =VLOOKUP(B92,'Diciembre Data'!A:D,4,FALSE) -> UESP1328
A93: Polikem S.A.S | B93: POLIKEM S.A.S | C93: Factura | D93: Factura | F93: Administración | G93: =G92*5% -> 48926.687 | H93: =VLOOKUP(B93,'Diciembre Data'!A:D,4,FALSE) -> UESP1328
A94: Polikem S.A.S | B94: POLIKEM S.A.S | C94: Factura | D94: Factura | F94: Total | G94: =G93 -> 48926.687 | H94: =VLOOKUP(B94,'Diciembre Data'!A:D,4,FALSE) -> UESP1328
A95: Servicios Industriales Y Metalmecanicos Sas | B95: SERVICIOS INDUSTRIALES Y METALMECANICOS SAS | C95: Total | D95: Mandato | E95: Cartagena De Indias | F95: Ingreso Bruto | G95: =SUMIFS('Diciembre Data'!C:C,'Diciembre Data'!A:A,B95,'Diciembre Data'!B:B,F95) -> 3649095.5 | H95: =VLOOKUP(B95,'Diciembre Data'!A:D,4,FALSE) -> UESP1330 | I95: Seridme | J95: =J88+1 -> 301
A96: Servicios Industriales Y Metalmecanicos Sas | B96: SERVICIOS INDUSTRIALES Y METALMECANICOS SAS | C96: total | D96: Mandato | E96: Cartagena De Indias | F96: Interes | G96: =SUMIFS('Diciembre Data'!C:C,'Diciembre Data'!A:A,B96,'Diciembre Data'!B:B,F96) -> 0 | H96: =VLOOKUP(B96,'Diciembre Data'!A:D,4,FALSE) -> UESP1330 | I96: Seridme
A97: Servicios Industriales Y Metalmecanicos Sas | B97: SERVICIOS INDUSTRIALES Y METALMECANICOS SAS | C97: total | D97: Mandato | E97: Cartagena De Indias | F97: Valor a Pagar | G97: =G96+G95 -> 3649095.5 | H97: =VLOOKUP(B97,'Diciembre Data'!A:D,4,FALSE) -> UESP1330
A98: Servicios Industriales Y Metalmecanicos Sas | B98: SERVICIOS INDUSTRIALES Y METALMECANICOS SAS | C98: Factura | D98: Factura | F98: Administración | G98: =G97*5% -> 182454.78 | H98: =VLOOKUP(B98,'Diciembre Data'!A:D,4,FALSE) -> UESP1330
A99: Servicios Industriales Y Metalmecanicos Sas | B99: SERVICIOS INDUSTRIALES Y METALMECANICOS SAS | C99: Factura | D99: Factura | F99: Total | G99: =G98 -> 182454.78 | H99: =VLOOKUP(B99,'Diciembre Data'!A:D,4,FALSE) -> UESP1330
A100: Sociedad Educativa Ngs Sas | B100: SOCIEDAD EDUCATIVA NGS SAS | C100: Total | D100: Mandato | E100: Villavicencio | F100: Ingreso Bruto | G100: =SUMIFS('Diciembre Data'!C:C,'Diciembre Data'!A:A,B100,'Diciembre Data'!B:B,F100) -> 0 | H100: =VLOOKUP(B100,'Diciembre Data'!A:D,4,FALSE) -> #N/A | I100: NGS | J100: =J95+1 -> 302
A101: Sociedad Educativa Ngs Sas | B101: SOCIEDAD EDUCATIVA NGS SAS | C101: total | D101: Mandato | E101: Villavicencio | F101: Interes | G101: =SUMIFS('Diciembre Data'!C:C,'Diciembre Data'!A:A,B101,'Diciembre Data'!B:B,F101) -> 0 | H101: =VLOOKUP(B101,'Diciembre Data'!A:D,4,FALSE) -> #N/A | I101: NGS
A102: Sociedad Educativa Ngs Sas | B102: SOCIEDAD EDUCATIVA NGS SAS | C102: total | D102: Mandato | E102: Villavicencio | F102: Valor a Pagar | G102: =G101+G100 -> 0 | H102: =VLOOKUP(B102,'Diciembre Data'!A:D,4,FALSE) -> #N/A
A103: Sociedad Educativa Ngs Sas | B103: SOCIEDAD EDUCATIVA NGS SAS | C103: Factura | D103: Factura | F103: Administración | G103: =G102*5% -> 0 | H103: =VLOOKUP(B103,'Diciembre Data'!A:D,4,FALSE) -> #N/A
A104: Sociedad Educativa Ngs Sas | B104: SOCIEDAD EDUCATIVA NGS SAS | C104: Factura | D104: Factura | F104: Total | G104: =G103 -> 0 | H104: =VLOOKUP(B104,'Diciembre Data'!A:D,4,FALSE) -> #N/A
A105: Sociedad Medica Rionegro S.A. Somer S.A. | B105: SOCIEDAD MEDICA RIONEGRO S.A. SOMER S.A. | C105: Total | D105: Mandato | E105: Rionegro | F105: Ingreso Bruto | G105: =SUMIFS('Diciembre Data'!C:C,'Diciembre Data'!A:A,B105,'Diciembre Data'!B:B,F105) -> 9301995.2 | H105: =VLOOKUP(B105,'Diciembre Data'!A:D,4,FALSE) -> UESP1320 | I105: Clinica Somer | J105: =J95+1 -> 302
...

Sheet Diciembre Data
A1: Proyecto | B1: Concepto | C1: Total | D1: Factura
A2: SOCIEDAD MEDICA RIONEGRO S.A. SOMER S.A. | B2: Ingreso Bruto | C2: 9301995.2 | D2: UESP1320
A3: SOCIEDAD MEDICA RIONEGRO S.A. SOMER S.A. | B3: Interes | C3: 0 | D3: UESP1320
A4: SOCIEDAD MEDICA RIONEGRO S.A. SOMER S.A. | B4: Valor a Pagar | C4: 9301995.2 | D4: UESP1320
A5: URBANIZACION ARBOLEDA DE CASTILLA PROPIEDAD HORIZONTAL | B5: Ingreso Bruto | C5: 2721813.6 | D5: UESP1321
A6: URBANIZACION ARBOLEDA DE CASTILLA PROPIEDAD HORIZONTAL | B6: Interes | C6: 16447.24 | D6: UESP1321
A7: URBANIZACION ARBOLEDA DE CASTILLA PROPIEDAD HORIZONTAL | B7: Valor a Pagar | C7: 2738260.9 | D7: UESP1321
A8: ECOIMAGEN SALUD S.A.S | B8: Ingreso Bruto | C8: 1569583.4 | D8: UESP1322
A9: ECOIMAGEN SALUD S.A.S | B9: Interes | C9: 12999.13 | D9: UESP1322
A10: ECOIMAGEN SALUD S.A.S | B10: Valor a Pagar | C10: 1582582.6 | D10: UESP1322
A11: CONDOMINIO ACANTO Ρ. Η | B11: Ingreso Bruto | C11: 4790049.8 | D11: UESP1323
A12: CONDOMINIO ACANTO Ρ. Η | B12: Interes | C12: 0 | D12: UESP1323
A13: CONDOMINIO ACANTO Ρ. Η | B13: Valor a Pagar | C13: 4790049.8 | D13: UESP1323
... A60: CONJUNTO LAURELES CAMPESTRE ETAPAS I II Y III | B60: Interes | C60: 75767.13 | D60: UESP1339
A61: CONJUNTO LAURELES CAMPESTRE ETAPAS I II Y III | B61: Valor a Pagar | C61: =C59+C60 -> 12153277 | D61: UESP1339

Sheet Poliza
A1: Proyecto | C1: Inversionista | D1: Documento contable | E1: Ciudad | F1: Concepto | G1: Total | H1: Asiento contable | I1: Link Carpeta General | J1: Codigo | L1: Generar | M1: Proyecto | Q1: Fecha de Firma | R1: 45994 | S1: Fecha periodo | T1: 01 al 30 de noviembre del 2025 | U1: consecutivo final | V1: 527
A2: Arcillas San Simon S.A.S. | B2: ARCILLAS SAN SIMON S.A.S. | C2: Total | D2: Mandato | E2: El Zulia | F2: Poliza | G2: 1657631.9 | I2: Arcillas San Simón | J2: =V1 -> 527 | L2: TRUE | M2: Arcillas San Simon S.A.S.
A3: Arcillas San Simon S.A.S. | B3: ARCILLAS SAN SIMON S.A.S. | C3: Total | D3: Mandato | F3: IVA | G3: =G2*19% -> 314950.07 | L3: TRUE | M3: Centro Comercial Y Empresarial Obelisco - P.H.-
A4: Arcillas San Simon S.A.S. | B4: ARCILLAS SAN SIMON S.A.S. | C4: total | D4: Mandato | E4: El Zulia | F4: Valor a Pagar | G4: =G2+G3 -> 1972582 | L4: TRUE | M4: Centro Comercial Y Empresarial Savanna Plaza Propiedad Horizontal
A5: Centro Comercial Y Empresarial Obelisco - P.H.- | B5: CENTRO COMERCIAL Y EMPRESARIAL OBELISCO - P.H.- | C5: Total | D5: Mandato | E5: Medellín | F5: Poliza | G5: 1275226.9 | I5: Obelisco | J5: =J2+1 -> 528 | L5: TRUE | M5: Condominio Acanto P. H
A6: Centro Comercial Y Empresarial Obelisco - P.H.- | B6: CENTRO COMERCIAL Y EMPRESARIAL OBELISCO - P.H.- | C6: Total | D6: Mandato | F6: IVA | G6: =G5*19% -> 242293.11 | L6: TRUE | M6: Conjunto Residencial San Esteban Del Poblado P.H.
A7: Centro Comercial Y Empresarial Obelisco - P.H.- | B7: CENTRO COMERCIAL Y EMPRESARIAL OBELISCO - P.H.- | C7: total | D7: Mandato | E7: Medellín | F7: Valor a Pagar | G7: =G5+G6 -> 1517520 | L7: TRUE | M7: Cooperativa Antioqueña De Salud
A8: Centro Comercial Y Empresarial Savanna Plaza Propiedad Horizontal | B8: CENTRO COMERCIAL Y EMPRESARIAL SAVANNA PLAZA PROPIEDAD HORIZONTAL | C8: Total | D8: Mandato | E8: Rionegro | F8: Poliza | G8: 538967.23 | I8: Savanna Plaza | J8: =J5+1 -> 529 | L8: TRUE | M8: Dual Cross S.A.S
A9: Centro Comercial Y Empresarial Savanna Plaza Propiedad Horizontal | B9: CENTRO COMERCIAL Y EMPRESARIAL SAVANNA PLAZA PROPIEDAD HORIZONTAL | C9: Total | D9: Mandato | F9: IVA | G9: =G8*19% -> 102403.77 | L9: TRUE | M9: Ecoimagen Salud S.A.S
A10: Centro Comercial Y Empresarial Savanna Plaza Propiedad Horizontal | B10: CENTRO COMERCIAL Y EMPRESARIAL SAVANNA PLAZA PROPIEDAD HORIZONTAL | C10: total | D10: Mandato | E10: Rionegro | F10: Valor a Pagar | G10: =G8+G9 -> 641371 | L10: TRUE | M10: Edificio Torre Almagran Propiedad Horizontal
A11: Condominio Acanto P. H | B11: CONDOMINIO ACANTO Ρ. Η | C11: Total | D11: Mandato | E11: Envigado | F11: Poliza | G11: 1200235.3 | I11: Acanto | J11: =J8+1 -> 530 | L11: TRUE | M11: Los Coches
A12: Condominio Acanto P. H | B12: CONDOMINIO ACANTO Ρ. Η | C12: Total | D12: Mandato | F12: IVA | G12: =G11*19% -> 228044.71 | L12: TRUE | M12: M.D.M. Cientifica S.A.S
A13: Condominio Acanto P. H | B13: CONDOMINIO ACANTO Ρ. Η | C13: total | D13: Mandato | E13: Envigado | F13: Valor a Pagar | G13: =G11+G12 -> 1428280 | L13: TRUE | M13: Polikem S.A.S
A14: Conjunto Residencial San Esteban Del Poblado P.H. | B14: CONJUNTO RESIDENCIAL SAN ESTEBAN DEL POBLADO P.H. | C14: Total | D14: Mandato | E14: Medellín | F14: Poliza | G14: 689048.74 | I14: San Esteban | J14: =J11+1 -> 531 | L14: TRUE | M14: Servicios Industriales Y Metalmecanicos Sas
A15: Conjunto Residencial San Esteban Del Poblado P.H. | B15: CONJUNTO RESIDENCIAL SAN ESTEBAN DEL POBLADO P.H. | C15: Total | D15: Mandato | F15: IVA | G15: =G14*19% -> 130919.26 | L15: TRUE | M15: Sociedad Educativa Ngs Sas
A16: Conjunto Residencial San Esteban Del Poblado P.H. | B16: CONJUNTO RESIDENCIAL SAN ESTEBAN DEL POBLADO P.H. | C16: total | D16: Mandato | E16: Medellín | F16: Valor a Pagar | G16: =G15+G14 -> 819968 | L16: TRUE | M16: Sociedad Medica Rionegro S.A. Somer S.A.
A17: Cooperativa Antioqueña De Salud | B17: COOPERATIVA ANTIOQUEÑA DE SALUD | C17: Total | D17: Mandato | E17: Medellín | F17: Poliza | G17: 448324.37 | I17: coopsana ips | J17: =J14+1 -> 532 | L17: TRUE | M17: The Pub S. A. S.
A18: Cooperativa Antioqueña De Salud | B18: COOPERATIVA ANTIOQUEÑA DE SALUD | C18: Total | D18: Mandato | F18: IVA | G18: =G17*19% -> 85181.63 | L18: TRUE | M18: Gimnasio San Angelo
A19: Cooperativa Antioqueña De Salud | B19: COOPERATIVA ANTIOQUEÑA DE SALUD | C19: Total | D19: Mandato | E19: Medellín | F19: Valor a Pagar | G19: =G18+G17 -> 533506
A20: Dual Cross S.A.S | B20: DUAL CROSS S.A.S | C20: Total | D20: Mandato | E20: Medellín | F20: Poliza | G20: 680227.73 | I20: Cross Bisnes center | J20: =J17+1 -> 533
A21: Dual Cross S.A.S | B21: DUAL CROSS S.A.S | C21: Total | D21: Mandato | F21: IVA | G21: =G20*19% -> 129243.27
A22: Dual Cross S.A.S | B22: DUAL CROSS S.A.S | C22: total | D22: Mandato | E22: Medellín | F22: Valor a Pagar | G22: =G21+G20 -> 809471
A23: Ecoimagen Salud S.A.S | B23: ECOIMAGEN SALUD S.A.S | C23: Total | D23: Mandato | E23: Cúcuta | F23: Poliza | G23: 422515.97 | I23: Ecoimagen ips | J23: =J20+1 -> 534
A24: Ecoimagen Salud S.A.S | B24: ECOIMAGEN SALUD S.A.S | C24: Total | D24: Mandato | F24: IVA | G24: =G23*19% -> 80278.034
A25: Ecoimagen Salud S.A.S | B25: ECOIMAGEN SALUD S.A.S | C25: total | D25: Mandato | E25: Cúcuta | F25: Valor a Pagar | G25: =G24+G23 -> 502794
A26: Edificio Torre Almagran Propiedad Horizontal | B26: EDIFICIO TORRE ALMAGRAN PROPIEDAD HORIZONTAL | C26: Total | D26: Mandato | E26: Medellín | F26: Poliza | G26: 447405.04 | I26: Almagran | J26: =J23+1 -> 535
A27: Edificio Torre Almagran Propiedad Horizontal | B27: EDIFICIO TORRE ALMAGRAN PROPIEDAD HORIZONTAL | C27: Total | D27: Mandato | F27: IVA | G27: =G26*19% -> 85006.958
A28: Edificio Torre Almagran Propiedad Horizontal | B28: EDIFICIO TORRE ALMAGRAN PROPIEDAD HORIZONTAL | C28: total | D28: Mandato | E28: Medellín | F28: Valor a Pagar | G28: =G27+G26 -> 532412
A29: Los Coches | B29: CORREA TOBON ALBERTO DE JESUS | C29: Total | D29: Mandato | E29: Montelíbano | F29: Poliza | G29: 426730.25 | I29: Hotel los coches | J29: =J26+1 -> 536
A30: Los Coches | B30: CORREA TOBON ALBERTO DE JESUS | C30: Total | D30: Mandato | F30: IVA | G30: =G29*19% -> 81078.747
A31: Los Coches | B31: CORREA TOBON ALBERTO DE JESUS | C31: total | D31: Mandato | E31: Montelíbano | F31: Valor a Pagar | G31: =G30+G29 -> 507809
A32: M.D.M. Cientifica S.A.S | B32: M.D.M. CIENTIFICA S.A.S | C32: Total | D32: Mandato | E32: Medellín | F32: Poliza | G32: 625722.69 | I32: MDM Cientifica | J32: =J29+1 -> 537
A33: M.D.M. Cientifica S.A.S | B33: M.D.M. CIENTIFICA S.A.S | C33: Total | D33: Mandato | F33: IVA | G33: =G32*19% -> 118887.31
A34: M.D.M. Cientifica S.A.S | B34: M.D.M. CIENTIFICA S.A.S | C34: total | D34: Mandato | E34: Medellín | F34: Valor a Pagar | G34: =G33+G32 -> 744610
A35: Polikem S.A.S | B35: POLIKEM S.A.S | C35: Total | D35: Mandato | E35: Rionegro | F35: Poliza | G35: 433598.32 | I35: Polikem | J35: =J32+1 -> 538
A36: Polikem S.A.S | B36: POLIKEM S.A.S | C36: Total | D36: Mandato | F36: IVA | G36: =G35*19% -> 82383.681
A37: Polikem S.A.S | B37: POLIKEM S.A.S | C37: total | D37: Mandato | E37: Rionegro | F37: Valor a Pagar | G37: =G36+G35 -> 515982
A38: Servicios Industriales Y Metalmecanicos Sas | B38: SERVICIOS INDUSTRIALES Y METALMECANICOS SAS | C38: Total | D38: Mandato | E38: Cartagena De Indias | F38: Poliza | G38: 654646.22 | I38: Seridme | J38: =J35+1 -> 539
A39: Servicios Industriales Y Metalmecanicos Sas | B39: SERVICIOS INDUSTRIALES Y METALMECANICOS SAS | C39: Total | D39: Mandato | F39: IVA | G39: =G38*19% -> 124382.78
A40: Servicios Industriales Y Metalmecanicos Sas | B40: SERVICIOS INDUSTRIALES Y METALMECANICOS SAS | C40: total | D40: Mandato | E40: Cartagena De Indias | F40: Valor a Pagar | G40: =G39+G38 -> 779029
A41: Sociedad Educativa Ngs Sas | B41: SOCIEDAD EDUCATIVA NGS SAS | C41: Total | D41: Mandato | E41: Villavicencio | F41: Poliza | G41: 545614.29 | I41: NGS | J41: =J38+1 -> 540
A42: Sociedad Educativa Ngs Sas | B42: SOCIEDAD EDUCATIVA NGS SAS | C42: Total | D42: Mandato | F42: IVA | G42: =G41*19% -> 103666.72
A43: Sociedad Educativa Ngs Sas | B43: SOCIEDAD EDUCATIVA NGS SAS | C43: total | D43: Mandato | E43: Villavicencio | F43: Valor a Pagar | G43: =G42+G41 -> 649281.01
A44: Sociedad Medica Rionegro S.A. Somer S.A. | B44: SOCIEDAD MEDICA RIONEGRO S.A. SOMER S.A. | C44: Total | D44: Mandato | E44: Rionegro | F44: Poliza | G44: 3083524.4 | I44: Clinica Somer | J44: =J41+1 -> 541
A45: Sociedad Medica Rionegro S.A. Somer S.A. | B45: SOCIEDAD MEDICA RIONEGRO S.A. SOMER S.A. | C45: Total | D45: Mandato | F45: IVA | G45: =G44*19% -> 585869.63
A46: Sociedad Medica Rionegro S.A. Somer S.A. | B46: SOCIEDAD MEDICA RIONEGRO S.A. SOMER S.A. | C46: total | D46: Mandato | E46: Rionegro | F46: Valor a Pagar | G46: =G44+G45 -> 3669394
A47: The Pub S. A. S. | B47: THE PUB S. A. S. | C47: Total | D47: Mandato | E47: Tocancipá | F47: Poliza | G47: 1007583.2 | I47: Pola Del Pub | J47: =J44+1 -> 542
A48: The Pub S. A. S. | B48: THE PUB S. A. S. | C48: Total | D48: Mandato | F48: IVA | G48: =G47*19% -> 191440.81
A49: The Pub S. A. S. | B49: THE PUB S. A. S. | C49: total | D49: Mandato | E49: Tocancipá | F49: Valor a Pagar | G49: =G48+G47 -> 1199024
A50: Gimnasio San Angelo | C50: Total | D50: Mandato | E50: Tocancipá | F50: Poliza | G50: 983778.15 | J50: =J47+1 -> 543
A51: Gimnasio San Angelo | C51: Total | D51: Mandato | F51: IVA | G51: =G50*19% -> 186917.85
A52: Gimnasio San Angelo | B52: SOCIEDAD MEDICA RIONEGRO S.A. SOMER S.A. | C52: total | D52: Mandato | E52: Rionegro | F52: Valor a Pagar | G52: =G51+G50 -> 1170696

Sheet Enero
A1: Proyecto | B1: CLIENTE | C1: Inversionista | D1: Documento contable | E1: Ciudad | F1: Concepto | G1: Total | H1: Factura | I1: Link Carpeta General | J1: Codigo | L1: Generar | M1: Proyecto | N1: Carpeta proyecto | O1: Factura | Q1: Fecha de Firma | R1: 46057 | S1: Fecha periodo | T1: 01 al 31 de enero del 2025 | U1: consecutivo final | V1: 287
A2: Almacen Amc Sas | B2: ALMACEN AMC SAS | C2: Total | D2: Mandato | E2: Sincelejo | F2: Ingreso Bruto | G2: =SUMIFS('Enero Data'!C:C,'Enero Data'!A:A,B2,'Enero Data'!B:B,F2) -> 4095983.8 | H2: =VLOOKUP(B2,'Enero Data'!A:D,4,FALSE) -> UESP1422 | I2: AMC | J2: 405 | L2: FALSE | M2: Almacen Amc Sas | N2: AMC
A3: Almacen Amc Sas | B3: ALMACEN AMC SAS | C3: total | D3: Mandato | E3: Sincelejo | F3: Interes | G3: =SUMIFS('Enero Data'!C:C,'Enero Data'!A:A,B3,'Enero Data'!B:B,F3) -> 88460.21 | H3: =VLOOKUP(B3,'Enero Data'!A:D,4,FALSE) -> UESP1422 | I3: AMC | L3: FALSE | M3: Arcillas San Simon S.A.S. | N3: Arcillas San Simón
A4: Almacen Amc Sas | B4: ALMACEN AMC SAS | C4: total | D4: Mandato | E4: Sincelejo | F4: Valor a Pagar | G4: =G2+G3 -> 4184444 | H4: =VLOOKUP(B4,'Enero Data'!A:D,4,FALSE) -> UESP1422 | L4: FALSE | M4: Central De Maderas G&S S.A.S. | N4: Central de maderas
A5: Almacen Amc Sas | B5: ALMACEN AMC SAS | C5: Factura | D5: Factura | E5: Sincelejo | F5: Administración | G5: =G4*5% -> 209222.2 | H5: =VLOOKUP(B5,'Enero Data'!A:D,4,FALSE) -> UESP1422 | I5: AMC | L5: FALSE | M5: Centro Comercial Y Empresarial Obelisco - P.H.- | N5: Obelisco
A6: Almacen Amc Sas | B6: ALMACEN AMC SAS | C6: Factura | D6: Factura | E6: Sincelejo | F6: Total | G6: =G5 -> 209222.2 | H6: =VLOOKUP(B6,'Enero Data'!A:D,4,FALSE) -> UESP1422 | I6: AMC | L6: FALSE | M6: Condominio Acanto P. H | N6: Acanto
A7: Arcillas San Simon S.A.S. | B7: ARCILLAS SAN SIMON S.A.S. | C7: Total | D7: Mandato | E7: El Zulia | F7: Ingreso Bruto | G7: =SUMIFS('Enero Data'!C:C,'Enero Data'!A:A,B7,'Enero Data'!B:B,F7) -> 0 | H7: =VLOOKUP(B7,'Enero Data'!A:D,4,FALSE) -> #N/A | I7: Arcillas San Simón | J7: =J2 -> 405 | L7: FALSE | M7: Congregación De Religiosas Hijas De Cristo Rey | N7: Cristo Rey
A8: Arcillas San Simon S.A.S. | B8: ARCILLAS SAN SIMON S.A.S. | C8: total | D8: Mandato | E8: El Zulia | F8: Interes | G8: =SUMIFS('Enero Data'!C:C,'Enero Data'!A:A,B8,'Enero Data'!B:B,F8) -> 0 | H8: =VLOOKUP(B8,'Enero Data'!A:D,4,FALSE) -> #N/A | I8: Arcillas San Simón | L8: FALSE | M8: Conjunto Laureles Campestre Etapas I Ii Y Iii Ph | N8: Laureles Campestre
A9: Arcillas San Simon S.A.S. | B9: ARCILLAS SAN SIMON S.A.S. | C9: total | D9: Mandato | E9: El Zulia | F9: Valor a Pagar | G9: =G8+G7 -> 0 | H9: =VLOOKUP(B9,'Enero Data'!A:D,4,FALSE) -> #N/A | L9: FALSE | M9: Conjunto Residencial San Esteban Del Poblado P.H. | N9: San Esteban
A10: Arcillas San Simon S.A.S. | B10: ARCILLAS SAN SIMON S.A.S. | C10: Factura | D10: Factura | E10: El Zulia | F10: Administración | G10: =G9*5% -> 0 | H10: =VLOOKUP(B10,'Enero Data'!A:D,4,FALSE) -> #N/A | L10: FALSE | M10: Cooperativa Antioqueña De Salud | N10: coopsana ips
A11: Arcillas San Simon S.A.S. | B11: ARCILLAS SAN SIMON S.A.S. | C11: Factura | D11: Factura | E11: El Zulia | F11: Total | G11: =G10 -> 0 | H11: =VLOOKUP(B11,'Enero Data'!A:D,4,FALSE) -> #N/A | L11: FALSE | M11: Dual Cross S.A.S | N11: Cross Bisnes center
A12: Central De Maderas G&S S.A.S. | B12: CENTRAL DE MADERAS G&S S.A.S. | C12: Total | D12: Mandato | E12: Turbaná | F12: Ingreso Bruto | G12: =SUMIFS('Enero Data'!C:C,'Enero Data'!A:A,B12,'Enero Data'!B:B,F12) -> 2716852.4 | H12: =VLOOKUP(B12,'Enero Data'!A:D,4,FALSE) -> UESP1433 | I12: Central de maderas | J12: =J2+1 -> 406 | L12: FALSE | M12: Ecoimagen Salud S.A.S | N12: Ecoimagen ips
A13: Central De Maderas G&S S.A.S. | B13: CENTRAL DE MADERAS G&S S.A.S. | C13: total | D13: Mandato | E13: Turbaná | F13: Interes | G13: =SUMIFS('Enero Data'!C:C,'Enero Data'!A:A,B13,'Enero Data'!B:B,F13) -> 4102.6 | H13: =VLOOKUP(B13,'Enero Data'!A:D,4,FALSE) -> UESP1433 | I13: Central de maderas | L13: FALSE | M13: Edificio Torre Almagran Propiedad Horizontal | N13: Almagran
A14: Central De Maderas G&S S.A.S. | B14: CENTRAL DE MADERAS G&S S.A.S. | C14: total | D14: Mandato | F14: Retención en la fuente | G14: =(G12+G13)*4% -> 108838.2 | H14: =VLOOKUP(B14,'Enero Data'!A:D,4,FALSE) -> UESP1433 | L14: FALSE | M14: Instituto Bolivariano (Ibes) | N14: instituto bolivariano (ibes)
A15: Central De Maderas G&S S.A.S. | B15: CENTRAL DE MADERAS G&S S.A.S. | C15: total | D15: Mandato | E15: Turbaná | F15: Valor a Pagar | G15: =G12+G13-G14 -> 2612116.8 | H15: =VLOOKUP(B15,'Enero Data'!A:D,4,FALSE) -> UESP1433 | L15: FALSE | M15: Los Coches | N15: Hotel los coches
A16: Central De Maderas G&S S.A.S. | B16: CENTRAL DE MADERAS G&S S.A.S. | C16: Factura | D16: Factura | E16: Turbaná | F16: Administración | G16: =G15*5% -> 130605.84 | H16: =VLOOKUP(B16,'Enero Data'!A:D,4,FALSE) -> UESP1433 | L16: FALSE | M16: M.D.M. Cientifica S.A.S | N16: MDM Cientifica
A17: Central De Maderas G&S S.A.S. | B17: CENTRAL DE MADERAS G&S S.A.S. | C17: Factura | D17: Factura | E17: Turbaná | F17: Total | G17: =G16 -> 130605.84 | H17: =VLOOKUP(B17,'Enero Data'!A:D,4,FALSE) -> UESP1433 | L17: FALSE | M17: Polikem S.A.S | N17: Polikem
A18: Centro Comercial Y Empresarial Obelisco - P.H.- | B18: CENTRO COMERCIAL Y EMPRESARIAL OBELISCO -P.H.- | C18: Total | D18: Mandato | E18: Medellín | F18: Ingreso Bruto | G18: =SUMIFS('Enero Data'!C:C,'Enero Data'!A:A,B18,'Enero Data'!B:B,F18) -> 4906552.8 | H18: =VLOOKUP(B18,'Enero Data'!A:D,4,FALSE) -> UESP1424 | I18: Obelisco | J18: =J12+1 -> 407 | L18: FALSE | M18: Servicios Industriales Y Metalmecanicos Sas | N18: Seridme
A19: Centro Comercial Y Empresarial Obelisco - P.H.- | B19: CENTRO COMERCIAL Y EMPRESARIAL OBELISCO -P.H.- | C19: total | D19: Mandato | E19: Medellín | F19: Interes | G19: =SUMIFS('Enero Data'!C:C,'Enero Data'!A:A,B19,'Enero Data'!B:B,F19) -> 0 | H19: =VLOOKUP(B19,'Enero Data'!A:D,4,FALSE) -> UESP1424 | I19: Obelisco | L19: FALSE | M19: Sociedad Educativa Ngs Sas | N19: NGS
A20: Centro Comercial Y Empresarial Obelisco - P.H.- | B20: CENTRO COMERCIAL Y EMPRESARIAL OBELISCO -P.H.- | C20: total | D20: Mandato | E20: Medellín | F20: Valor a Pagar | G20: =G19+G18 -> 4906552.8 | H20: =VLOOKUP(B20,'Enero Data'!A:D,4,FALSE) -> UESP1424 | L20: TRUE | M20: Sociedad Medica Rionegro S.A. Somer S.A. | N20: Clinica Somer
A21: Centro Comercial Y Empresarial Obelisco - P.H.- | B21: CENTRO COMERCIAL Y EMPRESARIAL OBELISCO -P.H.- | C21: Factura | D21: Factura | F21: Administración | G21: =G20*5% -> 245327.64 | H21: =VLOOKUP(B21,'Enero Data'!A:D,4,FALSE) -> UESP1424 | L21: FALSE | M21: The Pub S. A. S. | N21: Pola Del Pub
A22: Centro Comercial Y Empresarial Obelisco - P.H.- | B22: CENTRO COMERCIAL Y EMPRESARIAL OBELISCO -P.H.- | C22: Factura | D22: Factura | F22: Total | G22: =G21 -> 245327.64 | H22: =VLOOKUP(B22,'Enero Data'!A:D,4,FALSE) -> UESP1424 | L22: TRUE | M22: Urbanizacion Arboleda De Castilla Propiedad Horizontal | N22: arboleda de castilla
A23: Condominio Acanto P. H | B23: CONDOMINIO ACANTO Ρ. Η | C23: Total | D23: Mandato | E23: Envigado | F23: Ingreso Bruto | G23: =SUMIFS('Enero Data'!C:C,'Enero Data'!A:A,B23,'Enero Data'!B:B,F23) -> 4209142.2 | H23: =VLOOKUP(B23,'Enero Data'!A:D,4,FALSE) -> UESP1420 | I23: Acanto | J23: =J18+1 -> 408
A24: Condominio Acanto P. H | B24: CONDOMINIO ACANTO Ρ. Η | C24: total | D24: Mandato | E24: Envigado | F24: Interes | G24: =SUMIFS('Enero Data'!C:C,'Enero Data'!A:A,B24,'Enero Data'!B:B,F24) -> 0 | H24: =VLOOKUP(B24,'Enero Data'!A:D,4,FALSE) -> UESP1420 | I24: Acanto
A25: Condominio Acanto P. H | B25: CONDOMINIO ACANTO Ρ. Η | C25: total | D25: Mandato | E25: Envigado | F25: Valor a Pagar | G25: =G24+G23 -> 4209142.2 | H25: =VLOOKUP(B25,'Enero Data'!A:D,4,FALSE) -> UESP1420
A26: Condominio Acanto P. H | B26: CONDOMINIO ACANTO Ρ. Η | C26: Factura | D26: Factura | F26: Administración | G26: =G25*5% -> 210457.11 | H26: =VLOOKUP(B26,'Enero Data'!A:D,4,FALSE) -> UESP1420
A27: Condominio Acanto P. H | B27: CONDOMINIO ACANTO Ρ. Η | C27: Factura | D27: Factura | F27: Total | G27: =G26 -> 210457.11 | H27: =VLOOKUP(B27,'Enero Data'!A:D,4,FALSE) -> UESP1420
A28: Congregación De Religiosas Hijas De Cristo Rey | B28: CONGREGACIÓN DE RELIGIOSAS HIJAS DE CRISTO REY | C28: Total | D28: Mandato | E28: Bogotá, D.C. | F28: Ingreso Bruto | G28: =SUMIFS('Enero Data'!C:C,'Enero Data'!A:A,B28,'Enero Data'!B:B,F28) -> 2372766.8 | H28: =VLOOKUP(B28,'Enero Data'!A:D,4,FALSE) -> UESP1416 | I28: Cristo Rey | J28: =J23+1 -> 409
A29: Congregación De Religiosas Hijas De Cristo Rey | B29: CONGREGACIÓN DE RELIGIOSAS HIJAS DE CRISTO REY | C29: total | D29: Mandato | E29: Bogotá, D.C. | F29: Interes | G29: =SUMIFS('Enero Data'!C:C,'Enero Data'!A:A,B29,'Enero Data'!B:B,F29) -> 32062.42 | H29: =VLOOKUP(B29,'Enero Data'!A:D,4,FALSE) -> UESP1416 | I29: Cristo Rey
A30: Congregación De Religiosas Hijas De Cristo Rey | B30: CONGREGACIÓN DE RELIGIOSAS HIJAS DE CRISTO REY | C30: total | D30: Mandato | E30: Bogotá, D.C. | F30: Valor a Pagar | G30: =G29+G28 -> 2404829.2 | H30: =VLOOKUP(B30,'Enero Data'!A:D,4,FALSE) -> UESP1416
A31: Congregación De Religiosas Hijas De Cristo Rey | B31: CONGREGACIÓN DE RELIGIOSAS HIJAS DE CRISTO REY | C31: Factura | D31: Factura | F31: Administración | G31: =G30*5% -> 120241.46 | H31: =VLOOKUP(B31,'Enero Data'!A:D,4,FALSE) -> UESP1416
A32: Congregación De Religiosas Hijas De Cristo Rey | B32: CONGREGACIÓN DE RELIGIOSAS HIJAS DE CRISTO REY | C32: Factura | D32: Factura | F32: Total | G32: =G31 -> 120241.46 | H32: =VLOOKUP(B32,'Enero Data'!A:D,4,FALSE) -> UESP1416
A33: Conjunto Laureles Campestre Etapas I Ii Y Iii Ph | B33: CONJUNTO LAURELES CAMPESTRE ETAPAS I II Y III | C33: Total | D33: Mandato | E33: Medellín | F33: Ingreso Bruto | G33: =SUMIFS('Enero Data'!C:C,'Enero Data'!A:A,B33,'Enero Data'!B:B,F33) -> 0 | H33: =VLOOKUP(B33,'Enero Data'!A:D,4,FALSE) -> #N/A | I33: Laureles Campestre | J33: =J28+1 -> 410
A34: Conjunto Laureles Campestre Etapas I Ii Y Iii Ph | B34: CONJUNTO LAURELES CAMPESTRE ETAPAS I II Y III | C34: total | D34: Mandato | E34: Medellín | F34: Interes | G34: =SUMIFS('Enero Data'!C:C,'Enero Data'!A:A,B34,'Enero Data'!B:B,F34) -> 0 | H34: =VLOOKUP(B34,'Enero Data'!A:D,4,FALSE) -> #N/A | I34: Laureles Campestre
A35: Conjunto Laureles Campestre Etapas I Ii Y Iii Ph | B35: CONJUNTO LAURELES CAMPESTRE ETAPAS I II Y III | C35: total | D35: Mandato | E35: Medellín | F35: Valor a Pagar | G35: =G34+G33 -> 0 | H35: =VLOOKUP(B35,'Enero Data'!A:D,4,FALSE) -> #N/A
A36: Conjunto Laureles Campestre Etapas I Ii Y Iii Ph | B36: CONJUNTO LAURELES CAMPESTRE ETAPAS I II Y III | C36: Factura | D36: Factura | F36: Administración | G36: =G35*5% -> 0 | H36: =VLOOKUP(B36,'Enero Data'!A:D,4,FALSE) -> #N/A
A37: Conjunto Laureles Campestre Etapas I Ii Y Iii Ph | B37: CONJUNTO LAURELES CAMPESTRE ETAPAS I II Y III | C37: Factura | D37: Factura | F37: Total | G37: =G36 -> 0 | H37: =VLOOKUP(B37,'Enero Data'!A:D,4,FALSE) -> #N/A
A38: Conjunto Residencial San Esteban Del Poblado P.H. | B38: CONJUNTO RESIDENCIAL SAN ESTEBAN DEL POBLADO P.H. | C38: Total | D38: Mandato | E38: Medellín | F38: Ingreso Bruto | G38: =SUMIFS('Enero Data'!C:C,'Enero Data'!A:A,B38,'Enero Data'!B:B,F38) -> 1516423.9 | H38: =VLOOKUP(B38,'Enero Data'!A:D,4,FALSE) -> UESP1430 | I38: San Esteban | J38: =J33+1 -> 411
A39: Conjunto Residencial San Esteban Del Poblado P.H. | B39: CONJUNTO RESIDENCIAL SAN ESTEBAN DEL POBLADO P.H. | C39: total | D39: Mandato | E39: Medellín | F39: Interes | G39: =SUMIFS('Enero Data'!C:C,'Enero Data'!A:A,B39,'Enero Data'!B:B,F39) -> 10686.82 | H39: =VLOOKUP(B39,'Enero Data'!A:D,4,FALSE) -> UESP1430 | I39: San Esteban
A40: Conjunto Residencial San Esteban Del Poblado P.H. | B40: CONJUNTO RESIDENCIAL SAN ESTEBAN DEL POBLADO P.H. | C40: total | D40: Mandato | E40: Medellín | F40: Valor a Pagar | G40: =G39+G38 -> 1527110.7 | H40: =VLOOKUP(B40,'Enero Data'!A:D,4,FALSE) -> UESP1430
A41: Conjunto Residencial San Esteban Del Poblado P.H. | B41: CONJUNTO RESIDENCIAL SAN ESTEBAN DEL POBLADO P.H. | C41: Factura | D41: Factura | F41: Administración | G41: =G40*5% -> 76355.535 | H41: =VLOOKUP(B41,'Enero Data'!A:D,4,FALSE) -> UESP1430
A42: Conjunto Residencial San Esteban Del Poblado P.H. | B42: CONJUNTO RESIDENCIAL SAN ESTEBAN DEL POBLADO P.H. | C42: Factura | D42: Factura | F42: Total | G42: =G41 -> 76355.535 | H42: =VLOOKUP(B42,'Enero Data'!A:D,4,FALSE) -> UESP1430
A43: Cooperativa Antioqueña De Salud | B43: COOPERATIVA ANTIOQUEÑA DE SALUD | C43: Total | D43: Mandato | E43: Medellín | F43: Ingreso Bruto | G43: =SUMIFS('Enero Data'!C:C,'Enero Data'!A:A,B43,'Enero Data'!B:B,F43) -> 2095940.3 | H43: =VLOOKUP(B43,'Enero Data'!A:D,4,FALSE) -> UESP1415 | I43: coopsana ips | J43: =J38+1 -> 412
A44: Cooperativa Antioqueña De Salud | B44: COOPERATIVA ANTIOQUEÑA DE SALUD | C44: Total | D44: Mandato | E44: Medellín | F44: Interes | G44: =SUMIFS('Enero Data'!C:C,'Enero Data'!A:A,B44,'Enero Data'!B:B,F44) -> 348261.03 | H44: =VLOOKUP(B44,'Enero Data'!A:D,4,FALSE) -> UESP1415 | I44: coopsana ips
A45: Cooperativa Antioqueña De Salud | B45: COOPERATIVA ANTIOQUEÑA DE SALUD | C45: Total | D45: Mandato | E45: Medellín | F45: Valor a Pagar | G45: =G44+G43 -> 2444201.3 | H45: =VLOOKUP(B45,'Enero Data'!A:D,4,FALSE) -> UESP1415
A46: Cooperativa Antioqueña De Salud | B46: COOPERATIVA ANTIOQUEÑA DE SALUD | C46: Factura | D46: Factura | F46: Administración | G46: =G45*5% -> 122210.07 | H46: =VLOOKUP(B46,'Enero Data'!A:D,4,FALSE) -> UESP1415
A47: Cooperativa Antioqueña De Salud | B47: COOPERATIVA ANTIOQUEÑA DE SALUD | C47: Factura | D47: Factura | F47: Total | G47: =G46 -> 122210.07 | H47: =VLOOKUP(B47,'Enero Data'!A:D,4,FALSE) -> UESP1415
A48: Dual Cross S.A.S | B48: DUAL CROSS S.A.S | C48: Total | D48: Mandato | E48: Medellín | F48: Ingreso Bruto | G48: =SUMIFS('Enero Data'!C:C,'Enero Data'!A:A,B48,'Enero Data'!B:B,F48) -> 2221685.1 | H48: =VLOOKUP(B48,'Enero Data'!A:D,4,FALSE) -> UESP1427 | I48: Cross Bisnes center | J48: =J43+1 -> 413
A49: Dual Cross S.A.S | B49: DUAL CROSS S.A.S | C49: total | D49: Mandato | E49: Medellín | F49: Interes | G49: =SUMIFS('Enero Data'!C:C,'Enero Data'!A:A,B49,'Enero Data'!B:B,F49) -> 15923.39 | H49: =VLOOKUP(B49,'Enero Data'!A:D,4,FALSE) -> UESP1427 | I49: Cross Bisnes center
A50: Dual Cross S.A.S | B50: DUAL CROSS S.A.S | C50: total | D50: Mandato | F50: Retención en la fuente | G50: =(G48+G49)*4% -> 89504.34 | H50: =VLOOKUP(B50,'Enero Data'!A:D,4,FALSE) -> UESP1427
A51: Dual Cross S.A.S | B51: DUAL CROSS S.A.S | C51: total | D51: Mandato | E51: Medellín | F51: Valor a Pagar | G51: =G48+G49-G50 -> 2148104.2 | H51: =VLOOKUP(B51,'Enero Data'!A:D,4,FALSE) -> UESP1427
A52: Dual Cross S.A.S | B52: DUAL CROSS S.A.S | C52: Factura | D52: Factura | F52: Administración | G52: =G51*5% -> 107405.21 | H52: =VLOOKUP(B52,'Enero Data'!A:D,4,FALSE) -> UESP1427
A53: Dual Cross S.A.S | B53: DUAL CROSS S.A.S | C53: Factura | D53: Factura | F53: Total | G53: =G52 -> 107405.21 | H53: =VLOOKUP(B53,'Enero Data'!A:D,4,FALSE) -> UESP1427
A54: Ecoimagen Salud S.A.S | B54: ECOIMAGEN SALUD S.A.S | C54: Total | D54: Mandato | E54: Cúcuta | F54: Ingreso Bruto | G54: =SUMIFS('Enero Data'!C:C,'Enero Data'!A:A,B54,'Enero Data'!B:B,F54) -> 1301979.6 | H54: =VLOOKUP(B54,'Enero Data'!A:D,4,FALSE) -> UESP1419 | I54: Ecoimagen ips | J54: =J48+1 -> 414
A55: Ecoimagen Salud S.A.S | B55: ECOIMAGEN SALUD S.A.S | C55: total | D55: Mandato | E55: Cúcuta | F55: Interes | G55: =SUMIFS('Enero Data'!C:C,'Enero Data'!A:A,B55,'Enero Data'!B:B,F55) -> 24394.91 | H55: =VLOOKUP(B55,'Enero Data'!A:D,4,FALSE) -> UESP1419 | I55: Ecoimagen ips
A56: Ecoimagen Salud S.A.S | B56: ECOIMAGEN SALUD S.A.S | C56: total | D56: Mandato | E56: Cúcuta | F56: Retención en la fuente | G56: =(G54+G55)*2.5% -> 33159.364 | H56: =VLOOKUP(B56,'Enero Data'!A:D,4,FALSE) -> UESP1419
A57: Ecoimagen Salud S.A.S | B57: ECOIMAGEN SALUD S.A.S | C57: total | D57: Mandato | E57: Cúcuta | F57: Valor a Pagar | G57: =G54+G55-G56 -> 1293215.2
A58: Ecoimagen Salud S.A.S | B58: ECOIMAGEN SALUD S.A.S | C58: Factura | D58: Factura | F58: Administración | G58: =G57*5% -> 64660.76 | H58: =VLOOKUP(B58,'Enero Data'!A:D,4,FALSE) -> UESP1419
A59: Ecoimagen Salud S.A.S | B59: ECOIMAGEN SALUD S.A.S | C59: Factura | D59: Factura | F59: Total | G59: =G58 -> 64660.76 | H59: =VLOOKUP(B59,'Enero Data'!A:D,4,FALSE) -> UESP1419
A60: Edificio Torre Almagran Propiedad Horizontal | B60: EDIFICIO TORRE ALMAGRAN PROPIEDAD HORIZONTAL | C60: Total | D60: Mandato | E60: Medellín | F60: Ingreso Bruto | G60: =SUMIFS('Enero Data'!C:C,'Enero Data'!A:A,B60,'Enero Data'!B:B,F60) -> 1484963.5 | H60: =VLOOKUP(B60,'Enero Data'!A:D,4,FALSE) -> UESP1421 | I60: Almagran | J60: =J54+1 -> 415
A61: Edificio Torre Almagran Propiedad Horizontal | B61: EDIFICIO TORRE ALMAGRAN PROPIEDAD HORIZONTAL | C61: total | D61: Mandato | E61: Medellín | F61: Interes | G61: =SUMIFS('Enero Data'!C:C,'Enero Data'!A:A,B61,'Enero Data'!B:B,F61) -> 1988.36 | H61: =VLOOKUP(B61,'Enero Data'!A:D,4,FALSE) -> UESP1421 | I61: Almagran
A62: Edificio Torre Almagran Propiedad Horizontal | B62: EDIFICIO TORRE ALMAGRAN PROPIEDAD HORIZONTAL | C62: total | D62: Mandato | F62: Retención en la fuente | G62: =(G60+G61)*2.5% -> 37173.796 | H62: =VLOOKUP(B62,'Enero Data'!A:D,4,FALSE) -> UESP1421
A63: Edificio Torre Almagran Propiedad Horizontal | B63: EDIFICIO TORRE ALMAGRAN PROPIEDAD HORIZONTAL | C63: total | D63: Mandato | E63: Medellín | F63: Valor a Pagar | G63: =G60+G61-G62 -> 1449778 | H63: =VLOOKUP(B63,'Enero Data'!A:D,4,FALSE) -> UESP1421
A64: Edificio Torre Almagran Propiedad Horizontal | B64: EDIFICIO TORRE ALMAGRAN PROPIEDAD HORIZONTAL | C64: Factura | D64: Factura | F64: Administración | G64: =G63*5% -> 72488.901 | H64: =VLOOKUP(B64,'Enero Data'!A:D,4,FALSE) -> UESP1421
A65: Edificio Torre Almagran Propiedad Horizontal | B65: EDIFICIO TORRE ALMAGRAN PROPIEDAD HORIZONTAL | C65: Factura | D65: Factura | F65: Total | G65: =G64 -> 72488.901 | H65: =VLOOKUP(B65,'Enero Data'!A:D,4,FALSE) -> UESP1421
A66: Instituto Bolivariano (Ibes) | B66: CORREDOR NIÑO FRANK EDWIN | C66: Total | D66: Mandato | E66: Cúcuta | F66: Ingreso Bruto | G66: =SUMIFS('Enero Data'!C:C,'Enero Data'!A:A,B66,'Enero Data'!B:B,F66) -> 2473635.1 | H66: =VLOOKUP(B66,'Enero Data'!A:D,4,FALSE) -> UESP1423 | I66: instituto bolivariano (ibes) | J66: =J60+1 -> 416
A67: Instituto Bolivariano (Ibes) | B67: CORREDOR NIÑO FRANK EDWIN | C67: total | D67: Mandato | E67: Cúcuta | F67: Interes | G67: =SUMIFS('Enero Data'!C:C,'Enero Data'!A:A,B67,'Enero Data'!B:B,F67) -> 18404.39 | H67: =VLOOKUP(B67,'Enero Data'!A:D,4,FALSE) -> UESP1423 | I67: instituto bolivariano (ibes)
A68: Instituto Bolivariano (Ibes) | B68: CORREDOR NIÑO FRANK EDWIN | C68: total | D68: Mandato | E68: Cúcuta | F68: Valor a Pagar | G68: =G67+G66 -> 2492039.5 | H68: =VLOOKUP(B68,'Enero Data'!A:D,4,FALSE) -> UESP1423
A69: Instituto Bolivariano (Ibes) | B69: CORREDOR NIÑO FRANK EDWIN | C69: Factura | D69: Factura | F69: Administración | G69: =G68*5% -> 124601.97 | H69: =VLOOKUP(B69,'Enero Data'!A:D,4,FALSE) -> UESP1423
A70: Instituto Bolivariano (Ibes) | B70: CORREDOR NIÑO FRANK EDWIN | C70: Factura | D70: Factura | F70: Total | G70: =G69 -> 124601.97 | H70: =VLOOKUP(B70,'Enero Data'!A:D,4,FALSE) -> UESP1423
A71: Los Coches | B71: CORREA TOBON ALBERTO DE JESUS | C71: Total | D71: Mandato | E71: Montelíbano | F71: Ingreso Bruto | G71: =SUMIFS('Enero Data'!C:C,'Enero Data'!A:A,B71,'Enero Data'!B:B,F71) -> 2361908.2 | H71: =VLOOKUP(B71,'Enero Data'!A:D,4,FALSE) -> UESP1425 | I71: Hotel los coches | J71: =J66+1 -> 417
A72: Los Coches | B72: CORREA TOBON ALBERTO DE JESUS | C72: total | D72: Mandato | E72: Montelíbano | F72: Interes | G72: =SUMIFS('Enero Data'!C:C,'Enero Data'!A:A,B72,'Enero Data'!B:B,F72) -> 0 | H72: =VLOOKUP(B72,'Enero Data'!A:D,4,FALSE) -> UESP1425 | I72: Hotel los coches
A73: Los Coches | B73: CORREA TOBON ALBERTO DE JESUS | C73: total | D73: Mandato | E73: Montelíbano | F73: Valor a Pagar | G73: =G72+G71 -> 2361908.2 | H73: =VLOOKUP(B73,'Enero Data'!A:D,4,FALSE) -> UESP1425
A74: Los Coches | B74: CORREA TOBON ALBERTO DE JESUS | C74: Factura | D74: Factura | F74: Administración | G74: =G73*5% -> 118095.41 | H74: =VLOOKUP(B74,'Enero Data'!A:D,4,FALSE) -> UESP1425
A75: Los Coches | B75: CORREA TOBON ALBERTO DE JESUS | C75: Factura | D75: Factura | F75: Total | G75: =G74 -> 118095.41 | H75: =VLOOKUP(B75,'Enero Data'!A:D,4,FALSE) -> UESP1425
A76: M.D.M. Cientifica S.A.S | B76: M.D.M. CIENTIFICA S.A.S | C76: Total | D76: Mandato | E76: Medellín | F76: Ingreso Bruto | G76: =SUMIFS('Enero Data'!C:C,'Enero Data'!A:A,B76,'Enero Data'!B:B,F76) -> 0 | H76: =VLOOKUP(B76,'Enero Data'!A:D,4,FALSE) -> #N/A | I76: MDM Cientifica | J76: =J71+1 -> 418
A77: M.D.M. Cientifica S.A.S | B77: M.D.M. CIENTIFICA S.A.S | C77: total | D77: Mandato | E77: Medellín | F77: Interes | G77: =SUMIFS('Enero Data'!C:C,'Enero Data'!A:A,B77,'Enero Data'!B:B,F77) -> 0 | H77: =VLOOKUP(B77,'Enero Data'!A:D,4,FALSE) -> #N/A | I77: MDM Cientifica
A78: M.D.M. Cientifica S.A.S | B78: M.D.M. CIENTIFICA S.A.S | C78: total | D78: Mandato | F78: Retención en la fuente | G78: =(G76+G77)*2.5% -> 0 | H78: =VLOOKUP(B78,'Enero Data'!A:D,4,FALSE) -> #N/A
A79: M.D.M. Cientifica S.A.S | B79: M.D.M. CIENTIFICA S.A.S | C79: total | D79: Mandato | E79: Medellín | F79: Valor a Pagar | G79: =G76+G77-G78 -> 0 | H79: =VLOOKUP(B79,'Enero Data'!A:D,4,FALSE) -> #N/A
A80: M.D.M. Cientifica S.A.S | B80: M.D.M. CIENTIFICA S.A.S | C80: Factura | D80: Factura | F80: Administración | G80: =G79*5% -> 0 | H80: =VLOOKUP(B80,'Enero Data'!A:D,4,FALSE) -> #N/A
A81: M.D.M. Cientifica S.A.S | B81: M.D.M. CIENTIFICA S.A.S | C81: Factura | D81: Factura | F81: Total | G81: =G80 -> 0 | H81: =VLOOKUP(B81,'Enero Data'!A:D,4,FALSE) -> #N/A
A82: Polikem S.A.S | B82: POLIKEM S.A.S | C82: Total | D82: Mandato | E82: Rionegro | F82: Ingreso Bruto | G82: =SUMIFS('Enero Data'!C:C,'Enero Data'!A:A,B82,'Enero Data'!B:B,F82) -> 2034790.1 | H82: =VLOOKUP(B82,'Enero Data'!A:D,4,FALSE) -> UESP1432 | I82: Polikem | J82: =J71+1 -> 418
A83: Polikem S.A.S | B83: POLIKEM S.A.S | C83: total | D83: Mandato | E83: Rionegro | F83: Interes | G83: =SUMIFS('Enero Data'!C:C,'Enero Data'!A:A,B83,'Enero Data'!B:B,F83) -> 625.52 | H83: =VLOOKUP(B83,'Enero Data'!A:D,4,FALSE) -> UESP1432 | I83: Polikem
A84: Polikem S.A.S | B84: POLIKEM S.A.S | C84: total | D84: Mandato | F84: Retención en la fuente | G84: =(G82+G83)*4% -> 81416.627 | H84: =VLOOKUP(B84,'Enero Data'!A:D,4,FALSE) -> UESP1432
A85: Polikem S.A.S | B85: POLIKEM S.A.S | C85: total | D85: Mandato | F85: ICA | G85: =(G82+G83)*0.4% -> 8141.6627 | H85: =VLOOKUP(B85,'Enero Data'!A:D,4,FALSE) -> UESP1432
A86: Polikem S.A.S | B86: POLIKEM S.A.S | C86: total | D86: Mandato | E86: Rionegro | F86: Valor a Pagar | G86: =G82+G83-G84-G85 -> 1945857.4 | H86: =VLOOKUP(B86,'Enero Data'!A:D,4,FALSE) -> UESP1432
A87: Polikem S.A.S | B87: POLIKEM S.A.S | C87: Factura | D87: Factura | F87: Administración | G87: =G86*5% -> 97292.869 | H87: =VLOOKUP(B87,'Enero Data'!A:D,4,FALSE) -> UESP1432
A88: Polikem S.A.S | B88: POLIKEM S.A.S | C88: Factura | D88: Factura | F88: Total | G88: =G87 -> 97292.869 | H88: =VLOOKUP(B88,'Enero Data'!A:D,4,FALSE) -> UESP1432
A89: Servicios Industriales Y Metalmecanicos Sas | B89: SERVICIOS INDUSTRIALES Y METALMECANICOS SAS | C89: Total | D89: Mandato | E89: Cartagena De Indias | F89: Ingreso Bruto | G89: =SUMIFS('Enero Data'!C:C,'Enero Data'!A:A,B89,'Enero Data'!B:B,F89) -> 3375148.4 | H89: =VLOOKUP(B89,'Enero Data'!A:D,4,FALSE) -> UESP1431 | I89: Seridme | J89: =J82+1 -> 419
A90: Servicios Industriales Y Metalmecanicos Sas | B90: SERVICIOS INDUSTRIALES Y METALMECANICOS SAS | C90: total | D90: Mandato | E90: Cartagena De Indias | F90: Interes | G90: =SUMIFS('Enero Data'!C:C,'Enero Data'!A:A,B90,'Enero Data'!B:B,F90) -> 0 | H90: =VLOOKUP(B90,'Enero Data'!A:D,4,FALSE) -> UESP1431 | I90: Seridme
A91: Servicios Industriales Y Metalmecanicos Sas | B91: SERVICIOS INDUSTRIALES Y METALMECANICOS SAS | C91: total | D91: Mandato | E91: Cartagena De Indias | F91: Valor a Pagar | G91: =G90+G89 -> 3375148.4 | H91: =VLOOKUP(B91,'Enero Data'!A:D,4,FALSE) -> UESP1431
A92: Servicios Industriales Y Metalmecanicos Sas | B92: SERVICIOS INDUSTRIALES Y METALMECANICOS SAS | C92: Factura | D92: Factura | F92: Administración | G92: =G91*5% -> 168757.42 | H92: =VLOOKUP(B92,'Enero Data'!A:D,4,FALSE) -> UESP1431
A93: Servicios Industriales Y Metalmecanicos Sas | B93: SERVICIOS INDUSTRIALES Y METALMECANICOS SAS | C93: Factura | D93: Factura | F93: Total | G93: =G92 -> 168757.42 | H93: =VLOOKUP(B93,'Enero Data'!A:D,4,FALSE) -> UESP1431
A94: Sociedad Educativa Ngs Sas | B94: SOCIEDAD EDUCATIVA NGS SAS | C94: Total | D94: Mandato | E94: Villavicencio | F94: Ingreso Bruto | G94: =SUMIFS('Enero Data'!C:C,'Enero Data'!A:A,B94,'Enero Data'!B:B,F94) -> 0 | H94: =VLOOKUP(B94,'Enero Data'!A:D,4,FALSE) -> #N/A | I94: NGS | J94: =J89 -> 419
A95: Sociedad Educativa Ngs Sas | B95: SOCIEDAD EDUCATIVA NGS SAS | C95: total | D95: Mandato | E95: Villavicencio | F95: Interes | G95: =SUMIFS('Enero Data'!C:C,'Enero Data'!A:A,B95,'Enero Data'!B:B,F95) -> 0 | H95: =VLOOKUP(B95,'Enero Data'!A:D,4,FALSE) -> #N/A | I95: NGS
A96: Sociedad Educativa Ngs Sas | B96: SOCIEDAD EDUCATIVA NGS SAS | C96: total | D96: Mandato | E96: Villavicencio | F96: Valor a Pagar | G96: =G95+G94 -> 0 | H96: =VLOOKUP(B96,'Enero Data'!A:D,4,FALSE) -> #N/A
A97: Sociedad Educativa Ngs Sas | B97: SOCIEDAD EDUCATIVA NGS SAS | C97: Factura | D97: Factura | F97: Administración | G97: =G96*5% -> 0 | H97: =VLOOKUP(B97,'Enero Data'!A:D,4,FALSE) -> #N/A
A98: Sociedad Educativa Ngs Sas | B98: SOCIEDAD EDUCATIVA NGS SAS | C98: Factura | D98: Factura | F98: Total | G98: =G97 -> 0 | H98: =VLOOKUP(B98,'Enero Data'!A:D,4,FALSE) -> #N/A
A99: Sociedad Medica Rionegro S.A. Somer S.A. | B99: SOCIEDAD MEDICA RIONEGRO S.A. SOMER S.A. | C99: Total | D99: Mandato | E99: Rionegro | F99: Ingreso Bruto | G99: =SUMIFS('Enero Data'!C:C,'Enero Data'!A:A,B99,'Enero Data'!B:B,F99) -> 11294700 | H99: =VLOOKUP(B99,'Enero Data'!A:D,4,FALSE) -> UESP1436 | I99: Clinica Somer | J99: =J89+1 -> 420
A100: Sociedad Medica Rionegro S.A. Somer S.A. | B100: SOCIEDAD MEDICA RIONEGRO S.A. SOMER S.A. | C100: total | D100: Mandato | E100: Rionegro | F100: Interes | G100: =SUMIFS('Enero Data'!C:C,'Enero Data'!A:A,B100,'Enero Data'!B:B,F100) -> 0 | H100: =VLOOKUP(B100,'Enero Data'!A:D,4,FALSE) -> UESP1436 | I100: Clinica Somer
...

Sheet Febrero
A1: Proyecto | B1: CLIENTE | C1: Inversionista | D1: Documento contable | E1: Ciudad | F1: Concepto | G1: Total | H1: Factura | I1: Link Carpeta General | J1: Codigo | L1: Generar | M1: Proyecto | N1: Carpeta proyecto | O1: Factura | Q1: Fecha de Firma | R1: 46092 | S1: Fecha periodo | T1: 01 al 28 de febrero del 2026 | U1: consecutivo final | V1: 522
A2: Almacen Amc Sas | B2: ALMACEN AMC SAS | C2: Total | D2: Mandato | E2: Sincelejo | F2: Ingreso Bruto | G2: =SUMIFS('Febrero Data'!C:C,'Febrero Data'!A:A,B2,'Febrero Data'!B:B,F2) -> 3765456 | H2: =VLOOKUP(B2,'Febrero Data'!A:D,4,FALSE) -> UESP1526 | I2: AMC | J2: =V1 -> 522 | L2: TRUE | M2: Almacen Amc Sas | N2: AMC
A3: Almacen Amc Sas | B3: ALMACEN AMC SAS | C3: total | D3: Mandato | E3: Sincelejo | F3: Interes | G3: =SUMIFS('Febrero Data'!C:C,'Febrero Data'!A:A,B3,'Febrero Data'!B:B,F3) -> 153874.2 | H3: =VLOOKUP(B3,'Febrero Data'!A:D,4,FALSE) -> UESP1526 | I3: AMC | L3: TRUE
A4: Almacen Amc Sas | B4: ALMACEN AMC SAS | C4: total | D4: Mandato | E4: Sincelejo | F4: Valor a Pagar | G4: =G2+G3 -> 3919330.2 | H4: =VLOOKUP(B4,'Febrero Data'!A:D,4,FALSE) -> UESP1526 | L4: TRUE | M4: Central De Maderas G&S S.A.S. | N4: Central de maderas
A5: Almacen Amc Sas | B5: ALMACEN AMC SAS | C5: Factura | D5: Factura | E5: Sincelejo | F5: Administración | G5: =G4*5% -> 195966.51 | H5: =VLOOKUP(B5,'Febrero Data'!A:D,4,FALSE) -> UESP1526 | I5: AMC | L5: TRUE | M5: Centro Comercial Y Empresarial Obelisco - P.H.- | N5: Obelisco
A6: Almacen Amc Sas | B6: ALMACEN AMC SAS | C6: Factura | D6: Factura | E6: Sincelejo | F6: Total | G6: =G5 -> 195966.51 | H6: =VLOOKUP(B6,'Febrero Data'!A:D,4,FALSE) -> UESP1526 | I6: AMC | L6: TRUE | M6: Condominio Acanto P. H | N6: Acanto
A7: Arcillas San Simon S.A.S. | B7: ARCILLAS SAN SIMON S.A.S. | C7: Total | D7: Mandato | E7: El Zulia | F7: Ingreso Bruto | G7: =SUMIFS('Febrero Data'!C:C,'Febrero Data'!A:A,B7,'Febrero Data'!B:B,F7) -> 0 | H7: =VLOOKUP(B7,'Febrero Data'!A:D,4,FALSE) -> #N/A | I7: Arcillas San Simón | J7: =J2 -> 522 | L7: TRUE
A8: Arcillas San Simon S.A.S. | B8: ARCILLAS SAN SIMON S.A.S. | C8: total | D8: Mandato | E8: El Zulia | F8: Interes | G8: =SUMIFS('Febrero Data'!C:C,'Febrero Data'!A:A,B8,'Febrero Data'!B:B,F8) -> 0 | H8: =VLOOKUP(B8,'Febrero Data'!A:D,4,FALSE) -> #N/A | I8: Arcillas San Simón | L8: TRUE
A9: Arcillas San Simon S.A.S. | B9: ARCILLAS SAN SIMON S.A.S. | C9: total | D9: Mandato | E9: El Zulia | F9: Valor a Pagar | G9: =G8+G7 -> 0 | H9: =VLOOKUP(B9,'Febrero Data'!A:D,4,FALSE) -> #N/A | L9: TRUE
A10: Arcillas San Simon S.A.S. | B10: ARCILLAS SAN SIMON S.A.S. | C10: Factura | D10: Factura | E10: El Zulia | F10: Administración | G10: =G9*5% -> 0 | H10: =VLOOKUP(B10,'Febrero Data'!A:D,4,FALSE) -> #N/A | L10: TRUE
A11: Arcillas San Simon S.A.S. | B11: ARCILLAS SAN SIMON S.A.S. | C11: Factura | D11: Factura | E11: El Zulia | F11: Total | G11: =G10 -> 0 | H11: =VLOOKUP(B11,'Febrero Data'!A:D,4,FALSE) -> #N/A | L11: TRUE
A12: Central De Maderas G&S S.A.S. | B12: CENTRAL DE MADERAS G&S S.A.S. | C12: Total | D12: Mandato | E12: Turbaná | F12: Ingreso Bruto | G12: =SUMIFS('Febrero Data'!C:C,'Febrero Data'!A:A,B12,'Febrero Data'!B:B,F12) -> 3089496 | H12: =VLOOKUP(B12,'Febrero Data'!A:D,4,FALSE) -> UESP1534 | I12: Central de maderas | J12: =J2+1 -> 523 | L12: TRUE | M12: Congregación De Religiosas Hijas De Cristo Rey | N12: Cristo Rey
A13: Central De Maderas G&S S.A.S. | B13: CENTRAL DE MADERAS G&S S.A.S. | C13: total | D13: Mandato | E13: Turbaná | F13: Interes | G13: =SUMIFS('Febrero Data'!C:C,'Febrero Data'!A:A,B13,'Febrero Data'!B:B,F13) -> 15425.21 | H13: =VLOOKUP(B13,'Febrero Data'!A:D,4,FALSE) -> UESP1534 | I13: Central de maderas | L13: TRUE | M13: Conjunto Laureles Campestre Etapas I Ii Y Iii Ph | N13: Laureles Campestre
A14: Central De Maderas G&S S.A.S. | B14: CENTRAL DE MADERAS G&S S.A.S. | C14: total | D14: Mandato | F14: Retención en la fuente | G14: =(G12+G13)*4% -> 124196.85 | H14: =VLOOKUP(B14,'Febrero Data'!A:D,4,FALSE) -> UESP1534 | L14: TRUE | M14: Conjunto Residencial San Esteban Del Poblado P.H. | N14: San Esteban
A15: Central De Maderas G&S S.A.S. | B15: CENTRAL DE MADERAS G&S S.A.S. | C15: total | D15: Mandato | E15: Turbaná | F15: Valor a Pagar | G15: =G12+G13-G14 -> 2980724.4 | H15: =VLOOKUP(B15,'Febrero Data'!A:D,4,FALSE) -> UESP1534 | L15: TRUE | M15: Cooperativa Antioqueña De Salud | N15: coopsana ips
A16: Central De Maderas G&S S.A.S. | B16: CENTRAL DE MADERAS G&S S.A.S. | C16: Factura | D16: Factura | E16: Turbaná | F16: Administración | G16: =G15*5% -> 149036.22 | H16: =VLOOKUP(B16,'Febrero Data'!A:D,4,FALSE) -> UESP1534 | L16: TRUE | M16: Dual Cross S.A.S | N16: Cross Bisnes center
A17: Central De Maderas G&S S.A.S. | B17: CENTRAL DE MADERAS G&S S.A.S. | C17: Factura | D17: Factura | E17: Turbaná | F17: Total | G17: =G16 -> 149036.22 | H17: =VLOOKUP(B17,'Febrero Data'!A:D,4,FALSE) -> UESP1534 | L17: TRUE | M17: Ecoimagen Salud S.A.S | N17: Ecoimagen ips
A18: Centro Comercial Y Empresarial Obelisco - P.H.- | B18: CENTRO COMERCIAL Y EMPRESARIAL OBELISCO - P.H.- | C18: Total | D18: Mandato | E18: Medellín | F18: Ingreso Bruto | G18: =SUMIFS('Febrero Data'!C:C,'Febrero Data'!A:A,B18,'Febrero Data'!B:B,F18) -> 4884847 | H18: =VLOOKUP(B18,'Febrero Data'!A:D,4,FALSE) -> UESP1528 | I18: Obelisco | J18: =J12+1 -> 524 | L18: TRUE | M18: Edificio Torre Almagran Propiedad Horizontal | N18: Almagran
A19: Centro Comercial Y Empresarial Obelisco - P.H.- | B19: CENTRO COMERCIAL Y EMPRESARIAL OBELISCO - P.H.- | C19: total | D19: Mandato | E19: Medellín | F19: Interes | G19: =SUMIFS('Febrero Data'!C:C,'Febrero Data'!A:A,B19,'Febrero Data'!B:B,F19) -> 3515.89 | H19: =VLOOKUP(B19,'Febrero Data'!A:D,4,FALSE) -> UESP1528 | I19: Obelisco | L19: TRUE | M19: Instituto Bolivariano (Ibes) | N19: instituto bolivariano (ibes)
A20: Centro Comercial Y Empresarial Obelisco - P.H.- | B20: CENTRO COMERCIAL Y EMPRESARIAL OBELISCO - P.H.- | C20: total | D20: Mandato | E20: Medellín | F20: Valor a Pagar | G20: =G19+G18 -> 4888362.9 | H20: =VLOOKUP(B20,'Febrero Data'!A:D,4,FALSE) -> UESP1528 | L20: TRUE | M20: Los Coches | N20: Hotel los coches
A21: Centro Comercial Y Empresarial Obelisco - P.H.- | B21: CENTRO COMERCIAL Y EMPRESARIAL OBELISCO - P.H.- | C21: Factura | D21: Factura | F21: Administración | G21: =G20*5% -> 244418.14 | H21: =VLOOKUP(B21,'Febrero Data'!A:D,4,FALSE) -> UESP1528 | L21: TRUE | M21: M.D.M. Cientifica S.A.S | N21: MDM Cientifica
A22: Centro Comercial Y Empresarial Obelisco - P.H.- | B22: CENTRO COMERCIAL Y EMPRESARIAL OBELISCO - P.H.- | C22: Factura | D22: Factura | F22: Total | G22: =G21 -> 244418.14 | H22: =VLOOKUP(B22,'Febrero Data'!A:D,4,FALSE) -> UESP1528 | L22: TRUE | M22: Polikem S.A.S | N22: Polikem
A23: Condominio Acanto P. H | B23: CONDOMINIO ACANTO Ρ. Η | C23: Total | D23: Mandato | E23: Envigado | F23: Ingreso Bruto | G23: =SUMIFS('Febrero Data'!C:C,'Febrero Data'!A:A,B23,'Febrero Data'!B:B,F23) -> 4271092 | H23: =VLOOKUP(B23,'Febrero Data'!A:D,4,FALSE) -> UESP1524 | I23: Acanto | J23: =J18+1 -> 525 | L23: TRUE | M23: Servicios Industriales Y Metalmecanicos Sas | N23: Seridme
A24: Condominio Acanto P. H | B24: CONDOMINIO ACANTO Ρ. Η | C24: total | D24: Mandato | E24: Envigado | F24: Interes | G24: =SUMIFS('Febrero Data'!C:C,'Febrero Data'!A:A,B24,'Febrero Data'!B:B,F24) -> 0 | H24: =VLOOKUP(B24,'Febrero Data'!A:D,4,FALSE) -> UESP1524 | I24: Acanto | L24: TRUE | M24: Sociedad Educativa Ngs Sas | N24: NGS
A25: Condominio Acanto P. H | B25: CONDOMINIO ACANTO Ρ. Η | C25: total | D25: Mandato | E25: Envigado | F25: Valor a Pagar | G25: =G24+G23 -> 4271092 | H25: =VLOOKUP(B25,'Febrero Data'!A:D,4,FALSE) -> UESP1524 | L25: TRUE | M25: Sociedad Medica Rionegro S.A. Somer S.A. | N25: Clinica Somer
A26: Condominio Acanto P. H | B26: CONDOMINIO ACANTO Ρ. Η | C26: Factura | D26: Factura | F26: Administración | G26: =G25*5% -> 213554.6 | H26: =VLOOKUP(B26,'Febrero Data'!A:D,4,FALSE) -> UESP1524 | L26: TRUE | M26: The Pub S. A. S. | N26: Pola Del Pub
A27: Condominio Acanto P. H | B27: CONDOMINIO ACANTO Ρ. Η | C27: Factura | D27: Factura | F27: Total | G27: =G26 -> 213554.6 | H27: =VLOOKUP(B27,'Febrero Data'!A:D,4,FALSE) -> UESP1524 | L27: TRUE | M27: Urbanizacion Arboleda De Castilla Propiedad Horizontal | N27: arboleda de castilla
A28: Congregación De Religiosas Hijas De Cristo Rey | B28: CONGREGACIÓN DE RELIGIOSAS HIJAS DE CRISTO REY | C28: Total | D28: Mandato | E28: Bogotá, D.C. | F28: Ingreso Bruto | G28: =SUMIFS('Febrero Data'!C:C,'Febrero Data'!A:A,B28,'Febrero Data'!B:B,F28) -> 2244451 | H28: =VLOOKUP(B28,'Febrero Data'!A:D,4,FALSE) -> UESP1519 | I28: Cristo Rey | J28: =J23+1 -> 526
A29: Congregación De Religiosas Hijas De Cristo Rey | B29: CONGREGACIÓN DE RELIGIOSAS HIJAS DE CRISTO REY | C29: total | D29: Mandato | E29: Bogotá, D.C. | F29: Interes | G29: =SUMIFS('Febrero Data'!C:C,'Febrero Data'!A:A,B29,'Febrero Data'!B:B,F29) -> 53672.5 | H29: =VLOOKUP(B29,'Febrero Data'!A:D,4,FALSE) -> UESP1519 | I29: Cristo Rey
A30: Congregación De Religiosas Hijas De Cristo Rey | B30: CONGREGACIÓN DE RELIGIOSAS HIJAS DE CRISTO REY | C30: total | D30: Mandato | E30: Bogotá, D.C. | F30: Valor a Pagar | G30: =G29+G28 -> 2298123.5 | H30: =VLOOKUP(B30,'Febrero Data'!A:D,4,FALSE) -> UESP1519
A31: Congregación De Religiosas Hijas De Cristo Rey | B31: CONGREGACIÓN DE RELIGIOSAS HIJAS DE CRISTO REY | C31: Factura | D31: Factura | F31: Administración | G31: =G30*5% -> 114906.18 | H31: =VLOOKUP(B31,'Febrero Data'!A:D,4,FALSE) -> UESP1519
A32: Congregación De Religiosas Hijas De Cristo Rey | B32: CONGREGACIÓN DE RELIGIOSAS HIJAS DE CRISTO REY | C32: Factura | D32: Factura | F32: Total | G32: =G31 -> 114906.18 | H32: =VLOOKUP(B32,'Febrero Data'!A:D,4,FALSE) -> UESP1519
A33: Conjunto Laureles Campestre Etapas I Ii Y Iii Ph | B33: CONJUNTO LAURELES CAMPESTRE ETAPAS I II Y III | C33: Total | D33: Mandato | E33: Medellín | F33: Ingreso Bruto | G33: =SUMIFS('Febrero Data'!C:C,'Febrero Data'!A:A,B33,'Febrero Data'!B:B,F33) -> 11561704 | H33: =VLOOKUP(B33,'Febrero Data'!A:D,4,FALSE) -> UESP1539 | I33: Laureles Campestre | J33: =J28+1 -> 527
A34: Conjunto Laureles Campestre Etapas I Ii Y Iii Ph | B34: CONJUNTO LAURELES CAMPESTRE ETAPAS I II Y III | C34: total | D34: Mandato | E34: Medellín | F34: Interes | G34: =SUMIFS('Febrero Data'!C:C,'Febrero Data'!A:A,B34,'Febrero Data'!B:B,F34) -> 171219.46 | H34: =VLOOKUP(B34,'Febrero Data'!A:D,4,FALSE) -> UESP1539 | I34: Laureles Campestre
A35: Conjunto Laureles Campestre Etapas I Ii Y Iii Ph | B35: CONJUNTO LAURELES CAMPESTRE ETAPAS I II Y III | C35: total | D35: Mandato | E35: Medellín | F35: Valor a Pagar | G35: =G34+G33 -> 11732924 | H35: =VLOOKUP(B35,'Febrero Data'!A:D,4,FALSE) -> UESP1539
A36: Conjunto Laureles Campestre Etapas I Ii Y Iii Ph | B36: CONJUNTO LAURELES CAMPESTRE ETAPAS I II Y III | C36: Factura | D36: Factura | F36: Administración | G36: =G35*5% -> 586646.2 | H36: =VLOOKUP(B36,'Febrero Data'!A:D,4,FALSE) -> UESP1539
A37: Conjunto Laureles Campestre Etapas I Ii Y Iii Ph | B37: CONJUNTO LAURELES CAMPESTRE ETAPAS I II Y III | C37: Factura | D37: Factura | F37: Total | G37: =G36 -> 586646.2 | H37: =VLOOKUP(B37,'Febrero Data'!A:D,4,FALSE) -> UESP1539
A38: Conjunto Residencial San Esteban Del Poblado P.H. | B38: CONJUNTO RESIDENCIAL SAN ESTEBAN DEL POBLADO P.H. | C38: Total | D38: Mandato | E38: Medellín | F38: Ingreso Bruto | G38: =SUMIFS('Febrero Data'!C:C,'Febrero Data'!A:A,B38,'Febrero Data'!B:B,F38) -> 1609725 | H38: =VLOOKUP(B38,'Febrero Data'!A:D,4,FALSE) -> UESP1529 | I38: San Esteban | J38: =J33+1 -> 528
A39: Conjunto Residencial San Esteban Del Poblado P.H. | B39: CONJUNTO RESIDENCIAL SAN ESTEBAN DEL POBLADO P.H. | C39: total | D39: Mandato | E39: Medellín | F39: Interes | G39: =SUMIFS('Febrero Data'!C:C,'Febrero Data'!A:A,B39,'Febrero Data'!B:B,F39) -> 20928.27 | H39: =VLOOKUP(B39,'Febrero Data'!A:D,4,FALSE) -> UESP1529 | I39: San Esteban
A40: Conjunto Residencial San Esteban Del Poblado P.H. | B40: CONJUNTO RESIDENCIAL SAN ESTEBAN DEL POBLADO P.H. | C40: total | D40: Mandato | E40: Medellín | F40: Valor a Pagar | G40: =G39+G38 -> 1630653.3 | H40: =VLOOKUP(B40,'Febrero Data'!A:D,4,FALSE) -> UESP1529
A41: Conjunto Residencial San Esteban Del Poblado P.H. | B41: CONJUNTO RESIDENCIAL SAN ESTEBAN DEL POBLADO P.H. | C41: Factura | D41: Factura | F41: Administración | G41: =G40*5% -> 81532.663 | H41: =VLOOKUP(B41,'Febrero Data'!A:D,4,FALSE) -> UESP1529
A42: Conjunto Residencial San Esteban Del Poblado P.H. | B42: CONJUNTO RESIDENCIAL SAN ESTEBAN DEL POBLADO P.H. | C42: Factura | D42: Factura | F42: Total | G42: =G41 -> 81532.663 | H42: =VLOOKUP(B42,'Febrero Data'!A:D,4,FALSE) -> UESP1529
A43: Cooperativa Antioqueña De Salud | B43: COOPERATIVA ANTIOQUEÑA DE SALUD | C43: Total | D43: Mandato | E43: Medellín | F43: Ingreso Bruto | G43: =SUMIFS('Febrero Data'!C:C,'Febrero Data'!A:A,B43,'Febrero Data'!B:B,F43) -> 1992216 | H43: =VLOOKUP(B43,'Febrero Data'!A:D,4,FALSE) -> UESP1518 | I43: coopsana ips | J43: =J38+1 -> 529
A44: Cooperativa Antioqueña De Salud | B44: COOPERATIVA ANTIOQUEÑA DE SALUD | C44: Total | D44: Mandato | E44: Medellín | F44: Interes | G44: =SUMIFS('Febrero Data'!C:C,'Febrero Data'!A:A,B44,'Febrero Data'!B:B,F44) -> 367512.7 | H44: =VLOOKUP(B44,'Febrero Data'!A:D,4,FALSE) -> UESP1518 | I44: coopsana ips
A45: Cooperativa Antioqueña De Salud | B45: COOPERATIVA ANTIOQUEÑA DE SALUD | C45: Total | D45: Mandato | E45: Medellín | F45: Valor a Pagar | G45: =G44+G43 -> 2359728.7 | H45: =VLOOKUP(B45,'Febrero Data'!A:D,4,FALSE) -> UESP1518
A46: Cooperativa Antioqueña De Salud | B46: COOPERATIVA ANTIOQUEÑA DE SALUD | C46: Factura | D46: Factura | F46: Administración | G46: =G45*5% -> 117986.43 | H46: =VLOOKUP(B46,'Febrero Data'!A:D,4,FALSE) -> UESP1518
A47: Cooperativa Antioqueña De Salud | B47: COOPERATIVA ANTIOQUEÑA DE SALUD | C47: Factura | D47: Factura | F47: Total | G47: =G46 -> 117986.43 | H47: =VLOOKUP(B47,'Febrero Data'!A:D,4,FALSE) -> UESP1518
A48: Dual Cross S.A.S | B48: DUAL CROSS S.A.S | C48: Total | D48: Mandato | E48: Medellín | F48: Ingreso Bruto | G48: =SUMIFS('Febrero Data'!C:C,'Febrero Data'!A:A,B48,'Febrero Data'!B:B,F48) -> 2485290 | H48: =VLOOKUP(B48,'Febrero Data'!A:D,4,FALSE) -> UESP1533 | I48: Cross Bisnes center | J48: =J43+1 -> 530
A49: Dual Cross S.A.S | B49: DUAL CROSS S.A.S | C49: total | D49: Mandato | E49: Medellín | F49: Interes | G49: =SUMIFS('Febrero Data'!C:C,'Febrero Data'!A:A,B49,'Febrero Data'!B:B,F49) -> 3261.19 | H49: =VLOOKUP(B49,'Febrero Data'!A:D,4,FALSE) -> UESP1533 | I49: Cross Bisnes center
A50: Dual Cross S.A.S | B50: DUAL CROSS S.A.S | C50: total | D50: Mandato | F50: Retención en la fuente | G50: =(G48+G49)*4% -> 99542.048 | H50: =VLOOKUP(B50,'Febrero Data'!A:D,4,FALSE) -> UESP1533
A51: Dual Cross S.A.S | B51: DUAL CROSS S.A.S | C51: total | D51: Mandato | E51: Medellín | F51: Valor a Pagar | G51: =G48+G49-G50 -> 2389009.1 | H51: =VLOOKUP(B51,'Febrero Data'!A:D,4,FALSE) -> UESP1533
A52: Dual Cross S.A.S | B52: DUAL CROSS S.A.S | C52: Factura | D52: Factura | F52: Administración | G52: =G51*5% -> 119450.46 | H52: =VLOOKUP(B52,'Febrero Data'!A:D,4,FALSE) -> UESP1533
A53: Dual Cross S.A.S | B53: DUAL CROSS S.A.S | C53: Factura | D53: Factura | F53: Total | G53: =G52 -> 119450.46 | H53: =VLOOKUP(B53,'Febrero Data'!A:D,4,FALSE) -> UESP1533
A54: Ecoimagen Salud S.A.S | B54: ECOIMAGEN SALUD S.A.S | C54: Total | D54: Mandato | E54: Cúcuta | F54: Ingreso Bruto | G54: =SUMIFS('Febrero Data'!C:C,'Febrero Data'!A:A,B54,'Febrero Data'!B:B,F54) -> 1464854 | H54: =VLOOKUP(B54,'Febrero Data'!A:D,4,FALSE) -> UESP1523 | I54: Ecoimagen ips | J54: =J48+1 -> 531
A55: Ecoimagen Salud S.A.S | B55: ECOIMAGEN SALUD S.A.S | C55: total | D55: Mandato | E55: Cúcuta | F55: Interes | G55: =SUMIFS('Febrero Data'!C:C,'Febrero Data'!A:A,B55,'Febrero Data'!B:B,F55) -> 35938.05 | H55: =VLOOKUP(B55,'Febrero Data'!A:D,4,FALSE) -> UESP1523 | I55: Ecoimagen ips
A56: Ecoimagen Salud S.A.S | B56: ECOIMAGEN SALUD S.A.S | C56: total | D56: Mandato | E56: Cúcuta | F56: Retención en la fuente | G56: =(G54+G55)*2.5% -> 37519.801 | H56: =VLOOKUP(B56,'Febrero Data'!A:D,4,FALSE) -> UESP1523
A57: Ecoimagen Salud S.A.S | B57: ECOIMAGEN SALUD S.A.S | C57: total | D57: Mandato | E57: Cúcuta | F57: Valor a Pagar | G57: =G54+G55-G56 -> 1463272.2
A58: Ecoimagen Salud S.A.S | B58: ECOIMAGEN SALUD S.A.S | C58: Factura | D58: Factura | F58: Administración | G58: =G57*5% -> 73163.612 | H58: =VLOOKUP(B58,'Febrero Data'!A:D,4,FALSE) -> UESP1523
A59: Ecoimagen Salud S.A.S | B59: ECOIMAGEN SALUD S.A.S | C59: Factura | D59: Factura | F59: Total | G59: =G58 -> 73163.612 | H59: =VLOOKUP(B59,'Febrero Data'!A:D,4,FALSE) -> UESP1523
A60: Edificio Torre Almagran Propiedad Horizontal | B60: EDIFICIO TORRE ALMAGRAN PROPIEDAD HORIZONTAL | C60: Total | D60: Mandato | E60: Medellín | F60: Ingreso Bruto | G60: =SUMIFS('Febrero Data'!C:C,'Febrero Data'!A:A,B60,'Febrero Data'!B:B,F60) -> 1493894 | H60: =VLOOKUP(B60,'Febrero Data'!A:D,4,FALSE) -> UESP1525 | I60: Almagran | J60: =J54+1 -> 532
A61: Edificio Torre Almagran Propiedad Horizontal | B61: EDIFICIO TORRE ALMAGRAN PROPIEDAD HORIZONTAL | C61: total | D61: Mandato | E61: Medellín | F61: Interes | G61: =SUMIFS('Febrero Data'!C:C,'Febrero Data'!A:A,B61,'Febrero Data'!B:B,F61) -> 0 | H61: =VLOOKUP(B61,'Febrero Data'!A:D,4,FALSE) -> UESP1525 | I61: Almagran
A62: Edificio Torre Almagran Propiedad Horizontal | B62: EDIFICIO TORRE ALMAGRAN PROPIEDAD HORIZONTAL | C62: total | D62: Mandato | F62: Retención en la fuente | G62: =(G60+G61)*2.5% -> 37347.35 | H62: =VLOOKUP(B62,'Febrero Data'!A:D,4,FALSE) -> UESP1525
A63: Edificio Torre Almagran Propiedad Horizontal | B63: EDIFICIO TORRE ALMAGRAN PROPIEDAD HORIZONTAL | C63: total | D63: Mandato | E63: Medellín | F63: Valor a Pagar | G63: =G60+G61-G62 -> 1456546.6 | H63: =VLOOKUP(B63,'Febrero Data'!A:D,4,FALSE) -> UESP1525
A64: Edificio Torre Almagran Propiedad Horizontal | B64: EDIFICIO TORRE ALMAGRAN PROPIEDAD HORIZONTAL | C64: Factura | D64: Factura | F64: Administración | G64: =G63*5% -> 72827.333 | H64: =VLOOKUP(B64,'Febrero Data'!A:D,4,FALSE) -> UESP1525
A65: Edificio Torre Almagran Propiedad Horizontal | B65: EDIFICIO TORRE ALMAGRAN PROPIEDAD HORIZONTAL | C65: Factura | D65: Factura | F65: Total | G65: =G64 -> 72827.333 | H65: =VLOOKUP(B65,'Febrero Data'!A:D,4,FALSE) -> UESP1525
A66: Instituto Bolivariano (Ibes) | B66: CORREDOR NIÑO FRANK EDWIN | C66: Total | D66: Mandato | E66: Cúcuta | F66: Ingreso Bruto | G66: =SUMIFS('Febrero Data'!C:C,'Febrero Data'!A:A,B66,'Febrero Data'!B:B,F66) -> 2821205 | H66: =VLOOKUP(B66,'Febrero Data'!A:D,4,FALSE) -> UESP1527 | I66: instituto bolivariano (ibes) | J66: =J60+1 -> 533
A67: Instituto Bolivariano (Ibes) | B67: CORREDOR NIÑO FRANK EDWIN | C67: total | D67: Mandato | E67: Cúcuta | F67: Interes | G67: =SUMIFS('Febrero Data'!C:C,'Febrero Data'!A:A,B67,'Febrero Data'!B:B,F67) -> 61201.09 | H67: =VLOOKUP(B67,'Febrero Data'!A:D,4,FALSE) -> UESP1527 | I67: instituto bolivariano (ibes)
A68: Instituto Bolivariano (Ibes) | B68: CORREDOR NIÑO FRANK EDWIN | C68: total | D68: Mandato | E68: Cúcuta | F68: Valor a Pagar | G68: =G67+G66 -> 2882406.1 | H68: =VLOOKUP(B68,'Febrero Data'!A:D,4,FALSE) -> UESP1527
A69: Instituto Bolivariano (Ibes) | B69: CORREDOR NIÑO FRANK EDWIN | C69: Factura | D69: Factura | F69: Administración | G69: =G68*5% -> 144120.3 | H69: =VLOOKUP(B69,'Febrero Data'!A:D,4,FALSE) -> UESP1527
A70: Instituto Bolivariano (Ibes) | B70: CORREDOR NIÑO FRANK EDWIN | C70: Factura | D70: Factura | F70: Total | G70: =G69 -> 144120.3 | H70: =VLOOKUP(B70,'Febrero Data'!A:D,4,FALSE) -> UESP1527
A71: Los Coches | B71: CORREA TOBON ALBERTO DE JESUS | C71: Total | D71: Mandato | E71: Montelíbano | F71: Ingreso Bruto | G71: =SUMIFS('Febrero Data'!C:C,'Febrero Data'!A:A,B71,'Febrero Data'!B:B,F71) -> 2046666 | H71: =VLOOKUP(B71,'Febrero Data'!A:D,4,FALSE) -> UESP1531 | I71: Hotel los coches | J71: =J66+1 -> 534
A72: Los Coches | B72: CORREA TOBON ALBERTO DE JESUS | C72: total | D72: Mandato | E72: Montelíbano | F72: Interes | G72: =SUMIFS('Febrero Data'!C:C,'Febrero Data'!A:A,B72,'Febrero Data'!B:B,F72) -> 0 | H72: =VLOOKUP(B72,'Febrero Data'!A:D,4,FALSE) -> UESP1531 | I72: Hotel los coches
A73: Los Coches | B73: CORREA TOBON ALBERTO DE JESUS | C73: total | D73: Mandato | E73: Montelíbano | F73: Valor a Pagar | G73: =G72+G71 -> 2046666 | H73: =VLOOKUP(B73,'Febrero Data'!A:D,4,FALSE) -> UESP1531
A74: Los Coches | B74: CORREA TOBON ALBERTO DE JESUS | C74: Factura | D74: Factura | F74: Administración | G74: =G73*5% -> 102333.3 | H74: =VLOOKUP(B74,'Febrero Data'!A:D,4,FALSE) -> UESP1531
A75: Los Coches | B75: CORREA TOBON ALBERTO DE JESUS | C75: Factura | D75: Factura | F75: Total | G75: =G74 -> 102333.3 | H75: =VLOOKUP(B75,'Febrero Data'!A:D,4,FALSE) -> UESP1531
A76: M.D.M. Cientifica S.A.S | B76: M.D.M. CIENTIFICA S.A.S | C76: Total | D76: Mandato | E76: Medellín | F76: Ingreso Bruto | G76: =SUMIFS('Febrero Data'!C:C,'Febrero Data'!A:A,B76,'Febrero Data'!B:B,F76) -> 798603 | H76: =VLOOKUP(B76,'Febrero Data'!A:D,4,FALSE) -> UESP1522 | I76: MDM Cientifica | J76: =J71+1 -> 535
A77: M.D.M. Cientifica S.A.S | B77: M.D.M. CIENTIFICA S.A.S | C77: total | D77: Mandato | E77: Medellín | F77: Interes | G77: =SUMIFS('Febrero Data'!C:C,'Febrero Data'!A:A,B77,'Febrero Data'!B:B,F77) -> 2186.18 | H77: =VLOOKUP(B77,'Febrero Data'!A:D,4,FALSE) -> UESP1522 | I77: MDM Cientifica
A78: M.D.M. Cientifica S.A.S | B78: M.D.M. CIENTIFICA S.A.S | C78: total | D78: Mandato | F78: Retención en la fuente | G78: =(G76+G77)*2.5% -> 20019.73 | H78: =VLOOKUP(B78,'Febrero Data'!A:D,4,FALSE) -> UESP1522
A79: M.D.M. Cientifica S.A.S | B79: M.D.M. CIENTIFICA S.A.S | C79: total | D79: Mandato | E79: Medellín | F79: Valor a Pagar | G79: =G76+G77-G78 -> 780769.45 | H79: =VLOOKUP(B79,'Febrero Data'!A:D,4,FALSE) -> UESP1522
A80: M.D.M. Cientifica S.A.S | B80: M.D.M. CIENTIFICA S.A.S | C80: Factura | D80: Factura | F80: Administración | G80: =G79*5% -> 39038.473 | H80: =VLOOKUP(B80,'Febrero Data'!A:D,4,FALSE) -> UESP1522
A81: M.D.M. Cientifica S.A.S | B81: M.D.M. CIENTIFICA S.A.S | C81: Factura | D81: Factura | F81: Total | G81: =G80 -> 39038.473 | H81: =VLOOKUP(B81,'Febrero Data'!A:D,4,FALSE) -> UESP1522
A82: Polikem S.A.S | B82: POLIKEM S.A.S | C82: Total | D82: Mandato | E82: Rionegro | F82: Ingreso Bruto | G82: =SUMIFS('Febrero Data'!C:C,'Febrero Data'!A:A,B82,'Febrero Data'!B:B,F82) -> 2150266 | H82: =VLOOKUP(B82,'Febrero Data'!A:D,4,FALSE) -> UESP1517 | I82: Polikem | J82: =J76+1 -> 536
A83: Polikem S.A.S | B83: POLIKEM S.A.S | C83: total | D83: Mandato | E83: Rionegro | F83: Interes | G83: =SUMIFS('Febrero Data'!C:C,'Febrero Data'!A:A,B83,'Febrero Data'!B:B,F83) -> 0 | H83: =VLOOKUP(B83,'Febrero Data'!A:D,4,FALSE) -> UESP1517 | I83: Polikem
A84: Polikem S.A.S | B84: POLIKEM S.A.S | C84: total | D84: Mandato | F84: Retención en la fuente | G84: =(G82+G83)*4% -> 86010.64 | H84: =VLOOKUP(B84,'Febrero Data'!A:D,4,FALSE) -> UESP1517
A85: Polikem S.A.S | B85: POLIKEM S.A.S | C85: total | D85: Mandato | F85: ICA | G85: =(G82+G83)*0.4% -> 8601.064 | H85: =VLOOKUP(B85,'Febrero Data'!A:D,4,FALSE) -> UESP1517
A86: Polikem S.A.S | B86: POLIKEM S.A.S | C86: total | D86: Mandato | E86: Rionegro | F86: Valor a Pagar | G86: =G82+G83-G84-G85 -> 2055654.3 | H86: =VLOOKUP(B86,'Febrero Data'!A:D,4,FALSE) -> UESP1517
A87: Polikem S.A.S | B87: POLIKEM S.A.S | C87: Factura | D87: Factura | F87: Administración | G87: =G86*5% -> 102782.71 | H87: =VLOOKUP(B87,'Febrero Data'!A:D,4,FALSE) -> UESP1517
A88: Polikem S.A.S | B88: POLIKEM S.A.S | C88: Factura | D88: Factura | F88: Total | G88: =G87 -> 102782.71 | H88: =VLOOKUP(B88,'Febrero Data'!A:D,4,FALSE) -> UESP1517
A89: Servicios Industriales Y Metalmecanicos Sas | B89: SERVICIOS INDUSTRIALES Y METALMECANICOS SAS | C89: Total | D89: Mandato | E89: Cartagena De Indias | F89: Ingreso Bruto | G89: =SUMIFS('Febrero Data'!C:C,'Febrero Data'!A:A,B89,'Febrero Data'!B:B,F89) -> 3438237 | H89: =VLOOKUP(B89,'Febrero Data'!A:D,4,FALSE) -> UESP1530 | I89: Seridme | J89: =J82+1 -> 537
A90: Servicios Industriales Y Metalmecanicos Sas | B90: SERVICIOS INDUSTRIALES Y METALMECANICOS SAS | C90: total | D90: Mandato | E90: Cartagena De Indias | F90: Interes | G90: =SUMIFS('Febrero Data'!C:C,'Febrero Data'!A:A,B90,'Febrero Data'!B:B,F90) -> 4258.39 | H90: =VLOOKUP(B90,'Febrero Data'!A:D,4,FALSE) -> UESP1530 | I90: Seridme
A91: Servicios Industriales Y Metalmecanicos Sas | B91: SERVICIOS INDUSTRIALES Y METALMECANICOS SAS | C91: total | D91: Mandato | E91: Cartagena De Indias | F91: Valor a Pagar | G91: =G90+G89 -> 3442495.4 | H91: =VLOOKUP(B91,'Febrero Data'!A:D,4,FALSE) -> UESP1530
A92: Servicios Industriales Y Metalmecanicos Sas | B92: SERVICIOS INDUSTRIALES Y METALMECANICOS SAS | C92: Factura | D92: Factura | F92: Administración | G92: =G91*5% -> 172124.77 | H92: =VLOOKUP(B92,'Febrero Data'!A:D,4,FALSE) -> UESP1530
A93: Servicios Industriales Y Metalmecanicos Sas | B93: SERVICIOS INDUSTRIALES Y METALMECANICOS SAS | C93: Factura | D93: Factura | F93: Total | G93: =G92 -> 172124.77 | H93: =VLOOKUP(B93,'Febrero Data'!A:D,4,FALSE) -> UESP1530
A94: Sociedad Educativa Ngs Sas | B94: SOCIEDAD EDUCATIVA NGS SAS | C94: Total | D94: Mandato | E94: Villavicencio | F94: Ingreso Bruto | G94: =SUMIFS('Febrero Data'!C:C,'Febrero Data'!A:A,B94,'Febrero Data'!B:B,F94) -> 2200048 | H94: =VLOOKUP(B94,'Febrero Data'!A:D,4,FALSE) -> UESP1535 | I94: NGS | J94: =J89+1 -> 538
A95: Sociedad Educativa Ngs Sas | B95: SOCIEDAD EDUCATIVA NGS SAS | C95: total | D95: Mandato | E95: Villavicencio | F95: Interes | G95: =SUMIFS('Febrero Data'!C:C,'Febrero Data'!A:A,B95,'Febrero Data'!B:B,F95) -> 2118 | H95: =VLOOKUP(B95,'Febrero Data'!A:D,4,FALSE) -> UESP1535 | I95: NGS
A96: Sociedad Educativa Ngs Sas | B96: SOCIEDAD EDUCATIVA NGS SAS | C96: total | D96: Mandato | E96: Villavicencio | F96: Valor a Pagar | G96: =G95+G94 -> 2202166 | H96: =VLOOKUP(B96,'Febrero Data'!A:D,4,FALSE) -> UESP1535
A97: Sociedad Educativa Ngs Sas | B97: SOCIEDAD EDUCATIVA NGS SAS | C97: Factura | D97: Factura | F97: Administración | G97: =G96*5% -> 110108.3 | H97: =VLOOKUP(B97,'Febrero Data'!A:D,4,FALSE) -> UESP1535
A98: Sociedad Educativa Ngs Sas | B98: SOCIEDAD EDUCATIVA NGS SAS | C98: Factura | D98: Factura | F98: Total | G98: =G97 -> 110108.3 | H98: =VLOOKUP(B98,'Febrero Data'!A:D,4,FALSE) -> UESP1535
A99: Sociedad Medica Rionegro S.A. Somer S.A. | B99: SOCIEDAD MEDICA RIONEGRO S.A. SOMER S.A. | C99: Total | D99: Mandato | E99: Rionegro | F99: Ingreso Bruto | G99: =SUMIFS('Febrero Data'!C:C,'Febrero Data'!A:A,B99,'Febrero Data'!B:B,F99) -> 11034808 | H99: =VLOOKUP(B99,'Febrero Data'!A:D,4,FALSE) -> UESP1521 | I99: Clinica Somer | J99: =J94+1 -> 539
A100: Sociedad Medica Rionegro S.A. Somer S.A. | B100: SOCIEDAD MEDICA RIONEGRO S.A. SOMER S.A. | C100: total | D100: Mandato | E100: Rionegro | F100: Interes | G100: =SUMIFS('Febrero Data'!C:C,'Febrero Data'!A:A,B100,'Febrero Data'!B:B,F100) -> 0 | H100: =VLOOKUP(B100,'Febrero Data'!A:D,4,FALSE) -> UESP1521 | I100: Clinica Somer
...

Sheet Marzo
A1: Proyecto | B1: CLIENTE | C1: Inversionista | D1: Documento contable | E1: Ciudad | F1: Concepto | G1: Total | H1: Factura | I1: ID ODOO | J1: Codigo | L1: Generar | M1: Proyecto | N1: Carpeta proyecto | O1: Factura | Q1: Fecha de Firma | R1: 46123 | S1: Fecha periodo | T1: 01 al 31 de marzo del 2026 | U1: consecutivo final | V1: 642
A2: Almacen Amc Sas | B2: ALMACEN AMC SAS | C2: Total | D2: Mandato | E2: Sincelejo | F2: Ingreso Bruto | G2: =SUMIFS('Marzo Data'!C:C,'Marzo Data'!A:A,B2,'Marzo Data'!B:B,F2) -> 4861937.7 | H2: =VLOOKUP(B2,'Marzo Data'!A:D,4,FALSE) -> UESP1658 | I2: ALMACEN AMC SAS | J2: =V1 -> 642 | L2: FALSE | M2: Almacen Amc Sas | N2: AMC
A3: Almacen Amc Sas | B3: ALMACEN AMC SAS | C3: total | D3: Mandato | E3: Sincelejo | F3: Interes | G3: =SUMIFS('Marzo Data'!C:C,'Marzo Data'!A:A,B3,'Marzo Data'!B:B,F3) -> 241991.07 | H3: =VLOOKUP(B3,'Marzo Data'!A:D,4,FALSE) -> UESP1658 | I3: ALMACEN AMC SAS | L3: FALSE
A4: Almacen Amc Sas | B4: ALMACEN AMC SAS | C4: total | D4: Mandato | E4: Sincelejo | F4: Valor a Pagar | G4: =G2+G3 -> 5103928.8 | H4: =VLOOKUP(B4,'Marzo Data'!A:D,4,FALSE) -> UESP1658 | L4: FALSE | M4: Central De Maderas G&S S.A.S. | N4: Central de maderas
A5: Almacen Amc Sas | B5: ALMACEN AMC SAS | C5: Factura | D5: Factura | E5: Sincelejo | F5: Administración | G5: =G4*5% -> 255196.44 | H5: =VLOOKUP(B5,'Marzo Data'!A:D,4,FALSE) -> UESP1658 | I5: ALMACEN AMC SAS | L5: FALSE | M5: Centro Comercial Y Empresarial Obelisco - P.H.- | N5: Obelisco
A6: Almacen Amc Sas | B6: ALMACEN AMC SAS | C6: Factura | D6: Factura | E6: Sincelejo | F6: Total | G6: =G5 -> 255196.44 | H6: =VLOOKUP(B6,'Marzo Data'!A:D,4,FALSE) -> UESP1658 | I6: ALMACEN AMC SAS | L6: FALSE | M6: Condominio Acanto P. H | N6: Acanto
A7: Arcillas San Simon S.A.S. | B7: ARCILLAS SAN SIMON S.A.S. | C7: Total | D7: Mandato | E7: El Zulia | F7: Mantenimiento CENS | G7: 76359129 | H7: =VLOOKUP(B7,'Marzo Data'!A:D,4,FALSE) -> #N/A | J7: 759 | L7: FALSE
A8: Arcillas San Simon S.A.S. | B8: ARCILLAS SAN SIMON S.A.S. | C8: total | D8: Mandato | E8: El Zulia | F8: Interes | G8: =SUMIFS('Marzo Data'!C:C,'Marzo Data'!A:A,B8,'Marzo Data'!B:B,F8) -> 0 | H8: =VLOOKUP(B8,'Marzo Data'!A:D,4,FALSE) -> #N/A | L8: TRUE | M8: Arcillas San Simon S.A.S.
A9: Arcillas San Simon S.A.S. | B9: ARCILLAS SAN SIMON S.A.S. | C9: total | D9: Mandato | E9: El Zulia | F9: Valor a Pagar | G9: =G8+G7 -> 76359129 | H9: =VLOOKUP(B9,'Marzo Data'!A:D,4,FALSE) -> #N/A | L9: FALSE
A10: Arcillas San Simon S.A.S. | B10: ARCILLAS SAN SIMON S.A.S. | C10: Factura | D10: Factura | E10: El Zulia | F10: Administración | G10: =G9*5% -> 3817956.5 | H10: =VLOOKUP(B10,'Marzo Data'!A:D,4,FALSE) -> #N/A | L10: FALSE
A11: Arcillas San Simon S.A.S. | B11: ARCILLAS SAN SIMON S.A.S. | C11: Factura | D11: Factura | E11: El Zulia | F11: Total | G11: =G10 -> 3817956.5 | H11: =VLOOKUP(B11,'Marzo Data'!A:D,4,FALSE) -> #N/A | L11: FALSE
A12: Central De Maderas G&S S.A.S. | B12: CENTRAL DE MADERAS G&S S.A.S. | C12: Total | D12: Mandato | E12: Turbaná | F12: Ingreso Bruto | G12: =SUMIFS('Marzo Data'!C:C,'Marzo Data'!A:A,B12,'Marzo Data'!B:B,F12) -> 4058738.2 | H12: =VLOOKUP(B12,'Marzo Data'!A:D,4,FALSE) -> UESP1665 | I12: CENTRAL DE MADERAS G&S SAS | J12: =J2+1 -> 643 | L12: FALSE | M12: Congregación De Religiosas Hijas De Cristo Rey | N12: Cristo Rey
A13: Central De Maderas G&S S.A.S. | B13: CENTRAL DE MADERAS G&S S.A.S. | C13: total | D13: Mandato | E13: Turbaná | F13: Interes | G13: =SUMIFS('Marzo Data'!C:C,'Marzo Data'!A:A,B13,'Marzo Data'!B:B,F13) -> 49606.16 | H13: =VLOOKUP(B13,'Marzo Data'!A:D,4,FALSE) -> UESP1665 | I13: CENTRAL DE MADERAS G&S SAS | L13: FALSE | M13: Conjunto Laureles Campestre Etapas I Ii Y Iii Ph | N13: Laureles Campestre
A14: Central De Maderas G&S S.A.S. | B14: CENTRAL DE MADERAS G&S S.A.S. | C14: total | D14: Mandato | F14: Retención en la fuente | G14: =(G12+G13)*4% -> 164333.77 | H14: =VLOOKUP(B14,'Marzo Data'!A:D,4,FALSE) -> UESP1665 | I14: CENTRAL DE MADERAS G&S SAS | L14: FALSE | M14: Conjunto Residencial San Esteban Del Poblado P.H. | N14: San Esteban
A15: Central De Maderas G&S S.A.S. | B15: CENTRAL DE MADERAS G&S S.A.S. | C15: total | D15: Mandato | E15: Turbaná | F15: Valor a Pagar | G15: =G12+G13-G14 -> 3944010.6 | H15: =VLOOKUP(B15,'Marzo Data'!A:D,4,FALSE) -> UESP1665 | L15: FALSE | M15: Cooperativa Antioqueña De Salud | N15: coopsana ips
A16: Central De Maderas G&S S.A.S. | B16: CENTRAL DE MADERAS G&S S.A.S. | C16: Factura | D16: Factura | E16: Turbaná | F16: Administración | G16: =G15*5% -> 197200.53 | H16: =VLOOKUP(B16,'Marzo Data'!A:D,4,FALSE) -> UESP1665 | I16: CENTRAL DE MADERAS G&S SAS | L16: FALSE | M16: Dual Cross S.A.S | N16: Cross Bisnes center
A17: Central De Maderas G&S S.A.S. | B17: CENTRAL DE MADERAS G&S S.A.S. | C17: Factura | D17: Factura | E17: Turbaná | F17: Total | G17: =G16 -> 197200.53 | H17: =VLOOKUP(B17,'Marzo Data'!A:D,4,FALSE) -> UESP1665 | I17: CENTRAL DE MADERAS G&S SAS | L17: FALSE | M17: Ecoimagen Salud S.A.S | N17: Ecoimagen ips
A18: Centro Comercial Y Empresarial Obelisco - P.H.- | B18: CENTRO COMERCIAL Y EMPRESARIAL OBELISCO - P.H.- | C18: Total | D18: Mandato | E18: Medellín | F18: Ingreso Bruto | G18: =SUMIFS('Marzo Data'!C:C,'Marzo Data'!A:A,B18,'Marzo Data'!B:B,F18) -> 7222564.5 | H18: =VLOOKUP(B18,'Marzo Data'!A:D,4,FALSE) -> UESP1660 | I18: CENTRO COMERCIAL Y EMPRESARIAL OBELISCO -P.H.- | J18: =J12+1 -> 644 | L18: FALSE | M18: Edificio Torre Almagran Propiedad Horizontal | N18: Almagran
A19: Centro Comercial Y Empresarial Obelisco - P.H.- | B19: CENTRO COMERCIAL Y EMPRESARIAL OBELISCO - P.H.- | C19: total | D19: Mandato | E19: Medellín | F19: Interes | G19: =SUMIFS('Marzo Data'!C:C,'Marzo Data'!A:A,B19,'Marzo Data'!B:B,F19) -> 0 | H19: =VLOOKUP(B19,'Marzo Data'!A:D,4,FALSE) -> UESP1660 | I19: CENTRO COMERCIAL Y EMPRESARIAL OBELISCO -P.H.- | L19: FALSE | M19: Instituto Bolivariano (Ibes) | N19: instituto bolivariano (ibes)
A20: Centro Comercial Y Empresarial Obelisco - P.H.- | B20: CENTRO COMERCIAL Y EMPRESARIAL OBELISCO - P.H.- | C20: total | D20: Mandato | E20: Medellín | F20: Valor a Pagar | G20: =G19+G18 -> 7222564.5 | H20: =VLOOKUP(B20,'Marzo Data'!A:D,4,FALSE) -> UESP1660 | L20: FALSE | M20: Los Coches | N20: Hotel los coches
A21: Centro Comercial Y Empresarial Obelisco - P.H.- | B21: CENTRO COMERCIAL Y EMPRESARIAL OBELISCO - P.H.- | C21: Factura | D21: Factura | F21: Administración | G21: =G20*5% -> 361128.22 | H21: =VLOOKUP(B21,'Marzo Data'!A:D,4,FALSE) -> UESP1660 | I21: CENTRO COMERCIAL Y EMPRESARIAL OBELISCO -P.H.- | L21: FALSE | M21: M.D.M. Cientifica S.A.S | N21: MDM Cientifica
A22: Centro Comercial Y Empresarial Obelisco - P.H.- | B22: CENTRO COMERCIAL Y EMPRESARIAL OBELISCO - P.H.- | C22: Factura | D22: Factura | F22: Total | G22: =G21 -> 361128.22 | H22: =VLOOKUP(B22,'Marzo Data'!A:D,4,FALSE) -> UESP1660 | I22: CENTRO COMERCIAL Y EMPRESARIAL OBELISCO -P.H.- | L22: FALSE | M22: Polikem S.A.S | N22: Polikem
A23: Condominio Acanto P. H | B23: CONDOMINIO ACANTO Ρ. Η | C23: Total | D23: Mandato | E23: Envigado | F23: Ingreso Bruto | G23: =SUMIFS('Marzo Data'!C:C,'Marzo Data'!A:A,B23,'Marzo Data'!B:B,F23) -> 6007095 | H23: =VLOOKUP(B23,'Marzo Data'!A:D,4,FALSE) -> UESP1656 | I23: CONDOMINIO ACANTO P. H | J23: =J18+1 -> 645 | L23: FALSE | M23: Servicios Industriales Y Metalmecanicos Sas | N23: Seridme
A24: Condominio Acanto P. H | B24: CONDOMINIO ACANTO Ρ. Η | C24: total | D24: Mandato | E24: Envigado | F24: Interes | G24: =SUMIFS('Marzo Data'!C:C,'Marzo Data'!A:A,B24,'Marzo Data'!B:B,F24) -> 0 | H24: =VLOOKUP(B24,'Marzo Data'!A:D,4,FALSE) -> UESP1656 | I24: CONDOMINIO ACANTO P. H | L24: FALSE | M24: Sociedad Educativa Ngs Sas | N24: NGS
A25: Condominio Acanto P. H | B25: CONDOMINIO ACANTO Ρ. Η | C25: total | D25: Mandato | E25: Envigado | F25: Valor a Pagar | G25: =G24+G23 -> 6007095 | H25: =VLOOKUP(B25,'Marzo Data'!A:D,4,FALSE) -> UESP1656 | L25: FALSE | M25: Sociedad Medica Rionegro S.A. Somer S.A. | N25: Clinica Somer
A26: Condominio Acanto P. H | B26: CONDOMINIO ACANTO Ρ. Η | C26: Factura | D26: Factura | F26: Administración | G26: =G25*5% -> 300354.75 | H26: =VLOOKUP(B26,'Marzo Data'!A:D,4,FALSE) -> UESP1656 | I26: CONDOMINIO ACANTO P. H | L26: FALSE | M26: The Pub S. A. S. | N26: Pola Del Pub
A27: Condominio Acanto P. H | B27: CONDOMINIO ACANTO Ρ. Η | C27: Factura | D27: Factura | F27: Total | G27: =G26 -> 300354.75 | H27: =VLOOKUP(B27,'Marzo Data'!A:D,4,FALSE) -> UESP1656 | I27: CONDOMINIO ACANTO P. H | L27: FALSE | M27: Urbanizacion Arboleda De Castilla Propiedad Horizontal | N27: arboleda de castilla
A28: Congregación De Religiosas Hijas De Cristo Rey | B28: CONGREGACIÓN DE RELIGIOSAS HIJAS DE CRISTO REY | C28: Total | D28: Mandato | E28: Bogotá, D.C. | F28: Ingreso Bruto | G28: =SUMIFS('Marzo Data'!C:C,'Marzo Data'!A:A,B28,'Marzo Data'!B:B,F28) -> 2558003.3 | H28: =VLOOKUP(B28,'Marzo Data'!A:D,4,FALSE) -> UESP1651 | I28: CONGREGACIÓN DE RELIGIOSAS HIJAS DE CRISTO REY | J28: =J23+1 -> 646
A29: Congregación De Religiosas Hijas De Cristo Rey | B29: CONGREGACIÓN DE RELIGIOSAS HIJAS DE CRISTO REY | C29: total | D29: Mandato | E29: Bogotá, D.C. | F29: Interes | G29: =SUMIFS('Marzo Data'!C:C,'Marzo Data'!A:A,B29,'Marzo Data'!B:B,F29) -> 85515.56 | H29: =VLOOKUP(B29,'Marzo Data'!A:D,4,FALSE) -> UESP1651 | I29: CONGREGACIÓN DE RELIGIOSAS HIJAS DE CRISTO REY
A30: Congregación De Religiosas Hijas De Cristo Rey | B30: CONGREGACIÓN DE RELIGIOSAS HIJAS DE CRISTO REY | C30: total | D30: Mandato | E30: Bogotá, D.C. | F30: Valor a Pagar | G30: =G29+G28 -> 2643518.9 | H30: =VLOOKUP(B30,'Marzo Data'!A:D,4,FALSE) -> UESP1651
A31: Congregación De Religiosas Hijas De Cristo Rey | B31: CONGREGACIÓN DE RELIGIOSAS HIJAS DE CRISTO REY | C31: Factura | D31: Factura | F31: Administración | G31: =G30*5% -> 132175.94 | H31: =VLOOKUP(B31,'Marzo Data'!A:D,4,FALSE) -> UESP1651 | I31: CONGREGACIÓN DE RELIGIOSAS HIJAS DE CRISTO REY
A32: Congregación De Religiosas Hijas De Cristo Rey | B32: CONGREGACIÓN DE RELIGIOSAS HIJAS DE CRISTO REY | C32: Factura | D32: Factura | F32: Total | G32: =G31 -> 132175.94 | H32: =VLOOKUP(B32,'Marzo Data'!A:D,4,FALSE) -> UESP1651 | I32: CONGREGACIÓN DE RELIGIOSAS HIJAS DE CRISTO REY
A33: Conjunto Laureles Campestre Etapas I Ii Y Iii Ph | B33: CONJUNTO LAURELES CAMPESTRE ETAPAS I II Y III | C33: Total | D33: Mandato | E33: Medellín | F33: Ingreso Bruto | G33: =SUMIFS('Marzo Data'!C:C,'Marzo Data'!A:A,B33,'Marzo Data'!B:B,F33) -> 14787227 | H33: =VLOOKUP(B33,'Marzo Data'!A:D,4,FALSE) -> UESP1668 | I33: CONJUNTO LAURELES CAMPESTRE ETAPAS I II Y III PH | J33: =J28+1 -> 647
A34: Conjunto Laureles Campestre Etapas I Ii Y Iii Ph | B34: CONJUNTO LAURELES CAMPESTRE ETAPAS I II Y III | C34: total | D34: Mandato | E34: Medellín | F34: Interes | G34: =SUMIFS('Marzo Data'!C:C,'Marzo Data'!A:A,B34,'Marzo Data'!B:B,F34) -> 374604.73 | H34: =VLOOKUP(B34,'Marzo Data'!A:D,4,FALSE) -> UESP1668 | I34: CONJUNTO LAURELES CAMPESTRE ETAPAS I II Y III PH
A35: Conjunto Laureles Campestre Etapas I Ii Y Iii Ph | B35: CONJUNTO LAURELES CAMPESTRE ETAPAS I II Y III | C35: total | D35: Mandato | E35: Medellín | F35: Valor a Pagar | G35: =G34+G33 -> 15161832 | H35: =VLOOKUP(B35,'Marzo Data'!A:D,4,FALSE) -> UESP1668
A36: Conjunto Laureles Campestre Etapas I Ii Y Iii Ph | B36: CONJUNTO LAURELES CAMPESTRE ETAPAS I II Y III | C36: Factura | D36: Factura | F36: Administración | G36: =G35*5% -> 758091.6 | H36: =VLOOKUP(B36,'Marzo Data'!A:D,4,FALSE) -> UESP1668 | I36: CONJUNTO LAURELES CAMPESTRE ETAPAS I II Y III PH
A37: Conjunto Laureles Campestre Etapas I Ii Y Iii Ph | B37: CONJUNTO LAURELES CAMPESTRE ETAPAS I II Y III | C37: Factura | D37: Factura | F37: Total | G37: =G36 -> 758091.6 | H37: =VLOOKUP(B37,'Marzo Data'!A:D,4,FALSE) -> UESP1668 | I37: CONJUNTO LAURELES CAMPESTRE ETAPAS I II Y III PH
A38: Conjunto Residencial San Esteban Del Poblado P.H. | B38: CONJUNTO RESIDENCIAL SAN ESTEBAN DEL POBLADO P.H. | C38: Total | D38: Mandato | E38: Medellín | F38: Ingreso Bruto | G38: =SUMIFS('Marzo Data'!C:C,'Marzo Data'!A:A,B38,'Marzo Data'!B:B,F38) -> 2586674.1 | H38: =VLOOKUP(B38,'Marzo Data'!A:D,4,FALSE) -> UESP1667 | I38: CONJUNTO RESIDENCIAL SAN ESTEBAN DEL POBLADO P.H. | J38: =J33+1 -> 648
A39: Conjunto Residencial San Esteban Del Poblado P.H. | B39: CONJUNTO RESIDENCIAL SAN ESTEBAN DEL POBLADO P.H. | C39: total | D39: Mandato | E39: Medellín | F39: Interes | G39: =SUMIFS('Marzo Data'!C:C,'Marzo Data'!A:A,B39,'Marzo Data'!B:B,F39) -> 33127.11 | H39: =VLOOKUP(B39,'Marzo Data'!A:D,4,FALSE) -> UESP1667 | I39: CONJUNTO RESIDENCIAL SAN ESTEBAN DEL POBLADO P.H.
A40: Conjunto Residencial San Esteban Del Poblado P.H. | B40: CONJUNTO RESIDENCIAL SAN ESTEBAN DEL POBLADO P.H. | C40: total | D40: Mandato | E40: Medellín | F40: Valor a Pagar | G40: =G39+G38 -> 2619801.2 | H40: =VLOOKUP(B40,'Marzo Data'!A:D,4,FALSE) -> UESP1667
A41: Conjunto Residencial San Esteban Del Poblado P.H. | B41: CONJUNTO RESIDENCIAL SAN ESTEBAN DEL POBLADO P.H. | C41: Factura | D41: Factura | F41: Administración | G41: =G40*5% -> 130990.06 | H41: =VLOOKUP(B41,'Marzo Data'!A:D,4,FALSE) -> UESP1667 | I41: CONJUNTO RESIDENCIAL SAN ESTEBAN DEL POBLADO P.H.
A42: Conjunto Residencial San Esteban Del Poblado P.H. | B42: CONJUNTO RESIDENCIAL SAN ESTEBAN DEL POBLADO P.H. | C42: Factura | D42: Factura | F42: Total | G42: =G41 -> 130990.06 | H42: =VLOOKUP(B42,'Marzo Data'!A:D,4,FALSE) -> UESP1667 | I42: CONJUNTO RESIDENCIAL SAN ESTEBAN DEL POBLADO P.H.
A43: Cooperativa Antioqueña De Salud | B43: COOPERATIVA ANTIOQUEÑA DE SALUD | C43: Total | D43: Mandato | E43: Medellín | F43: Ingreso Bruto | G43: =SUMIFS('Marzo Data'!C:C,'Marzo Data'!A:A,B43,'Marzo Data'!B:B,F43) -> 2731068.5 | H43: =VLOOKUP(B43,'Marzo Data'!A:D,4,FALSE) -> UESP1650 | I43: COOPERATIVA ANTIOQUEÑA DE SALUD | J43: =J38+1 -> 649
A44: Cooperativa Antioqueña De Salud | B44: COOPERATIVA ANTIOQUEÑA DE SALUD | C44: Total | D44: Mandato | E44: Medellín | F44: Interes | G44: =SUMIFS('Marzo Data'!C:C,'Marzo Data'!A:A,B44,'Marzo Data'!B:B,F44) -> 452973.23 | H44: =VLOOKUP(B44,'Marzo Data'!A:D,4,FALSE) -> UESP1650 | I44: COOPERATIVA ANTIOQUEÑA DE SALUD
A45: Cooperativa Antioqueña De Salud | B45: COOPERATIVA ANTIOQUEÑA DE SALUD | C45: Total | D45: Mandato | E45: Medellín | F45: Valor a Pagar | G45: =G44+G43 -> 3184041.7 | H45: =VLOOKUP(B45,'Marzo Data'!A:D,4,FALSE) -> UESP1650
A46: Cooperativa Antioqueña De Salud | B46: COOPERATIVA ANTIOQUEÑA DE SALUD | C46: Factura | D46: Factura | F46: Administración | G46: =G45*5% -> 159202.09 | H46: =VLOOKUP(B46,'Marzo Data'!A:D,4,FALSE) -> UESP1650 | I46: COOPERATIVA ANTIOQUEÑA DE SALUD
A47: Cooperativa Antioqueña De Salud | B47: COOPERATIVA ANTIOQUEÑA DE SALUD | C47: Factura | D47: Factura | F47: Total | G47: =G46 -> 159202.09 | H47: =VLOOKUP(B47,'Marzo Data'!A:D,4,FALSE) -> UESP1650 | I47: COOPERATIVA ANTIOQUEÑA DE SALUD
A48: Dual Cross S.A.S | B48: DUAL CROSS S.A.S | C48: Total | D48: Mandato | E48: Medellín | F48: Ingreso Bruto | G48: =SUMIFS('Marzo Data'!C:C,'Marzo Data'!A:A,B48,'Marzo Data'!B:B,F48) -> 3416856.3 | H48: =VLOOKUP(B48,'Marzo Data'!A:D,4,FALSE) -> UESP1664 | I48: DUAL CROSS S.A.S | J48: =J43+1 -> 650
A49: Dual Cross S.A.S | B49: DUAL CROSS S.A.S | C49: total | D49: Mandato | E49: Medellín | F49: Interes | G49: =SUMIFS('Marzo Data'!C:C,'Marzo Data'!A:A,B49,'Marzo Data'!B:B,F49) -> 18548.86 | H49: =VLOOKUP(B49,'Marzo Data'!A:D,4,FALSE) -> UESP1664 | I49: DUAL CROSS S.A.S
A50: Dual Cross S.A.S | B50: DUAL CROSS S.A.S | C50: total | D50: Mandato | F50: Retención en la fuente | G50: =(G48+G49)*4% -> 137416.21 | H50: =VLOOKUP(B50,'Marzo Data'!A:D,4,FALSE) -> UESP1664 | I50: DUAL CROSS S.A.S
A51: Dual Cross S.A.S | B51: DUAL CROSS S.A.S | C51: total | D51: Mandato | E51: Medellín | F51: Valor a Pagar | G51: =G48+G49-G50 -> 3297989 | H51: =VLOOKUP(B51,'Marzo Data'!A:D,4,FALSE) -> UESP1664
A52: Dual Cross S.A.S | B52: DUAL CROSS S.A.S | C52: Factura | D52: Factura | F52: Administración | G52: =G51*5% -> 164899.45 | H52: =VLOOKUP(B52,'Marzo Data'!A:D,4,FALSE) -> UESP1664 | I52: DUAL CROSS S.A.S
A53: Dual Cross S.A.S | B53: DUAL CROSS S.A.S | C53: Factura | D53: Factura | F53: Total | G53: =G52 -> 164899.45 | H53: =VLOOKUP(B53,'Marzo Data'!A:D,4,FALSE) -> UESP1664 | I53: DUAL CROSS S.A.S
A54: Ecoimagen Salud S.A.S | B54: ECOIMAGEN SALUD S.A.S | C54: Total | D54: Mandato | E54: Cúcuta | F54: Ingreso Bruto | G54: =SUMIFS('Marzo Data'!C:C,'Marzo Data'!A:A,B54,'Marzo Data'!B:B,F54) -> 1537869.3 | H54: =VLOOKUP(B54,'Marzo Data'!A:D,4,FALSE) -> UESP1655 | I54: ECOIMAGEN SALUD S.A.S | J54: =J48+1 -> 651
A55: Ecoimagen Salud S.A.S | B55: ECOIMAGEN SALUD S.A.S | C55: total | D55: Mandato | E55: Cúcuta | F55: Interes | G55: =SUMIFS('Marzo Data'!C:C,'Marzo Data'!A:A,B55,'Marzo Data'!B:B,F55) -> 21320.48 | H55: =VLOOKUP(B55,'Marzo Data'!A:D,4,FALSE) -> UESP1655 | I55: ECOIMAGEN SALUD S.A.S
A56: Ecoimagen Salud S.A.S | B56: ECOIMAGEN SALUD S.A.S | C56: total | D56: Mandato | E56: Cúcuta | F56: Retención en la fuente | G56: =(G54+G55)*2.5% -> 38979.745 | H56: =VLOOKUP(B56,'Marzo Data'!A:D,4,FALSE) -> UESP1655 | I56: ECOIMAGEN SALUD S.A.S
A57: Ecoimagen Salud S.A.S | B57: ECOIMAGEN SALUD S.A.S | C57: total | D57: Mandato | E57: Cúcuta | F57: Valor a Pagar | G57: =G54+G55-G56 -> 1520210
A58: Ecoimagen Salud S.A.S | B58: ECOIMAGEN SALUD S.A.S | C58: Factura | D58: Factura | F58: Administración | G58: =G57*5% -> 76010.502 | H58: =VLOOKUP(B58,'Marzo Data'!A:D,4,FALSE) -> UESP1655 | I58: ECOIMAGEN SALUD S.A.S
A59: Ecoimagen Salud S.A.S | B59: ECOIMAGEN SALUD S.A.S | C59: Factura | D59: Factura | F59: Total | G59: =G58 -> 76010.502 | H59: =VLOOKUP(B59,'Marzo Data'!A:D,4,FALSE) -> UESP1655 | I59: ECOIMAGEN SALUD S.A.S
A60: Edificio Torre Almagran Propiedad Horizontal | B60: EDIFICIO TORRE ALMAGRAN PROPIEDAD HORIZONTAL | C60: Total | D60: Mandato | E60: Medellín | F60: Ingreso Bruto | G60: =SUMIFS('Marzo Data'!C:C,'Marzo Data'!A:A,B60,'Marzo Data'!B:B,F60) -> 1961033.4 | H60: =VLOOKUP(B60,'Marzo Data'!A:D,4,FALSE) -> UESP1657 | I60: EDIFICIO TORRE ALMAGRAN PROPIEDAD HORIZONTAL | J60: =J54+1 -> 652
A61: Edificio Torre Almagran Propiedad Horizontal | B61: EDIFICIO TORRE ALMAGRAN PROPIEDAD HORIZONTAL | C61: total | D61: Mandato | E61: Medellín | F61: Interes | G61: =SUMIFS('Marzo Data'!C:C,'Marzo Data'!A:A,B61,'Marzo Data'!B:B,F61) -> 0 | H61: =VLOOKUP(B61,'Marzo Data'!A:D,4,FALSE) -> UESP1657 | I61: EDIFICIO TORRE ALMAGRAN PROPIEDAD HORIZONTAL
A62: Edificio Torre Almagran Propiedad Horizontal | B62: EDIFICIO TORRE ALMAGRAN PROPIEDAD HORIZONTAL | C62: total | D62: Mandato | F62: Retención en la fuente | G62: =(G60+G61)*2.5% -> 49025.834 | H62: =VLOOKUP(B62,'Marzo Data'!A:D,4,FALSE) -> UESP1657 | I62: EDIFICIO TORRE ALMAGRAN PROPIEDAD HORIZONTAL
A63: Edificio Torre Almagran Propiedad Horizontal | B63: EDIFICIO TORRE ALMAGRAN PROPIEDAD HORIZONTAL | C63: total | D63: Mandato | E63: Medellín | F63: Valor a Pagar | G63: =G60+G61-G62 -> 1912007.5 | H63: =VLOOKUP(B63,'Marzo Data'!A:D,4,FALSE) -> UESP1657
A64: Edificio Torre Almagran Propiedad Horizontal | B64: EDIFICIO TORRE ALMAGRAN PROPIEDAD HORIZONTAL | C64: Factura | D64: Factura | F64: Administración | G64: =G63*5% -> 95600.376 | H64: =VLOOKUP(B64,'Marzo Data'!A:D,4,FALSE) -> UESP1657 | I64: EDIFICIO TORRE ALMAGRAN PROPIEDAD HORIZONTAL
A65: Edificio Torre Almagran Propiedad Horizontal | B65: EDIFICIO TORRE ALMAGRAN PROPIEDAD HORIZONTAL | C65: Factura | D65: Factura | F65: Total | G65: =G64 -> 95600.376 | H65: =VLOOKUP(B65,'Marzo Data'!A:D,4,FALSE) -> UESP1657 | I65: EDIFICIO TORRE ALMAGRAN PROPIEDAD HORIZONTAL
A66: Instituto Bolivariano (Ibes) | B66: CORREDOR NIÑO FRANK EDWIN | C66: Total | D66: Mandato | E66: Cúcuta | F66: Ingreso Bruto | G66: =SUMIFS('Marzo Data'!C:C,'Marzo Data'!A:A,B66,'Marzo Data'!B:B,F66) -> 2965846.3 | H66: =VLOOKUP(B66,'Marzo Data'!A:D,4,FALSE) -> UESP1659 | I66: CORREDOR NIÑO FRANK EDWIN | J66: =J60+1 -> 653
A67: Instituto Bolivariano (Ibes) | B67: CORREDOR NIÑO FRANK EDWIN | C67: total | D67: Mandato | E67: Cúcuta | F67: Interes | G67: =SUMIFS('Marzo Data'!C:C,'Marzo Data'!A:A,B67,'Marzo Data'!B:B,F67) -> 60995.46 | H67: =VLOOKUP(B67,'Marzo Data'!A:D,4,FALSE) -> UESP1659 | I67: CORREDOR NIÑO FRANK EDWIN
A68: Instituto Bolivariano (Ibes) | B68: CORREDOR NIÑO FRANK EDWIN | C68: total | D68: Mandato | E68: Cúcuta | F68: Valor a Pagar | G68: =G67+G66 -> 3026841.8 | H68: =VLOOKUP(B68,'Marzo Data'!A:D,4,FALSE) -> UESP1659
A69: Instituto Bolivariano (Ibes) | B69: CORREDOR NIÑO FRANK EDWIN | C69: Factura | D69: Factura | F69: Administración | G69: =G68*5% -> 151342.09 | H69: =VLOOKUP(B69,'Marzo Data'!A:D,4,FALSE) -> UESP1659 | I69: CORREDOR NIÑO FRANK EDWIN
A70: Instituto Bolivariano (Ibes) | B70: CORREDOR NIÑO FRANK EDWIN | C70: Factura | D70: Factura | F70: Total | G70: =G69 -> 151342.09 | H70: =VLOOKUP(B70,'Marzo Data'!A:D,4,FALSE) -> UESP1659 | I70: CORREDOR NIÑO FRANK EDWIN
A71: Los Coches | B71: CORREA TOBON ALBERTO DE JESUS | C71: Total | D71: Mandato | E71: Montelíbano | F71: Ingreso Bruto | G71: =SUMIFS('Marzo Data'!C:C,'Marzo Data'!A:A,B71,'Marzo Data'!B:B,F71) -> 3347873.4 | H71: =VLOOKUP(B71,'Marzo Data'!A:D,4,FALSE) -> UESP1662 | I71: CORREA TOBON ALBERTO DE JESUS | J71: =J66+1 -> 654
A72: Los Coches | B72: CORREA TOBON ALBERTO DE JESUS | C72: total | D72: Mandato | E72: Montelíbano | F72: Interes | G72: =SUMIFS('Marzo Data'!C:C,'Marzo Data'!A:A,B72,'Marzo Data'!B:B,F72) -> 0 | H72: =VLOOKUP(B72,'Marzo Data'!A:D,4,FALSE) -> UESP1662 | I72: CORREA TOBON ALBERTO DE JESUS
A73: Los Coches | B73: CORREA TOBON ALBERTO DE JESUS | C73: total | D73: Mandato | E73: Montelíbano | F73: Valor a Pagar | G73: =G72+G71 -> 3347873.4 | H73: =VLOOKUP(B73,'Marzo Data'!A:D,4,FALSE) -> UESP1662
A74: Los Coches | B74: CORREA TOBON ALBERTO DE JESUS | C74: Factura | D74: Factura | F74: Administración | G74: =G73*5% -> 167393.67 | H74: =VLOOKUP(B74,'Marzo Data'!A:D,4,FALSE) -> UESP1662 | I74: CORREA TOBON ALBERTO DE JESUS
A75: Los Coches | B75: CORREA TOBON ALBERTO DE JESUS | C75: Factura | D75: Factura | F75: Total | G75: =G74 -> 167393.67 | H75: =VLOOKUP(B75,'Marzo Data'!A:D,4,FALSE) -> UESP1662 | I75: CORREA TOBON ALBERTO DE JESUS
A76: M.D.M. Cientifica S.A.S | B76: M.D.M. CIENTIFICA S.A.S | C76: Total | D76: Mandato | E76: Medellín | F76: Ingreso Bruto | G76: =SUMIFS('Marzo Data'!C:C,'Marzo Data'!A:A,B76,'Marzo Data'!B:B,F76) -> 2616949 | H76: =VLOOKUP(B76,'Marzo Data'!A:D,4,FALSE) -> UESP1654 | I76: M.D.M. CIENTIFICA S.A.S | J76: =J71+1 -> 655
A77: M.D.M. Cientifica S.A.S | B77: M.D.M. CIENTIFICA S.A.S | C77: total | D77: Mandato | E77: Medellín | F77: Interes | G77: =SUMIFS('Marzo Data'!C:C,'Marzo Data'!A:A,B77,'Marzo Data'!B:B,F77) -> 12955.78 | H77: =VLOOKUP(B77,'Marzo Data'!A:D,4,FALSE) -> UESP1654 | I77: M.D.M. CIENTIFICA S.A.S
A78: M.D.M. Cientifica S.A.S | B78: M.D.M. CIENTIFICA S.A.S | C78: total | D78: Mandato | F78: Retención en la fuente | G78: =(G76+G77)*2.5% -> 65747.619 | H78: =VLOOKUP(B78,'Marzo Data'!A:D,4,FALSE) -> UESP1654 | I78: M.D.M. CIENTIFICA S.A.S
A79: M.D.M. Cientifica S.A.S | B79: M.D.M. CIENTIFICA S.A.S | C79: total | D79: Mandato | E79: Medellín | F79: Valor a Pagar | G79: =G76+G77-G78 -> 2564157.1 | H79: =VLOOKUP(B79,'Marzo Data'!A:D,4,FALSE) -> UESP1654
A80: M.D.M. Cientifica S.A.S | B80: M.D.M. CIENTIFICA S.A.S | C80: Factura | D80: Factura | F80: Administración | G80: =G79*5% -> 128207.86 | H80: =VLOOKUP(B80,'Marzo Data'!A:D,4,FALSE) -> UESP1654 | I80: M.D.M. CIENTIFICA S.A.S
A81: M.D.M. Cientifica S.A.S | B81: M.D.M. CIENTIFICA S.A.S | C81: Factura | D81: Factura | F81: Total | G81: =G80 -> 128207.86 | H81: =VLOOKUP(B81,'Marzo Data'!A:D,4,FALSE) -> UESP1654 | I81: M.D.M. CIENTIFICA S.A.S
A82: Polikem S.A.S | B82: POLIKEM S.A.S | C82: Total | D82: Mandato | E82: Rionegro | F82: Ingreso Bruto | G82: =SUMIFS('Marzo Data'!C:C,'Marzo Data'!A:A,B82,'Marzo Data'!B:B,F82) -> 2320232.6 | H82: =VLOOKUP(B82,'Marzo Data'!A:D,4,FALSE) -> UESP1649 | I82: POLIKEM S.A.S | J82: =J76+1 -> 656
A83: Polikem S.A.S | B83: POLIKEM S.A.S | C83: total | D83: Mandato | E83: Rionegro | F83: Interes | G83: =SUMIFS('Marzo Data'!C:C,'Marzo Data'!A:A,B83,'Marzo Data'!B:B,F83) -> 0 | H83: =VLOOKUP(B83,'Marzo Data'!A:D,4,FALSE) -> UESP1649 | I83: POLIKEM S.A.S
A84: Polikem S.A.S | B84: POLIKEM S.A.S | C84: total | D84: Mandato | F84: Retención en la fuente | G84: =(G82+G83)*4% -> 92809.304 | H84: =VLOOKUP(B84,'Marzo Data'!A:D,4,FALSE) -> UESP1649 | I84: POLIKEM S.A.S
A85: Polikem S.A.S | B85: POLIKEM S.A.S | C85: total | D85: Mandato | F85: ICA | G85: =(G82+G83)*0.4% -> 9280.9304 | H85: =VLOOKUP(B85,'Marzo Data'!A:D,4,FALSE) -> UESP1649 | I85: POLIKEM S.A.S
A86: Polikem S.A.S | B86: POLIKEM S.A.S | C86: total | D86: Mandato | E86: Rionegro | F86: Valor a Pagar | G86: =G82+G83-G84-G85 -> 2218142.4 | H86: =VLOOKUP(B86,'Marzo Data'!A:D,4,FALSE) -> UESP1649
A87: Polikem S.A.S | B87: POLIKEM S.A.S | C87: Factura | D87: Factura | F87: Administración | G87: =G86*5% -> 110907.12 | H87: =VLOOKUP(B87,'Marzo Data'!A:D,4,FALSE) -> UESP1649 | I87: POLIKEM S.A.S
A88: Polikem S.A.S | B88: POLIKEM S.A.S | C88: Factura | D88: Factura | F88: Total | G88: =G87 -> 110907.12 | H88: =VLOOKUP(B88,'Marzo Data'!A:D,4,FALSE) -> UESP1649 | I88: POLIKEM S.A.S
A89: Servicios Industriales Y Metalmecanicos Sas | B89: SERVICIOS INDUSTRIALES Y METALMECANICOS SAS | C89: Total | D89: Mandato | E89: Cartagena De Indias | F89: Ingreso Bruto | G89: =SUMIFS('Marzo Data'!C:C,'Marzo Data'!A:A,B89,'Marzo Data'!B:B,F89) -> 4490253.3 | H89: =VLOOKUP(B89,'Marzo Data'!A:D,4,FALSE) -> UESP1661 | I89: SERVICIOS INDUSTRIALES Y METALMECANICOS SAS | J89: =J82+1 -> 657
A90: Servicios Industriales Y Metalmecanicos Sas | B90: SERVICIOS INDUSTRIALES Y METALMECANICOS SAS | C90: total | D90: Mandato | E90: Cartagena De Indias | F90: Interes | G90: =SUMIFS('Marzo Data'!C:C,'Marzo Data'!A:A,B90,'Marzo Data'!B:B,F90) -> 19723.55 | H90: =VLOOKUP(B90,'Marzo Data'!A:D,4,FALSE) -> UESP1661 | I90: SERVICIOS INDUSTRIALES Y METALMECANICOS SAS
A91: Servicios Industriales Y Metalmecanicos Sas | B91: SERVICIOS INDUSTRIALES Y METALMECANICOS SAS | C91: total | D91: Mandato | E91: Cartagena De Indias | F91: Valor a Pagar | G91: =G90+G89 -> 4509976.8 | H91: =VLOOKUP(B91,'Marzo Data'!A:D,4,FALSE) -> UESP1661
A92: Servicios Industriales Y Metalmecanicos Sas | B92: SERVICIOS INDUSTRIALES Y METALMECANICOS SAS | C92: Factura | D92: Factura | F92: Administración | G92: =G91*5% -> 225498.84 | H92: =VLOOKUP(B92,'Marzo Data'!A:D,4,FALSE) -> UESP1661 | I92: SERVICIOS INDUSTRIALES Y METALMECANICOS SAS
A93: Servicios Industriales Y Metalmecanicos Sas | B93: SERVICIOS INDUSTRIALES Y METALMECANICOS SAS | C93: Factura | D93: Factura | F93: Total | G93: =G92 -> 225498.84 | H93: =VLOOKUP(B93,'Marzo Data'!A:D,4,FALSE) -> UESP1661 | I93: SERVICIOS INDUSTRIALES Y METALMECANICOS SAS
A94: Sociedad Educativa Ngs Sas | B94: SOCIEDAD EDUCATIVA NGS SAS | C94: Total | D94: Mandato | E94: Villavicencio | F94: Ingreso Bruto | G94: =SUMIFS('Marzo Data'!C:C,'Marzo Data'!A:A,B94,'Marzo Data'!B:B,F94) -> 2098339.8 | H94: =VLOOKUP(B94,'Marzo Data'!A:D,4,FALSE) -> UESP1666 | I94: SOCIEDAD EDUCATIVA NGS SAS | J94: =J89+1 -> 658
A95: Sociedad Educativa Ngs Sas | B95: SOCIEDAD EDUCATIVA NGS SAS | C95: total | D95: Mandato | E95: Villavicencio | F95: Interes | G95: =SUMIFS('Marzo Data'!C:C,'Marzo Data'!A:A,B95,'Marzo Data'!B:B,F95) -> 0 | H95: =VLOOKUP(B95,'Marzo Data'!A:D,4,FALSE) -> UESP1666 | I95: SOCIEDAD EDUCATIVA NGS SAS
A96: Sociedad Educativa Ngs Sas | B96: SOCIEDAD EDUCATIVA NGS SAS | C96: total | D96: Mandato | E96: Villavicencio | F96: Valor a Pagar | G96: =G95+G94 -> 2098339.8 | H96: =VLOOKUP(B96,'Marzo Data'!A:D,4,FALSE) -> UESP1666
A97: Sociedad Educativa Ngs Sas | B97: SOCIEDAD EDUCATIVA NGS SAS | C97: Factura | D97: Factura | F97: Administración | G97: =G96*5% -> 104916.99 | H97: =VLOOKUP(B97,'Marzo Data'!A:D,4,FALSE) -> UESP1666 | I97: SOCIEDAD EDUCATIVA NGS SAS
A98: Sociedad Educativa Ngs Sas | B98: SOCIEDAD EDUCATIVA NGS SAS | C98: Factura | D98: Factura | F98: Total | G98: =G97 -> 104916.99 | H98: =VLOOKUP(B98,'Marzo Data'!A:D,4,FALSE) -> UESP1666 | I98: SOCIEDAD EDUCATIVA NGS SAS
A99: Sociedad Medica Rionegro S.A. Somer S.A. | B99: SOCIEDAD MEDICA RIONEGRO S.A. SOMER S.A. | C99: Total | D99: Mandato | E99: Rionegro | F99: Ingreso Bruto | G99: =SUMIFS('Marzo Data'!C:C,'Marzo Data'!A:A,B99,'Marzo Data'!B:B,F99) -> 13102955 | H99: =VLOOKUP(B99,'Marzo Data'!A:D,4,FALSE) -> UESP1653 | I99: SOCIEDAD MEDICA RIONEGRO S.A. SOMER S.A. | J99: =J94+1 -> 659
A100: Sociedad Medica Rionegro S.A. Somer S.A. | B100: SOCIEDAD MEDICA RIONEGRO S.A. SOMER S.A. | C100: total | D100: Mandato | E100: Rionegro | F100: Interes | G100: =SUMIFS('Marzo Data'!C:C,'Marzo Data'!A:A,B100,'Marzo Data'!B:B,F100) -> 0 | H100: =VLOOKUP(B100,'Marzo Data'!A:D,4,FALSE) -> UESP1653 | I100: SOCIEDAD MEDICA RIONEGRO S.A. SOMER S.A.
...

Sheet Abril
A1: Proyecto | B1: CLIENTE | C1: Inversionista | D1: Documento contable | E1: Ciudad | F1: Concepto | G1: Total | H1: Factura | I1: ID ODOO | J1: Codigo | L1: Generar | M1: Proyecto | N1: Carpeta proyecto | O1: Factura | Q1: Fecha de Firma | R1: 46155 | S1: Fecha periodo | T1: 01 al 31 de abril del 2026 | U1: consecutivo final | V1: 769
A2: Almacen Amc Sas | B2: ALMACEN AMC SAS | C2: Total | D2: Mandato | E2: Sincelejo | F2: Ingreso Bruto | G2: =SUMIFS('Abril Data'!C:C,'Abril Data'!A:A,B2,'Abril Data'!B:B,F2) -> 4667178.4 | H2: =VLOOKUP(B2,'Abril Data'!A:D,4,FALSE) -> UESP1772 | I2: ALMACEN AMC SAS | J2: =V1 -> 769 | L2: TRUE | M2: Almacen Amc Sas | N2: AMC
A3: Almacen Amc Sas | B3: ALMACEN AMC SAS | C3: total | D3: Mandato | E3: Sincelejo | F3: Interes | G3: =SUMIFS('Abril Data'!C:C,'Abril Data'!A:A,B3,'Abril Data'!B:B,F3) -> 186419.25 | H3: =VLOOKUP(B3,'Abril Data'!A:D,4,FALSE) -> UESP1772 | I3: ALMACEN AMC SAS | L3: TRUE
A4: Almacen Amc Sas | B4: ALMACEN AMC SAS | C4: total | D4: Mandato | E4: Sincelejo | F4: Valor a Pagar | G4: =G2+G3 -> 4853597.6 | H4: =VLOOKUP(B4,'Abril Data'!A:D,4,FALSE) -> UESP1772 | L4: TRUE | M4: Central De Maderas G&S S.A.S. | N4: Central de maderas
A5: Almacen Amc Sas | B5: ALMACEN AMC SAS | C5: Factura | D5: Factura | E5: Sincelejo | F5: Administración | G5: =G4*5% -> 242679.88 | H5: =VLOOKUP(B5,'Abril Data'!A:D,4,FALSE) -> UESP1772 | I5: ALMACEN AMC SAS | L5: TRUE | M5: Centro Comercial Y Empresarial Obelisco - P.H.- | N5: Obelisco
A6: Almacen Amc Sas | B6: ALMACEN AMC SAS | C6: Factura | D6: Factura | E6: Sincelejo | F6: Total | G6: =G5 -> 242679.88 | H6: =VLOOKUP(B6,'Abril Data'!A:D,4,FALSE) -> UESP1772 | I6: ALMACEN AMC SAS | L6: TRUE | M6: Condominio Acanto P. H | N6: Acanto
A7: Arcillas San Simon S.A.S. | B7: ARCILLAS SAN SIMON S.A.S. | C7: Total | D7: Mandato | E7: El Zulia | F7: Mantenimiento CENS | G7: 0 | H7: =VLOOKUP(B7,'Abril Data'!A:D,4,FALSE) -> #N/A | J7: 759 | L7: TRUE
A8: Arcillas San Simon S.A.S. | B8: ARCILLAS SAN SIMON S.A.S. | C8: total | D8: Mandato | E8: El Zulia | F8: Interes | G8: =SUMIFS('Abril Data'!C:C,'Abril Data'!A:A,B8,'Abril Data'!B:B,F8) -> 0 | H8: =VLOOKUP(B8,'Abril Data'!A:D,4,FALSE) -> #N/A | L8: TRUE | M8: Arcillas San Simon S.A.S.
A9: Arcillas San Simon S.A.S. | B9: ARCILLAS SAN SIMON S.A.S. | C9: total | D9: Mandato | E9: El Zulia | F9: Valor a Pagar | G9: =G8+G7 -> 0 | H9: =VLOOKUP(B9,'Abril Data'!A:D,4,FALSE) -> #N/A | L9: TRUE
A10: Arcillas San Simon S.A.S. | B10: ARCILLAS SAN SIMON S.A.S. | C10: Factura | D10: Factura | E10: El Zulia | F10: Administración | G10: =G9*5% -> 0 | H10: =VLOOKUP(B10,'Abril Data'!A:D,4,FALSE) -> #N/A | L10: TRUE
A11: Arcillas San Simon S.A.S. | B11: ARCILLAS SAN SIMON S.A.S. | C11: Factura | D11: Factura | E11: El Zulia | F11: Total | G11: =G10 -> 0 | H11: =VLOOKUP(B11,'Abril Data'!A:D,4,FALSE) -> #N/A | L11: TRUE
A12: Central De Maderas G&S S.A.S. | B12: CENTRAL DE MADERAS G&S SAS | C12: Total | D12: Mandato | E12: Turbaná | F12: Ingreso Bruto | G12: =SUMIFS('Abril Data'!C:C,'Abril Data'!A:A,B12,'Abril Data'!B:B,F12) -> 3809524.3 | H12: =VLOOKUP(B12,'Abril Data'!A:D,4,FALSE) -> UESP1778 | I12: CENTRAL DE MADERAS G&S SAS | J12: =J2+1 -> 770 | L12: TRUE | M12: Congregación De Religiosas Hijas De Cristo Rey | N12: Cristo Rey
A13: Central De Maderas G&S S.A.S. | B13: CENTRAL DE MADERAS G&S SAS | C13: total | D13: Mandato | E13: Turbaná | F13: Interes | G13: =SUMIFS('Abril Data'!C:C,'Abril Data'!A:A,B13,'Abril Data'!B:B,F13) -> 85957.03 | H13: =VLOOKUP(B13,'Abril Data'!A:D,4,FALSE) -> UESP1778 | I13: CENTRAL DE MADERAS G&S SAS | L13: TRUE | M13: Conjunto Laureles Campestre Etapas I Ii Y Iii Ph | N13: Laureles Campestre
A14: Central De Maderas G&S S.A.S. | B14: CENTRAL DE MADERAS G&S SAS | C14: total | D14: Mandato | F14: Retención en la fuente | G14: =(G12+G13)*4% -> 155819.25 | H14: =VLOOKUP(B14,'Abril Data'!A:D,4,FALSE) -> UESP1778 | I14: CENTRAL DE MADERAS G&S SAS | L14: TRUE | M14: Conjunto Residencial San Esteban Del Poblado P.H. | N14: San Esteban
A15: Central De Maderas G&S S.A.S. | B15: CENTRAL DE MADERAS G&S SAS | C15: total | D15: Mandato | E15: Turbaná | F15: Valor a Pagar | G15: =G12+G13-G14 -> 3739662.1 | H15: =VLOOKUP(B15,'Abril Data'!A:D,4,FALSE) -> UESP1778 | L15: TRUE | M15: Cooperativa Antioqueña De Salud | N15: coopsana ips
A16: Central De Maderas G&S S.A.S. | B16: CENTRAL DE MADERAS G&S SAS | C16: Factura | D16: Factura | E16: Turbaná | F16: Administración | G16: =G15*5% -> 186983.1 | H16: =VLOOKUP(B16,'Abril Data'!A:D,4,FALSE) -> UESP1778 | I16: CENTRAL DE MADERAS G&S SAS | L16: TRUE | M16: Dual Cross S.A.S | N16: Cross Bisnes center
A17: Central De Maderas G&S S.A.S. | B17: CENTRAL DE MADERAS G&S SAS | C17: Factura | D17: Factura | E17: Turbaná | F17: Total | G17: =G16 -> 186983.1 | H17: =VLOOKUP(B17,'Abril Data'!A:D,4,FALSE) -> UESP1778 | I17: CENTRAL DE MADERAS G&S SAS | L17: TRUE | M17: Ecoimagen Salud S.A.S | N17: Ecoimagen ips
A18: Centro Comercial Y Empresarial Obelisco - P.H.- | B18: CENTRO COMERCIAL Y EMPRESARIAL OBELISCO - P.H.- | C18: Total | D18: Mandato | E18: Medellín | F18: Ingreso Bruto | G18: =SUMIFS('Abril Data'!C:C,'Abril Data'!A:A,B18,'Abril Data'!B:B,F18) -> 6920127.2 | H18: =VLOOKUP(B18,'Abril Data'!A:D,4,FALSE) -> UESP1782 | I18: CENTRO COMERCIAL Y EMPRESARIAL OBELISCO -P.H.- | J18: =J12+1 -> 771 | L18: TRUE | M18: Edificio Torre Almagran Propiedad Horizontal | N18: Almagran
A19: Centro Comercial Y Empresarial Obelisco - P.H.- | B19: CENTRO COMERCIAL Y EMPRESARIAL OBELISCO - P.H.- | C19: total | D19: Mandato | E19: Medellín | F19: Interes | G19: =SUMIFS('Abril Data'!C:C,'Abril Data'!A:A,B19,'Abril Data'!B:B,F19) -> 0 | H19: =VLOOKUP(B19,'Abril Data'!A:D,4,FALSE) -> UESP1782 | I19: CENTRO COMERCIAL Y EMPRESARIAL OBELISCO -P.H.- | L19: TRUE | M19: Instituto Bolivariano (Ibes) | N19: instituto bolivariano (ibes)
A20: Centro Comercial Y Empresarial Obelisco - P.H.- | B20: CENTRO COMERCIAL Y EMPRESARIAL OBELISCO - P.H.- | C20: total | D20: Mandato | E20: Medellín | F20: Valor a Pagar | G20: =G19+G18 -> 6920127.2 | H20: =VLOOKUP(B20,'Abril Data'!A:D,4,FALSE) -> UESP1782 | L20: TRUE | M20: Los Coches | N20: Hotel los coches
A21: Centro Comercial Y Empresarial Obelisco - P.H.- | B21: CENTRO COMERCIAL Y EMPRESARIAL OBELISCO - P.H.- | C21: Factura | D21: Factura | F21: Administración | G21: =G20*5% -> 346006.36 | H21: =VLOOKUP(B21,'Abril Data'!A:D,4,FALSE) -> UESP1782 | I21: CENTRO COMERCIAL Y EMPRESARIAL OBELISCO -P.H.- | L21: TRUE | M21: M.D.M. Cientifica S.A.S | N21: MDM Cientifica
A22: Centro Comercial Y Empresarial Obelisco - P.H.- | B22: CENTRO COMERCIAL Y EMPRESARIAL OBELISCO - P.H.- | C22: Factura | D22: Factura | F22: Total | G22: =G21 -> 346006.36 | H22: =VLOOKUP(B22,'Abril Data'!A:D,4,FALSE) -> UESP1782 | I22: CENTRO COMERCIAL Y EMPRESARIAL OBELISCO -P.H.- | L22: TRUE | M22: Polikem S.A.S | N22: Polikem
A23: Condominio Acanto P. H | B23: CONDOMINIO ACANTO Ρ. Η | C23: Total | D23: Mandato | E23: Envigado | F23: Ingreso Bruto | G23: =SUMIFS('Abril Data'!C:C,'Abril Data'!A:A,B23,'Abril Data'!B:B,F23) -> 5799515.4 | H23: =VLOOKUP(B23,'Abril Data'!A:D,4,FALSE) -> UESP1770 | I23: CONDOMINIO ACANTO P. H | J23: =J18+1 -> 772 | L23: TRUE | M23: Servicios Industriales Y Metalmecanicos Sas | N23: Seridme
A24: Condominio Acanto P. H | B24: CONDOMINIO ACANTO Ρ. Η | C24: total | D24: Mandato | E24: Envigado | F24: Interes | G24: =SUMIFS('Abril Data'!C:C,'Abril Data'!A:A,B24,'Abril Data'!B:B,F24) -> 31968.92 | H24: =VLOOKUP(B24,'Abril Data'!A:D,4,FALSE) -> UESP1770 | I24: CONDOMINIO ACANTO P. H | L24: TRUE | M24: Sociedad Educativa Ngs Sas | N24: NGS
A25: Condominio Acanto P. H | B25: CONDOMINIO ACANTO Ρ. Η | C25: total | D25: Mandato | E25: Envigado | F25: Valor a Pagar | G25: =G24+G23 -> 5831484.3 | H25: =VLOOKUP(B25,'Abril Data'!A:D,4,FALSE) -> UESP1770 | L25: TRUE | M25: Sociedad Medica Rionegro S.A. Somer S.A. | N25: Clinica Somer
A26: Condominio Acanto P. H | B26: CONDOMINIO ACANTO Ρ. Η | C26: Factura | D26: Factura | F26: Administración | G26: =G25*5% -> 291574.22 | H26: =VLOOKUP(B26,'Abril Data'!A:D,4,FALSE) -> UESP1770 | I26: CONDOMINIO ACANTO P. H | L26: TRUE | M26: The Pub S. A. S. | N26: Pola Del Pub
A27: Condominio Acanto P. H | B27: CONDOMINIO ACANTO Ρ. Η | C27: Factura | D27: Factura | F27: Total | G27: =G26 -> 291574.22 | H27: =VLOOKUP(B27,'Abril Data'!A:D,4,FALSE) -> UESP1770 | I27: CONDOMINIO ACANTO P. H | L27: TRUE | M27: Urbanizacion Arboleda De Castilla Propiedad Horizontal | N27: arboleda de castilla
A28: Congregación De Religiosas Hijas De Cristo Rey | B28: CONGREGACIÓN DE RELIGIOSAS HIJAS DE CRISTO REY | C28: Total | D28: Mandato | E28: Bogotá, D.C. | F28: Ingreso Bruto | G28: =SUMIFS('Abril Data'!C:C,'Abril Data'!A:A,B28,'Abril Data'!B:B,F28) -> 2402148.8 | H28: =VLOOKUP(B28,'Abril Data'!A:D,4,FALSE) -> UESP1764 | I28: CONGREGACIÓN DE RELIGIOSAS HIJAS DE CRISTO REY | J28: =J23+1 -> 773
A29: Congregación De Religiosas Hijas De Cristo Rey | B29: CONGREGACIÓN DE RELIGIOSAS HIJAS DE CRISTO REY | C29: total | D29: Mandato | E29: Bogotá, D.C. | F29: Interes | G29: =SUMIFS('Abril Data'!C:C,'Abril Data'!A:A,B29,'Abril Data'!B:B,F29) -> 52438.59 | H29: =VLOOKUP(B29,'Abril Data'!A:D,4,FALSE) -> UESP1764 | I29: CONGREGACIÓN DE RELIGIOSAS HIJAS DE CRISTO REY
A30: Congregación De Religiosas Hijas De Cristo Rey | B30: CONGREGACIÓN DE RELIGIOSAS HIJAS DE CRISTO REY | C30: total | D30: Mandato | E30: Bogotá, D.C. | F30: Valor a Pagar | G30: =G29+G28 -> 2454587.4 | H30: =VLOOKUP(B30,'Abril Data'!A:D,4,FALSE) -> UESP1764
A31: Congregación De Religiosas Hijas De Cristo Rey | B31: CONGREGACIÓN DE RELIGIOSAS HIJAS DE CRISTO REY | C31: Factura | D31: Factura | F31: Administración | G31: =G30*5% -> 122729.37 | H31: =VLOOKUP(B31,'Abril Data'!A:D,4,FALSE) -> UESP1764 | I31: CONGREGACIÓN DE RELIGIOSAS HIJAS DE CRISTO REY
A32: Congregación De Religiosas Hijas De Cristo Rey | B32: CONGREGACIÓN DE RELIGIOSAS HIJAS DE CRISTO REY | C32: Factura | D32: Factura | F32: Total | G32: =G31 -> 122729.37 | H32: =VLOOKUP(B32,'Abril Data'!A:D,4,FALSE) -> UESP1764 | I32: CONGREGACIÓN DE RELIGIOSAS HIJAS DE CRISTO REY
A33: Conjunto Laureles Campestre Etapas I Ii Y Iii Ph | B33: CONJUNTO LAURELES CAMPESTRE ETAPAS I II Y III | C33: Total | D33: Mandato | E33: Medellín | F33: Ingreso Bruto | G33: =SUMIFS('Abril Data'!C:C,'Abril Data'!A:A,B33,'Abril Data'!B:B,F33) -> 0 | H33: =VLOOKUP(B33,'Abril Data'!A:D,4,FALSE) -> #N/A | I33: CONJUNTO LAURELES CAMPESTRE ETAPAS I II Y III PH
A34: Conjunto Laureles Campestre Etapas I Ii Y Iii Ph | B34: CONJUNTO LAURELES CAMPESTRE ETAPAS I II Y III | C34: total | D34: Mandato | E34: Medellín | F34: Interes | G34: =SUMIFS('Abril Data'!C:C,'Abril Data'!A:A,B34,'Abril Data'!B:B,F34) -> 0 | H34: =VLOOKUP(B34,'Abril Data'!A:D,4,FALSE) -> #N/A | I34: CONJUNTO LAURELES CAMPESTRE ETAPAS I II Y III PH
A35: Conjunto Laureles Campestre Etapas I Ii Y Iii Ph | B35: CONJUNTO LAURELES CAMPESTRE ETAPAS I II Y III | C35: total | D35: Mandato | E35: Medellín | F35: Valor a Pagar | G35: =G34+G33 -> 0 | H35: =VLOOKUP(B35,'Abril Data'!A:D,4,FALSE) -> #N/A
A36: Conjunto Laureles Campestre Etapas I Ii Y Iii Ph | B36: CONJUNTO LAURELES CAMPESTRE ETAPAS I II Y III | C36: Factura | D36: Factura | F36: Administración | G36: =G35*5% -> 0 | H36: =VLOOKUP(B36,'Abril Data'!A:D,4,FALSE) -> #N/A | I36: CONJUNTO LAURELES CAMPESTRE ETAPAS I II Y III PH
A37: Conjunto Laureles Campestre Etapas I Ii Y Iii Ph | B37: CONJUNTO LAURELES CAMPESTRE ETAPAS I II Y III | C37: Factura | D37: Factura | F37: Total | G37: =G36 -> 0 | H37: =VLOOKUP(B37,'Abril Data'!A:D,4,FALSE) -> #N/A | I37: CONJUNTO LAURELES CAMPESTRE ETAPAS I II Y III PH
A38: Conjunto Residencial San Esteban Del Poblado P.H. | B38: CONJUNTO RESIDENCIAL SAN ESTEBAN DEL POBLADO P.H. | C38: Total | D38: Mandato | E38: Medellín | F38: Ingreso Bruto | G38: =SUMIFS('Abril Data'!C:C,'Abril Data'!A:A,B38,'Abril Data'!B:B,F38) -> 3114129.6 | H38: =VLOOKUP(B38,'Abril Data'!A:D,4,FALSE) -> UESP1780 | I38: CONJUNTO RESIDENCIAL SAN ESTEBAN DEL POBLADO P.H. | J38: =J28+1 -> 774
A39: Conjunto Residencial San Esteban Del Poblado P.H. | B39: CONJUNTO RESIDENCIAL SAN ESTEBAN DEL POBLADO P.H. | C39: total | D39: Mandato | E39: Medellín | F39: Interes | G39: =SUMIFS('Abril Data'!C:C,'Abril Data'!A:A,B39,'Abril Data'!B:B,F39) -> 19254.71 | H39: =VLOOKUP(B39,'Abril Data'!A:D,4,FALSE) -> UESP1780 | I39: CONJUNTO RESIDENCIAL SAN ESTEBAN DEL POBLADO P.H.
A40: Conjunto Residencial San Esteban Del Poblado P.H. | B40: CONJUNTO RESIDENCIAL SAN ESTEBAN DEL POBLADO P.H. | C40: total | D40: Mandato | E40: Medellín | F40: Valor a Pagar | G40: =G39+G38 -> 3133384.3 | H40: =VLOOKUP(B40,'Abril Data'!A:D,4,FALSE) -> UESP1780
A41: Conjunto Residencial San Esteban Del Poblado P.H. | B41: CONJUNTO RESIDENCIAL SAN ESTEBAN DEL POBLADO P.H. | C41: Factura | D41: Factura | F41: Administración | G41: =G40*5% -> 156669.21 | H41: =VLOOKUP(B41,'Abril Data'!A:D,4,FALSE) -> UESP1780 | I41: CONJUNTO RESIDENCIAL SAN ESTEBAN DEL POBLADO P.H.
A42: Conjunto Residencial San Esteban Del Poblado P.H. | B42: CONJUNTO RESIDENCIAL SAN ESTEBAN DEL POBLADO P.H. | C42: Factura | D42: Factura | F42: Total | G42: =G41 -> 156669.21 | H42: =VLOOKUP(B42,'Abril Data'!A:D,4,FALSE) -> UESP1780 | I42: CONJUNTO RESIDENCIAL SAN ESTEBAN DEL POBLADO P.H.
A43: Cooperativa Antioqueña De Salud | B43: COOPERATIVA ANTIOQUEÑA DE SALUD | C43: Total | D43: Mandato | E43: Medellín | F43: Ingreso Bruto | G43: =SUMIFS('Abril Data'!C:C,'Abril Data'!A:A,B43,'Abril Data'!B:B,F43) -> 2617489.7 | H43: =VLOOKUP(B43,'Abril Data'!A:D,4,FALSE) -> UESP1766 | I43: COOPERATIVA ANTIOQUEÑA DE SALUD | J43: =J38+1 -> 775
A44: Cooperativa Antioqueña De Salud | B44: COOPERATIVA ANTIOQUEÑA DE SALUD | C44: Total | D44: Mandato | E44: Medellín | F44: Interes | G44: =SUMIFS('Abril Data'!C:C,'Abril Data'!A:A,B44,'Abril Data'!B:B,F44) -> 498227.47 | H44: =VLOOKUP(B44,'Abril Data'!A:D,4,FALSE) -> UESP1766 | I44: COOPERATIVA ANTIOQUEÑA DE SALUD
A45: Cooperativa Antioqueña De Salud | B45: COOPERATIVA ANTIOQUEÑA DE SALUD | C45: Total | D45: Mandato | E45: Medellín | F45: Valor a Pagar | G45: =G44+G43 -> 3115717.1 | H45: =VLOOKUP(B45,'Abril Data'!A:D,4,FALSE) -> UESP1766
A46: Cooperativa Antioqueña De Salud | B46: COOPERATIVA ANTIOQUEÑA DE SALUD | C46: Factura | D46: Factura | F46: Administración | G46: =G45*5% -> 155785.86 | H46: =VLOOKUP(B46,'Abril Data'!A:D,4,FALSE) -> UESP1766 | I46: COOPERATIVA ANTIOQUEÑA DE SALUD
A47: Cooperativa Antioqueña De Salud | B47: COOPERATIVA ANTIOQUEÑA DE SALUD | C47: Factura | D47: Factura | F47: Total | G47: =G46 -> 155785.86 | H47: =VLOOKUP(B47,'Abril Data'!A:D,4,FALSE) -> UESP1766 | I47: COOPERATIVA ANTIOQUEÑA DE SALUD
A48: Dual Cross S.A.S | B48: DUAL CROSS S.A.S | C48: Total | D48: Mandato | E48: Medellín | F48: Ingreso Bruto | G48: =SUMIFS('Abril Data'!C:C,'Abril Data'!A:A,B48,'Abril Data'!B:B,F48) -> 3378348 | H48: =VLOOKUP(B48,'Abril Data'!A:D,4,FALSE) -> UESP1777 | I48: DUAL CROSS S.A.S | J48: =J43+1 -> 776
A49: Dual Cross S.A.S | B49: DUAL CROSS S.A.S | C49: total | D49: Mandato | E49: Medellín | F49: Interes | G49: =SUMIFS('Abril Data'!C:C,'Abril Data'!A:A,B49,'Abril Data'!B:B,F49) -> 25892.95 | H49: =VLOOKUP(B49,'Abril Data'!A:D,4,FALSE) -> UESP1777 | I49: DUAL CROSS S.A.S
A50: Dual Cross S.A.S | B50: DUAL CROSS S.A.S | C50: total | D50: Mandato | F50: Retención en la fuente | G50: =(G48+G49)*4% -> 136169.64 | H50: =VLOOKUP(B50,'Abril Data'!A:D,4,FALSE) -> UESP1777 | I50: DUAL CROSS S.A.S
A51: Dual Cross S.A.S | B51: DUAL CROSS S.A.S | C51: total | D51: Mandato | E51: Medellín | F51: Valor a Pagar | G51: =G48+G49-G50 -> 3268071.3 | H51: =VLOOKUP(B51,'Abril Data'!A:D,4,FALSE) -> UESP1777
A52: Dual Cross S.A.S | B52: DUAL CROSS S.A.S | C52: Factura | D52: Factura | F52: Administración | G52: =G51*5% -> 163403.56 | H52: =VLOOKUP(B52,'Abril Data'!A:D,4,FALSE) -> UESP1777 | I52: DUAL CROSS S.A.S
A53: Dual Cross S.A.S | B53: DUAL CROSS S.A.S | C53: Factura | D53: Factura | F53: Total | G53: =G52 -> 163403.56 | H53: =VLOOKUP(B53,'Abril Data'!A:D,4,FALSE) -> UESP1777 | I53: DUAL CROSS S.A.S
A54: Ecoimagen Salud S.A.S | B54: ECOIMAGEN SALUD S.A.S | C54: Total | D54: Mandato | E54: Cúcuta | F54: Ingreso Bruto | G54: =SUMIFS('Abril Data'!C:C,'Abril Data'!A:A,B54,'Abril Data'!B:B,F54) -> 1660537.4 | H54: =VLOOKUP(B54,'Abril Data'!A:D,4,FALSE) -> UESP1769 | I54: ECOIMAGEN SALUD S.A.S | J54: =J48+1 -> 777
A55: Ecoimagen Salud S.A.S | B55: ECOIMAGEN SALUD S.A.S | C55: total | D55: Mandato | E55: Cúcuta | F55: Interes | G55: =SUMIFS('Abril Data'!C:C,'Abril Data'!A:A,B55,'Abril Data'!B:B,F55) -> 8807.24 | H55: =VLOOKUP(B55,'Abril Data'!A:D,4,FALSE) -> UESP1769 | I55: ECOIMAGEN SALUD S.A.S
A56: Ecoimagen Salud S.A.S | B56: ECOIMAGEN SALUD S.A.S | C56: total | D56: Mandato | E56: Cúcuta | F56: Retención en la fuente | G56: =(G54+G55)*2.5% -> 41733.616 | H56: =VLOOKUP(B56,'Abril Data'!A:D,4,FALSE) -> UESP1769 | I56: ECOIMAGEN SALUD S.A.S
A57: Ecoimagen Salud S.A.S | B57: ECOIMAGEN SALUD S.A.S | C57: total | D57: Mandato | E57: Cúcuta | F57: Valor a Pagar | G57: =G54+G55-G56 -> 1627611
A58: Ecoimagen Salud S.A.S | B58: ECOIMAGEN SALUD S.A.S | C58: Factura | D58: Factura | F58: Administración | G58: =G57*5% -> 81380.551 | H58: =VLOOKUP(B58,'Abril Data'!A:D,4,FALSE) -> UESP1769 | I58: ECOIMAGEN SALUD S.A.S
A59: Ecoimagen Salud S.A.S | B59: ECOIMAGEN SALUD S.A.S | C59: Factura | D59: Factura | F59: Total | G59: =G58 -> 81380.551 | H59: =VLOOKUP(B59,'Abril Data'!A:D,4,FALSE) -> UESP1769 | I59: ECOIMAGEN SALUD S.A.S
A60: Edificio Torre Almagran Propiedad Horizontal | B60: EDIFICIO TORRE ALMAGRAN PROPIEDAD HORIZONTAL | C60: Total | D60: Mandato | E60: Medellín | F60: Ingreso Bruto | G60: =SUMIFS('Abril Data'!C:C,'Abril Data'!A:A,B60,'Abril Data'!B:B,F60) -> 1925343.5 | H60: =VLOOKUP(B60,'Abril Data'!A:D,4,FALSE) -> UESP1771 | I60: EDIFICIO TORRE ALMAGRAN PROPIEDAD HORIZONTAL | J60: =J54+1 -> 778
A61: Edificio Torre Almagran Propiedad Horizontal | B61: EDIFICIO TORRE ALMAGRAN PROPIEDAD HORIZONTAL | C61: total | D61: Mandato | E61: Medellín | F61: Interes | G61: =SUMIFS('Abril Data'!C:C,'Abril Data'!A:A,B61,'Abril Data'!B:B,F61) -> 0 | H61: =VLOOKUP(B61,'Abril Data'!A:D,4,FALSE) -> UESP1771 | I61: EDIFICIO TORRE ALMAGRAN PROPIEDAD HORIZONTAL
A62: Edificio Torre Almagran Propiedad Horizontal | B62: EDIFICIO TORRE ALMAGRAN PROPIEDAD HORIZONTAL | C62: total | D62: Mandato | F62: Retención en la fuente | G62: =(G60+G61)*2.5% -> 48133.587 | H62: =VLOOKUP(B62,'Abril Data'!A:D,4,FALSE) -> UESP1771 | I62: EDIFICIO TORRE ALMAGRAN PROPIEDAD HORIZONTAL
A63: Edificio Torre Almagran Propiedad Horizontal | B63: EDIFICIO TORRE ALMAGRAN PROPIEDAD HORIZONTAL | C63: total | D63: Mandato | E63: Medellín | F63: Valor a Pagar | G63: =G60+G61-G62 -> 1877209.9 | H63: =VLOOKUP(B63,'Abril Data'!A:D,4,FALSE) -> UESP1771
A64: Edificio Torre Almagran Propiedad Horizontal | B64: EDIFICIO TORRE ALMAGRAN PROPIEDAD HORIZONTAL | C64: Factura | D64: Factura | F64: Administración | G64: =G63*5% -> 93860.495 | H64: =VLOOKUP(B64,'Abril Data'!A:D,4,FALSE) -> UESP1771 | I64: EDIFICIO TORRE ALMAGRAN PROPIEDAD HORIZONTAL
A65: Edificio Torre Almagran Propiedad Horizontal | B65: EDIFICIO TORRE ALMAGRAN PROPIEDAD HORIZONTAL | C65: Factura | D65: Factura | F65: Total | G65: =G64 -> 93860.495 | H65: =VLOOKUP(B65,'Abril Data'!A:D,4,FALSE) -> UESP1771 | I65: EDIFICIO TORRE ALMAGRAN PROPIEDAD HORIZONTAL
A66: Instituto Bolivariano (Ibes) | B66: CORREDOR NIÑO FRANK EDWIN | C66: Total | D66: Mandato | E66: Cúcuta | F66: Ingreso Bruto | G66: =SUMIFS('Abril Data'!C:C,'Abril Data'!A:A,B66,'Abril Data'!B:B,F66) -> 3173435.1 | H66: =VLOOKUP(B66,'Abril Data'!A:D,4,FALSE) -> UESP1773 | I66: CORREDOR NIÑO FRANK EDWIN | J66: =J60+1 -> 779
A67: Instituto Bolivariano (Ibes) | B67: CORREDOR NIÑO FRANK EDWIN | C67: total | D67: Mandato | E67: Cúcuta | F67: Interes | G67: =SUMIFS('Abril Data'!C:C,'Abril Data'!A:A,B67,'Abril Data'!B:B,F67) -> 66552.49 | H67: =VLOOKUP(B67,'Abril Data'!A:D,4,FALSE) -> UESP1773 | I67: CORREDOR NIÑO FRANK EDWIN
A68: Instituto Bolivariano (Ibes) | B68: CORREDOR NIÑO FRANK EDWIN | C68: total | D68: Mandato | E68: Cúcuta | F68: Valor a Pagar | G68: =G67+G66 -> 3239987.6 | H68: =VLOOKUP(B68,'Abril Data'!A:D,4,FALSE) -> UESP1773
A69: Instituto Bolivariano (Ibes) | B69: CORREDOR NIÑO FRANK EDWIN | C69: Factura | D69: Factura | F69: Administración | G69: =G68*5% -> 161999.38 | H69: =VLOOKUP(B69,'Abril Data'!A:D,4,FALSE) -> UESP1773 | I69: CORREDOR NIÑO FRANK EDWIN
A70: Instituto Bolivariano (Ibes) | B70: CORREDOR NIÑO FRANK EDWIN | C70: Factura | D70: Factura | F70: Total | G70: =G69 -> 161999.38 | H70: =VLOOKUP(B70,'Abril Data'!A:D,4,FALSE) -> UESP1773 | I70: CORREDOR NIÑO FRANK EDWIN
A71: Los Coches | B71: CORREA TOBON ALBERTO DE JESUS | C71: Total | D71: Mandato | E71: Montelíbano | F71: Ingreso Bruto | G71: =SUMIFS('Abril Data'!C:C,'Abril Data'!A:A,B71,'Abril Data'!B:B,F71) -> 2977236.3 | H71: =VLOOKUP(B71,'Abril Data'!A:D,4,FALSE) -> UESP1775 | I71: CORREA TOBON ALBERTO DE JESUS | J71: =J66+1 -> 780
A72: Los Coches | B72: CORREA TOBON ALBERTO DE JESUS | C72: total | D72: Mandato | E72: Montelíbano | F72: Interes | G72: =SUMIFS('Abril Data'!C:C,'Abril Data'!A:A,B72,'Abril Data'!B:B,F72) -> 0 | H72: =VLOOKUP(B72,'Abril Data'!A:D,4,FALSE) -> UESP1775 | I72: CORREA TOBON ALBERTO DE JESUS
A73: Los Coches | B73: CORREA TOBON ALBERTO DE JESUS | C73: total | D73: Mandato | E73: Montelíbano | F73: Valor a Pagar | G73: =G72+G71 -> 2977236.3 | H73: =VLOOKUP(B73,'Abril Data'!A:D,4,FALSE) -> UESP1775
A74: Los Coches | B74: CORREA TOBON ALBERTO DE JESUS | C74: Factura | D74: Factura | F74: Administración | G74: =G73*5% -> 148861.82 | H74: =VLOOKUP(B74,'Abril Data'!A:D,4,FALSE) -> UESP1775 | I74: CORREA TOBON ALBERTO DE JESUS
A75: Los Coches | B75: CORREA TOBON ALBERTO DE JESUS | C75: Factura | D75: Factura | F75: Total | G75: =G74 -> 148861.82 | H75: =VLOOKUP(B75,'Abril Data'!A:D,4,FALSE) -> UESP1775 | I75: CORREA TOBON ALBERTO DE JESUS
A76: M.D.M. Cientifica S.A.S | B76: M.D.M. CIENTIFICA S.A.S | C76: Total | D76: Mandato | E76: Medellín | F76: Ingreso Bruto | G76: =SUMIFS('Abril Data'!C:C,'Abril Data'!A:A,B76,'Abril Data'!B:B,F76) -> 3245814.2 | H76: =VLOOKUP(B76,'Abril Data'!A:D,4,FALSE) -> UESP1768 | I76: M.D.M. CIENTIFICA S.A.S | J76: =J71+1 -> 781
A77: M.D.M. Cientifica S.A.S | B77: M.D.M. CIENTIFICA S.A.S | C77: total | D77: Mandato | E77: Medellín | F77: Interes | G77: =SUMIFS('Abril Data'!C:C,'Abril Data'!A:A,B77,'Abril Data'!B:B,F77) -> 10161.45 | H77: =VLOOKUP(B77,'Abril Data'!A:D,4,FALSE) -> UESP1768 | I77: M.D.M. CIENTIFICA S.A.S
A78: M.D.M. Cientifica S.A.S | B78: M.D.M. CIENTIFICA S.A.S | C78: total | D78: Mandato | F78: Retención en la fuente | G78: =(G76+G77)*2.5% -> 81399.391 | H78: =VLOOKUP(B78,'Abril Data'!A:D,4,FALSE) -> UESP1768 | I78: M.D.M. CIENTIFICA S.A.S
A79: M.D.M. Cientifica S.A.S | B79: M.D.M. CIENTIFICA S.A.S | C79: total | D79: Mandato | E79: Medellín | F79: Valor a Pagar | G79: =G76+G77-G78 -> 3174576.2 | H79: =VLOOKUP(B79,'Abril Data'!A:D,4,FALSE) -> UESP1768
A80: M.D.M. Cientifica S.A.S | B80: M.D.M. CIENTIFICA S.A.S | C80: Factura | D80: Factura | F80: Administración | G80: =G79*5% -> 158728.81 | H80: =VLOOKUP(B80,'Abril Data'!A:D,4,FALSE) -> UESP1768 | I80: M.D.M. CIENTIFICA S.A.S
A81: M.D.M. Cientifica S.A.S | B81: M.D.M. CIENTIFICA S.A.S | C81: Factura | D81: Factura | F81: Total | G81: =G80 -> 158728.81 | H81: =VLOOKUP(B81,'Abril Data'!A:D,4,FALSE) -> UESP1768 | I81: M.D.M. CIENTIFICA S.A.S
A82: Polikem S.A.S | B82: POLIKEM S.A.S | C82: Total | D82: Mandato | E82: Rionegro | F82: Ingreso Bruto | G82: =SUMIFS('Abril Data'!C:C,'Abril Data'!A:A,B82,'Abril Data'!B:B,F82) -> 2075694.7 | H82: =VLOOKUP(B82,'Abril Data'!A:D,4,FALSE) -> UESP1765 | I82: POLIKEM S.A.S | J82: =J76+1 -> 782
A83: Polikem S.A.S | B83: POLIKEM S.A.S | C83: total | D83: Mandato | E83: Rionegro | F83: Interes | G83: =SUMIFS('Abril Data'!C:C,'Abril Data'!A:A,B83,'Abril Data'!B:B,F83) -> 611.22 | H83: =VLOOKUP(B83,'Abril Data'!A:D,4,FALSE) -> UESP1765 | I83: POLIKEM S.A.S
A84: Polikem S.A.S | B84: POLIKEM S.A.S | C84: total | D84: Mandato | F84: Retención en la fuente | G84: =(G82+G83)*4% -> 83052.236 | H84: =VLOOKUP(B84,'Abril Data'!A:D,4,FALSE) -> UESP1765 | I84: POLIKEM S.A.S
A85: Polikem S.A.S | B85: POLIKEM S.A.S | C85: total | D85: Mandato | F85: ICA | G85: =(G82+G83)*0.4% -> 8305.2236 | H85: =VLOOKUP(B85,'Abril Data'!A:D,4,FALSE) -> UESP1765 | I85: POLIKEM S.A.S
A86: Polikem S.A.S | B86: POLIKEM S.A.S | C86: total | D86: Mandato | E86: Rionegro | F86: Valor a Pagar | G86: =G82+G83-G84-G85 -> 1984948.4 | H86: =VLOOKUP(B86,'Abril Data'!A:D,4,FALSE) -> UESP1765
A87: Polikem S.A.S | B87: POLIKEM S.A.S | C87: Factura | D87: Factura | F87: Administración | G87: =G86*5% -> 99247.422 | H87: =VLOOKUP(B87,'Abril Data'!A:D,4,FALSE) -> UESP1765 | I87: POLIKEM S.A.S
A88: Polikem S.A.S | B88: POLIKEM S.A.S | C88: Factura | D88: Factura | F88: Total | G88: =G87 -> 99247.422 | H88: =VLOOKUP(B88,'Abril Data'!A:D,4,FALSE) -> UESP1765 | I88: POLIKEM S.A.S
A89: Servicios Industriales Y Metalmecanicos Sas | B89: SERVICIOS INDUSTRIALES Y METALMECANICOS SAS | C89: Total | D89: Mandato | E89: Cartagena De Indias | F89: Ingreso Bruto | G89: =SUMIFS('Abril Data'!C:C,'Abril Data'!A:A,B89,'Abril Data'!B:B,F89) -> 4065177.2 | H89: =VLOOKUP(B89,'Abril Data'!A:D,4,FALSE) -> UESP1774 | I89: SERVICIOS INDUSTRIALES Y METALMECANICOS SAS | J89: =J82+1 -> 783
A90: Servicios Industriales Y Metalmecanicos Sas | B90: SERVICIOS INDUSTRIALES Y METALMECANICOS SAS | C90: total | D90: Mandato | E90: Cartagena De Indias | F90: Interes | G90: =SUMIFS('Abril Data'!C:C,'Abril Data'!A:A,B90,'Abril Data'!B:B,F90) -> 26883.56 | H90: =VLOOKUP(B90,'Abril Data'!A:D,4,FALSE) -> UESP1774 | I90: SERVICIOS INDUSTRIALES Y METALMECANICOS SAS
A91: Servicios Industriales Y Metalmecanicos Sas | B91: SERVICIOS INDUSTRIALES Y METALMECANICOS SAS | C91: total | D91: Mandato | E91: Cartagena De Indias | F91: Valor a Pagar | G91: =G90+G89 -> 4092060.8 | H91: =VLOOKUP(B91,'Abril Data'!A:D,4,FALSE) -> UESP1774
A92: Servicios Industriales Y Metalmecanicos Sas | B92: SERVICIOS INDUSTRIALES Y METALMECANICOS SAS | C92: Factura | D92: Factura | F92: Administración | G92: =G91*5% -> 204603.04 | H92: =VLOOKUP(B92,'Abril Data'!A:D,4,FALSE) -> UESP1774 | I92: SERVICIOS INDUSTRIALES Y METALMECANICOS SAS
A93: Servicios Industriales Y Metalmecanicos Sas | B93: SERVICIOS INDUSTRIALES Y METALMECANICOS SAS | C93: Factura | D93: Factura | F93: Total | G93: =G92 -> 204603.04 | H93: =VLOOKUP(B93,'Abril Data'!A:D,4,FALSE) -> UESP1774 | I93: SERVICIOS INDUSTRIALES Y METALMECANICOS SAS
A94: Sociedad Educativa Ngs Sas | B94: SOCIEDAD EDUCATIVA NGS SAS | C94: Total | D94: Mandato | E94: Villavicencio | F94: Ingreso Bruto | G94: =SUMIFS('Abril Data'!C:C,'Abril Data'!A:A,B94,'Abril Data'!B:B,F94) -> 2030147.9 | H94: =VLOOKUP(B94,'Abril Data'!A:D,4,FALSE) -> UESP1779 | I94: SOCIEDAD EDUCATIVA NGS SAS | J94: =J89+1 -> 784
A95: Sociedad Educativa Ngs Sas | B95: SOCIEDAD EDUCATIVA NGS SAS | C95: total | D95: Mandato | E95: Villavicencio | F95: Interes | G95: =SUMIFS('Abril Data'!C:C,'Abril Data'!A:A,B95,'Abril Data'!B:B,F95) -> 0 | H95: =VLOOKUP(B95,'Abril Data'!A:D,4,FALSE) -> UESP1779 | I95: SOCIEDAD EDUCATIVA NGS SAS
A96: Sociedad Educativa Ngs Sas | B96: SOCIEDAD EDUCATIVA NGS SAS | C96: total | D96: Mandato | E96: Villavicencio | F96: Valor a Pagar | G96: =G95+G94 -> 2030147.9 | H96: =VLOOKUP(B96,'Abril Data'!A:D,4,FALSE) -> UESP1779
A97: Sociedad Educativa Ngs Sas | B97: SOCIEDAD EDUCATIVA NGS SAS | C97: Factura | D97: Factura | F97: Administración | G97: =G96*5% -> 101507.4 | H97: =VLOOKUP(B97,'Abril Data'!A:D,4,FALSE) -> UESP1779 | I97: SOCIEDAD EDUCATIVA NGS SAS
A98: Sociedad Educativa Ngs Sas | B98: SOCIEDAD EDUCATIVA NGS SAS | C98: Factura | D98: Factura | F98: Total | G98: =G97 -> 101507.4 | H98: =VLOOKUP(B98,'Abril Data'!A:D,4,FALSE) -> UESP1779 | I98: SOCIEDAD EDUCATIVA NGS SAS
A99: Sociedad Medica Rionegro S.A. Somer S.A. | B99: SOCIEDAD MEDICA RIONEGRO S.A. SOMER S.A. | C99: Total | D99: Mandato | E99: Rionegro | F99: Ingreso Bruto | G99: =SUMIFS('Abril Data'!C:C,'Abril Data'!A:A,B99,'Abril Data'!B:B,F99) -> 12459320 | H99: =VLOOKUP(B99,'Abril Data'!A:D,4,FALSE) -> UESP1781 | I99: SOCIEDAD MEDICA RIONEGRO S.A. SOMER S.A. | J99: =J94+1 -> 785
A100: Sociedad Medica Rionegro S.A. Somer S.A. | B100: SOCIEDAD MEDICA RIONEGRO S.A. SOMER S.A. | C100: total | D100: Mandato | E100: Rionegro | F100: Interes | G100: =SUMIFS('Abril Data'!C:C,'Abril Data'!A:A,B100,'Abril Data'!B:B,F100) -> 0 | H100: =VLOOKUP(B100,'Abril Data'!A:D,4,FALSE) -> UESP1781 | I100: SOCIEDAD MEDICA RIONEGRO S.A. SOMER S.A.
...

Sheet Abril Data
A1: Proyecto | B1: Concepto | C1: Total | D1: Factura
A2: CONGREGACIÓN DE RELIGIOSAS HIJAS DE CRISTO REY | B2: Ingreso Bruto | C2: 2402148.8 | D2: UESP1764
A3: CONGREGACIÓN DE RELIGIOSAS HIJAS DE CRISTO REY | B3: Interes | C3: 52438.59 | D3: UESP1764
A4: CONGREGACIÓN DE RELIGIOSAS HIJAS DE CRISTO REY | B4: Valor a Pagar | C4: 2454587.4 | D4: UESP1764
A5: POLIKEM S.A.S | B5: Ingreso Bruto | C5: 2075694.7 | D5: UESP1765
A6: POLIKEM S.A.S | B6: Interes | C6: 611.22 | D6: UESP1765
A7: POLIKEM S.A.S | B7: Valor a Pagar | C7: 2076305.9 | D7: UESP1765
A8: COOPERATIVA ANTIOQUEÑA DE SALUD | B8: Ingreso Bruto | C8: 2617489.7 | D8: UESP1766
A9: COOPERATIVA ANTIOQUEÑA DE SALUD | B9: Interes | C9: 498227.47 | D9: UESP1766
A10: COOPERATIVA ANTIOQUEÑA DE SALUD | B10: Valor a Pagar | C10: 3115717.1 | D10: UESP1766
A11: URBANIZACION ARBOLEDA DE CASTILLA PROPIEDAD HORIZONTAL | B11: Ingreso Bruto | C11: 3726141.1 | D11: UESP1767
A12: URBANIZACION ARBOLEDA DE CASTILLA PROPIEDAD HORIZONTAL | B12: Interes | C12: 46152.91 | D12: UESP1767
A13: URBANIZACION ARBOLEDA DE CASTILLA PROPIEDAD HORIZONTAL | B13: Valor a Pagar | C13: 3772294 | D13: UESP1767
... A61: SALUD VEGAS - TORRE MÉDICA - PROPIEDAD HORIZONTAL | B61: Valor a Pagar | C61: 6171088 | D61: UESP1783

Sheet Marzo Data
A1: Proyecto | B1: Concepto | C1: Total | D1: Factura
A2: POLIKEM S.A.S | B2: Ingreso Bruto | C2: 2320232.6 | D2: UESP1649
A3: POLIKEM S.A.S | B3: Interes | C3: 0 | D3: UESP1649
A4: POLIKEM S.A.S | B4: Valor a Pagar | C4: 2320232.6 | D4: UESP1649
A5: COOPERATIVA ANTIOQUEÑA DE SALUD | B5: Ingreso Bruto | C5: 2731068.5 | D5: UESP1650
A6: COOPERATIVA ANTIOQUEÑA DE SALUD | B6: Interes | C6: 452973.23 | D6: UESP1650
A7: COOPERATIVA ANTIOQUEÑA DE SALUD | B7: Valor a Pagar | C7: 3184041.7 | D7: UESP1650
A8: CONGREGACIÓN DE RELIGIOSAS HIJAS DE CRISTO REY | B8: Ingreso Bruto | C8: 2558003.3 | D8: UESP1651
A9: CONGREGACIÓN DE RELIGIOSAS HIJAS DE CRISTO REY | B9: Interes | C9: 85515.56 | D9: UESP1651
A10: CONGREGACIÓN DE RELIGIOSAS HIJAS DE CRISTO REY | B10: Valor a Pagar | C10: 2643518.9 | D10: UESP1651
A11: URBANIZACION ARBOLEDA DE CASTILLA PROPIEDAD HORIZONTAL | B11: Ingreso Bruto | C11: 3741553.4 | D11: UESP1652
A12: URBANIZACION ARBOLEDA DE CASTILLA PROPIEDAD HORIZONTAL | B12: Interes | C12: 46332.87 | D12: UESP1652
A13: URBANIZACION ARBOLEDA DE CASTILLA PROPIEDAD HORIZONTAL | B13: Valor a Pagar | C13: 3787886.2 | D13: UESP1652
... A70: DAIRY PARTNERS AMERICAS MANUFACTURING COLOMBIA LTDA | B70: Valor a Pagar | C70: 94294621 | D70: UESP1671

Sheet MAPEO
G2: DEDITO | I2: CREDITO
F3: DESCRIPCION | G3: CUENTA | H3: ASOCIADO | I3: CUENTA | J3: ASOCIADO
E4: Ingreso Bruto | F4: EN MAYUSCULA (MES + AÑO + "PROY" + NOMBRE DEL PROYECTO + CONCEPTO | G4: 28150508 | H4: ID ODOO | I4: 28150508 | J4: SUNO ACTIVOS SOSTENIBLES S.A.S
E5: Interes | F5: EN MAYUSCULA (MES + AÑO + "PROY" + NOMBRE DEL PROYECTO + CONCEPTO | G5: 28150502 | H5: ID ODOO | I5: 28150508 | J5: SUNO ACTIVOS SOSTENIBLES S.A.S
E6: Retención en la fuente | F6: EN MAYUSCULA (MES + AÑO + "PROY" + NOMBRE DEL PROYECTO + CONCEPTO | G6: 28150508 | H6: SUNO ACTIVOS SOSTENIBLES S.A.S | I6: 13050505 | J6: ID ODOO
E7: ICA | F7: EN MAYUSCULA (MES + AÑO + "PROY" + NOMBRE DEL PROYECTO + CONCEPTO | G7: 28150508 | H7: SUNO ACTIVOS SOSTENIBLES S.A.S | I7: 13050505 | J7: ID ODOO

Sheet Febrero Data
A1: Proyecto | B1: Concepto | C1: Total | D1: Factura
A2: POLIKEM S.A.S | B2: Ingreso Bruto | C2: 2150266 | D2: UESP1517
A3: POLIKEM S.A.S | B3: Interes | C3: 0 | D3: UESP1517
A4: POLIKEM S.A.S | B4: Valor a Pagar | C4: 2150266 | D4: UESP1517
A5: COOPERATIVA ANTIOQUEÑA DE SALUD | B5: Ingreso Bruto | C5: 1992216 | D5: UESP1518
A6: COOPERATIVA ANTIOQUEÑA DE SALUD | B6: Interes | C6: 367512.7 | D6: UESP1518
A7: COOPERATIVA ANTIOQUEÑA DE SALUD | B7: Valor a Pagar | C7: 2359728 | D7: UESP1518
A8: CONGREGACIÓN DE RELIGIOSAS HIJAS DE CRISTO REY | B8: Ingreso Bruto | C8: 2244451 | D8: UESP1519
A9: CONGREGACIÓN DE RELIGIOSAS HIJAS DE CRISTO REY | B9: Interes | C9: 53672.5 | D9: UESP1519
A10: CONGREGACIÓN DE RELIGIOSAS HIJAS DE CRISTO REY | B10: Valor a Pagar | C10: 2298124 | D10: UESP1519
A11: URBANIZACION ARBOLEDA DE CASTILLA PROPIEDAD HORIZONTAL | B11: Ingreso Bruto | C11: 2605612 | D11: UESP1520
A12: URBANIZACION ARBOLEDA DE CASTILLA PROPIEDAD HORIZONTAL | B12: Interes | C12: 29819.04 | D12: UESP1520
A13: URBANIZACION ARBOLEDA DE CASTILLA PROPIEDAD HORIZONTAL | B13: Valor a Pagar | C13: 2635431 | D13: UESP1520
... A66: CONJUNTO LAURELES CAMPESTRE ETAPAS I II Y III | B66: Interes | C66: 171219.46 | D66: UESP1539
A67: CONJUNTO LAURELES CAMPESTRE ETAPAS I II Y III | B67: Valor a Pagar | C67: =C65+C66 -> 11732924 | D67: UESP1539

Sheet Enero Data
A1: Proyecto | B1: Concepto | C1: Total | D1: Factura
A2: COOPERATIVA ANTIOQUEÑA DE SALUD | B2: Ingreso Bruto | C2: 2095940.3 | D2: UESP1415
A3: COOPERATIVA ANTIOQUEÑA DE SALUD | B3: Interes | C3: 348261.03 | D3: UESP1415
A4: COOPERATIVA ANTIOQUEÑA DE SALUD | B4: Valor a Pagar | C4: 2444201.3 | D4: UESP1415
A5: CONGREGACIÓN DE RELIGIOSAS HIJAS DE CRISTO REY | B5: Ingreso Bruto | C5: 2372766.8 | D5: UESP1416
A6: CONGREGACIÓN DE RELIGIOSAS HIJAS DE CRISTO REY | B6: Interes | C6: 32062.42 | D6: UESP1416
A7: CONGREGACIÓN DE RELIGIOSAS HIJAS DE CRISTO REY | B7: Valor a Pagar | C7: 2404829.2 | D7: UESP1416
A8: URBANIZACION ARBOLEDA DE CASTILLA PROPIEDAD HORIZONTAL | B8: Ingreso Bruto | C8: 3087340.2 | D8: UESP1435
A9: URBANIZACION ARBOLEDA DE CASTILLA PROPIEDAD HORIZONTAL | B9: Interes | C9: 50874.54 | D9: UESP1435
A10: URBANIZACION ARBOLEDA DE CASTILLA PROPIEDAD HORIZONTAL | B10: Valor a Pagar | C10: =C8+C9 -> 3138214.7 | D10: UESP1435
A11: SOCIEDAD MEDICA RIONEGRO S.A. SOMER S.A. | B11: Ingreso Bruto | C11: 11294700 | D11: UESP1436
A12: SOCIEDAD MEDICA RIONEGRO S.A. SOMER S.A. | B12: Interes | C12: 0 | D12: UESP1436
A13: SOCIEDAD MEDICA RIONEGRO S.A. SOMER S.A. | B13: Valor a Pagar | C13: =C11+C12 -> 11294700 | D13: UESP1436
A14: ECOIMAGEN SALUD S.A.S | B14: Ingreso Bruto | C14: 1301979.6 | D14: UESP1419
A15: ECOIMAGEN SALUD S.A.S | B15: Interes | C15: 24394.91 | D15: UESP1419
A16: ECOIMAGEN SALUD S.A.S | B16: Valor a Pagar | C16: 1326374.6 | D16: UESP1419
A17: CONDOMINIO ACANTO Ρ. Η | B17: Ingreso Bruto | C17: 4209142.2 | D17: UESP1420
A18: CONDOMINIO ACANTO Ρ. Η | B18: Interes | C18: 0 | D18: UESP1420
A19: CONDOMINIO ACANTO Ρ. Η | B19: Valor a Pagar | C19: 4209142.2 | D19: UESP1420
A20: EDIFICIO TORRE ALMAGRAN PROPIEDAD HORIZONTAL | B20: Ingreso Bruto | C20: 1484963.5 | D20: UESP1421
A21: EDIFICIO TORRE ALMAGRAN PROPIEDAD HORIZONTAL | B21: Interes | C21: 1988.36 | D21: UESP1421
A22: EDIFICIO TORRE ALMAGRAN PROPIEDAD HORIZONTAL | B22: Valor a Pagar | C22: 1486951.8 | D22: UESP1421
A23: ALMACEN AMC SAS | B23: Ingreso Bruto | C23: 4095983.8 | D23: UESP1422
A24: ALMACEN AMC SAS | B24: Interes | C24: 88460.21 | D24: UESP1422
A25: ALMACEN AMC SAS | B25: Valor a Pagar | C25: 4184444 | D25: UESP1422
... A54: POLIKEM S.A.S | B54: Interes | C54: 625.52 | D54: UESP1432
A55: POLIKEM S.A.S | B55: Valor a Pagar | C55: =C54+C53 -> 2035415.7 | D55: UESP1432
A56: CENTRAL DE MADERAS G&S S.A.S. | B56: Ingreso Bruto | C56: 2716852.4 | D56: UESP1433
A57: CENTRAL DE MADERAS G&S S.A.S. | B57: Interes | C57: 4102.6 | D57: UESP1433
A58: CENTRAL DE MADERAS G&S S.A.S. | B58: Valor a Pagar | C58: 2720955 | D58: UESP1433
